Workbook

Sheet >> Execution

Sheet 📍Bảng confirm EXT - 2404 Quota
A1: PMAX | C.P.GROUP VIETNAM - QUOTATION FOR INFLUENCERS BOOKING SERVICE
A3: No | B3: Booking | C3: Unit | D3: Outcomes Quantity | E3: Total Cost
C4: KOL & Community | D4: =sum(D5,D7,D9:D10) -> 37 | E4: =Sum(E5:E11) -> 616000000
A5: 1 | B5: =A20 -> FOODY REVIEWER | C5: Video Post | D5: =K20 -> 9 | E5: =Q20 -> 217000000
C6: SDHA | D6: =K21 -> 9
A7: 2 | B7: =A50 -> FOODY UGC | C7: Video Post | D7: =K50 -> 18 | E7: =Q50 -> 163000000
C8: SDHA | D8: =K51 -> 18
A9: 3 | B9: =A114 -> FOODY COMMUNITY | C9: Video Post | D9: =K115 -> 5 | E9: =Q114 -> 216000000
C10: Photo Post | D10: =K114 -> 5
A11: 4 | B11: =A126 -> SEEDING PACKAGE | C11: Comment | D11: =K127 -> 2000 | E11: =Q126 -> 20000000
B12: Total (exl AF, exl VAT) | E12: =E4 -> 616000000
B13: AF | D13: 0.12 | E13: =E12*D13 -> 73920000
B14: Total (inc AF, exl VAT) | E14: =sum(E12:E13) -> 689920000
B15: Total (inc AF, VAT) | E15: =E14*1.08 -> 745113600
A19: No. | B19: Name | C19: Platform | D19: Followers | E19: Tiers | F19: Link | G19: Location | H19: SOW | I19: Pick | J19: Unit | K19: Outcomes Quantity | L19: Unit cost ( Estimated) | M19: KPI View | N19: KPI Engagement | O19: CPV | P19: CPE | Q19: Total cost | R19: Rationale | S19: NOTE | T19: PMAX' NOTE | U19: Vote
A20: FOODY REVIEWER | J20: Video Post | K20: =SUMIFS(K22:K49,J22:J49,"Video Post") -> 9 | M20: =sumif($I$22:$I$49,"TRUE",M22:M49) -> 710000 | N20: =sumif($I$22:$I$49,"TRUE",N22:N49) -> 28700 | Q20: =sum(Q22:Q49) -> 217000000
J21: SDHA | K21: =SUMIFS(K22:K49,J22:J49,"Tháng") -> 9
A22: Confirmed | B22: Thắng Lợi | C22: Tiktok | D22: 426.5K | E22: Micro | F22: Link | G22: Đồng Nai | H22: Sản xuất và đăng tải 01 Tiktok Video Review sản phẩm tại điểm bán Five Star Kiosk, theo định hướng nội dung của nhãn hàng - Thời lượng: 60-120s - Chất lượng: phù hợp điện thoại - Địa điểm: tại các Five Star Kiosk ở Tp. HCM Map Five Star Kiosk: Link | I22: TRUE | J22: Video Post | K22: =if(I22=True,1,if(I22=False,0)) -> 1 | L22: 16000000 | M22: 50000 | N22: 3000 | O22: =IFERROR(Q22/M22,"-") -> 320 | P22: =IFERROR(Q22/N22,"-") -> 5333.3333 | Q22: =iferror(L22*K22,"-") -> 16000000 | R22: Giới thiệu Profile Food/lifestyle reviewer có quy mô khá lớn; Tệp khán giả đại chúng, thiên về người trẻ xem TikTok để tìm quán, tìm món, tìm địa điểm vui cuối tuần; phù hợp cho nhóm người xem cần nội dung nhanh, dễ hiểu, quyết định thử món nhanh. Lý do phù hợp Đây là gương mặt phù hợp cho mục tiêu độ phủ. Với nền tảng follower/like lớn, Thắng Lợi có khả năng giúp Fivestar review món gà rán theo kiểu mass-friendly, dễ viral, dễ kéo reach; đồng thời vẫn bám đúng territory ăn uống/quán xá. | S22: Review khá đa dạng, từ các nhà hàng cao cấp đến các món nướng vỉa hè -> audience target khá dàn trải ER cao (6%) | U22: Confirm
H23: 01 tháng Sử dụng hình ảnh không độc quyền trên digital only *Bao gồm: Code Ads và reup kênh brand có chạy quảng cáo | I23: TRUE | J23: Tháng | K23: =if(I23=True,1,if(I23=False,0)) -> 1 | L23: 8000000 | M23: 0 | N23: 0 | O23: =IFERROR(Q23/M23,"-") -> - | P23: =IFERROR(Q23/N23,"-") -> - | Q23: =iferror(L23*K23,"-") -> 8000000
A24: Confirmed | B24: Lulu Review | C24: Tiktok | D24: 336.4K | E24: Micro | F24: Link | G24: Hồ Chí Minh | H24: Sản xuất và đăng tải 01 Tiktok Video Review sản phẩm tại điểm bán Five Star Kiosk, theo định hướng nội dung của nhãn hàng - Thời lượng: 60-120s - Chất lượng: phù hợp điện thoại - Địa điểm: tại các Five Star Kiosk ở Tp. HCM Map Five Star Kiosk: Link | I24: TRUE | J24: Video Post | K24: =if(I24=True,1,if(I24=False,0)) -> 1 | L24: 12000000 | M24: 100000 | N24: 3000 | O24: =IFERROR(Q24/M24,"-") -> 120 | P24: =IFERROR(Q24/N24,"-") -> 4000 | Q24: =iferror(L24*K24,"-") -> 12000000 | R24: Giới thiệu Profile Creator thiên về travel – food, creator làm các clip trải nghiệm ăn uống/điểm đến. Khán giả thích kết hợp ăn uống + đi chơi + khám phá địa điểm, thiên về nhóm trẻ thích lifestyle/travel nội địa. Audience này phù hợp với Fivestar khi thương hiệu muốn mở rộng từ “món ăn” sang “điểm chạm trong hành trình vui chơi” Lý do phù hợp Lulu phù hợp để kể Fivestar theo góc đi đâu ăn đó / tiện ghé – tiện trải nghiệm, không chỉ review món gà rán mà còn gắn với hành trình đi chơi, đi ăn, check-in. Điều này hợp với các hoạt động activation hoặc ghé cửa hàng trong hành trình khám phá thành phố | S24: Review khá đa dạng các lĩnh vực -> audience target khá dàn trải | U24: Confirm
H25: 01 tháng Sử dụng hình ảnh không độc quyền trên digital only *Bao gồm: Code Ads và reup kênh brand có chạy quảng cáo | I25: TRUE | J25: Tháng | K25: =if(I25=True,1,if(I25=False,0)) -> 1 | L25: 6000000 | M25: 0 | N25: 0 | O25: =IFERROR(Q25/M25,"-") -> - | P25: =IFERROR(Q25/N25,"-") -> - | Q25: =iferror(L25*K25,"-") -> 6000000
A26: Confirmed | B26: Hello Lập Đây | C26: Tiktok | D26: 260K | E26: Micro | F26: Link | G26: Hồ Chí Minh | H26: Sản xuất và đăng tải 01 Tiktok Video Review sản phẩm tại điểm bán Five Star Kiosk, theo định hướng nội dung của nhãn hàng - Thời lượng: 60-120s - Chất lượng: phù hợp điện thoại - Địa điểm: tại các Five Star Kiosk ở Tp. HCM Map Five Star Kiosk: Link | I26: TRUE | J26: Video Post | K26: =if(I26=True,1,if(I26=False,0)) -> 1 | L26: 20000000 | M26: 130000 | N26: 4000 | O26: =IFERROR(Q26/M26,"-") -> 153.84615 | P26: =IFERROR(Q26/N26,"-") -> 5000 | Q26: =iferror(L26*K26,"-") -> 20000000 | R26: Giới thiệu Profile Creator về du lịch và đời sống, ăn uống , đồng thời Lập cũng nói rõ mình “thích ăn ngon thích trải nghiệm”. Khán giả trẻ yêu thích trải nghiệm đời sống, du lịch ngắn ngày, quán xá và những nội dung nhẹ nhàng dễ xem; phù hợp với nhóm người xem thích recommendation kiểu “đi đâu – ăn gì – chơi gì” Lý do phù hợp Lập không phải pure foodie 100%, nhưng lại rất hợp cho tuyến review trải nghiệm thương hiệu: ghé cửa hàng, ăn thử món, tham gia hoạt động brand, kể cảm xúc theo kiểu gần gũi và vui vẻ. Đây là kiểu creator giúp Fivestar không chỉ bán món mà còn bán trải nghiệm ghé ăn – đi chơi – thư giãn. | S26: Tuyến content dàn trải nhưng khá tự nhiên | U26: Confirm
H27: 01 tháng Sử dụng hình ảnh không độc quyền trên digital only *Bao gồm: Code Ads và reup kênh brand có chạy quảng cáo | I27: TRUE | J27: Tháng | K27: =if(I27=True,1,if(I27=False,0)) -> 1 | L27: 13000000 | M27: 0 | N27: 0 | O27: =IFERROR(Q27/M27,"-") -> - | P27: =IFERROR(Q27/N27,"-") -> - | Q27: =iferror(L27*K27,"-") -> 13000000
A28: Confirmed | B28: Huyền Nhi | C28: Tiktok | D28: 118.1K | E28: Micro | F28: Link | G28: Hồ Chí Minh | H28: Sản xuất và đăng tải 01 Tiktok Video Review sản phẩm tại điểm bán Five Star Kiosk, theo định hướng nội dung của nhãn hàng - Thời lượng: 60-120s - Chất lượng: phù hợp điện thoại - Địa điểm: tại các Five Star Kiosk ở Tp. HCM Map Five Star Kiosk: Link | I28: TRUE | J28: Video Post | K28: =if(I28=True,1,if(I28=False,0)) -> 1 | L28: 8000000 | M28: 30000 | N28: 1200 | O28: =IFERROR(Q28/M28,"-") -> 266.66667 | P28: =IFERROR(Q28/N28,"-") -> 6666.6667 | Q28: =iferror(L28*K28,"-") -> 8000000 | R28: Giới thiệu Profile Creator thiên về food/lifestyle ở quy mô nhỏ hơn, cũng như từng đăng nội dung liên quan KFC tầm 1 năm trước. Tệp người xem trẻ, thiên nữ, quan tâm quán xá đẹp, món ngon dễ hẹn bạn bè hoặc đi hẹn hò; phù hợp cho nhóm cần cảm hứng “thấy hợp là đi thử”. Lý do phù hợp Huyền Nhi phù hợp cho tuyến micro/nano KOC nếu brand cần cảm giác review thật, mềm, nữ tính và gần gũi. Creator này hợp với các nội dung thử món, đi ăn cùng bạn bè, hoặc review cửa hàng theo vibe nhẹ nhàng, dễ tin. | S28: ER ổn (4) Giá phù hợp với KPI Nội dung ẩm thực là chính | U28: Confirm
H29: 01 tháng Sử dụng hình ảnh không độc quyền trên digital only *Bao gồm: Code Ads và reup kênh brand có chạy quảng cáo | I29: TRUE | J29: Tháng | K29: =if(I29=True,1,if(I29=False,0)) -> 1 | L29: 4000000 | M29: 0 | N29: 0 | O29: =IFERROR(Q29/M29,"-") -> - | P29: =IFERROR(Q29/N29,"-") -> - | Q29: =iferror(L29*K29,"-") -> 4000000
A30: Confirmed | B30: Thư Bonny | C30: Tiktok | D30: 114.7K | E30: Micro | F30: Link | G30: Hồ Chí Minh | H30: Sản xuất và đăng tải 01 Tiktok Video Review sản phẩm tại điểm bán Five Star Kiosk, theo định hướng nội dung của nhãn hàng - Thời lượng: 60-120s - Chất lượng: phù hợp điện thoại - Địa điểm: tại các Five Star Kiosk ở Tp. HCM Map Five Star Kiosk: Link | I30: TRUE | J30: Video Post | K30: =if(I30=True,1,if(I30=False,0)) -> 1 | L30: 10000000 | M30: 50000 | N30: 3000 | O30: =IFERROR(Q30/M30,"-") -> 200 | P30: =IFERROR(Q30/N30,"-") -> 3333.3333 | Q30: =iferror(L30*K30,"-") -> 10000000 | R30: Giới thiệu Profile Creator quy mô nhỏ, nội dung xoay quanh food review tại Sài Gòn như hủ tiếu Nam Vang, món mới, quán ăn. Tệp khán giả địa phương quan tâm quán ăn Sài Gòn và các gợi ý món ăn thường ngày; phù hợp cho mục tiêu phủ thêm lớp recommendation thực tế ở nhóm niche audience. Lý do phù hợp Thư Bonny hợp cho tuyến nano KOC seeding hơn là lead KOL. Điểm cộng là cảm giác gần gũi, ít “quảng cáo hóa”, phù hợp nếu Fivestar muốn có thêm lớp nội dung review chân thật, đời thường, dễ tạo niềm tin ở nhóm người xem nhỏ nhưng sát nhu cầu ăn uống hàng ngày. | S30: ER cao KPI ok Review khá đa dạng | U30: Confirm
H31: 01 tháng Sử dụng hình ảnh không độc quyền trên digital only *Bao gồm: Code Ads và reup kênh brand có chạy quảng cáo | I31: TRUE | J31: Tháng | K31: =if(I31=True,1,if(I31=False,0)) -> 1 | L31: 5000000 | M31: 0 | N31: 0 | O31: =IFERROR(Q31/M31,"-") -> - | P31: =IFERROR(Q31/N31,"-") -> - | Q31: =iferror(L31*K31,"-") -> 5000000
A32: Considering | B32: Nuchuu nè | C32: Tiktok | D32: 756K | E32: Micro | F32: Link | G32: Hồ Chí Minh | H32: Sản xuất và đăng tải 01 Tiktok Video Review sản phẩm tại điểm bán Five Star Kiosk, theo định hướng nội dung của nhãn hàng - Thời lượng: 60-120s - Chất lượng: phù hợp điện thoại - Địa điểm: tại các Five Star Kiosk ở Tp. HCM Map Five Star Kiosk: Link | I32: TRUE | J32: Video Post | K32: =if(I32=True,1,if(I32=False,0)) -> 1 | L32: 30000000 | M32: 120000 | N32: 4500 | O32: =IFERROR(Q32/M32,"-") -> 250 | P32: =IFERROR(Q32/N32,"-") -> 6666.6667 | Q32: =iferror(L32*K32,"-") -> 30000000 | R32: Giới thiệu Profile Food reviewer theo hướng gần gũi, hay làm format “cầm 100 cành ăn sập…” và review quán/điểm ăn uống thực tế; phần mô tả YouTube cũng cho thấy Nuchuu chia sẻ công thức nấu ăn và “review thật lòng” về thực phẩm, quán ăn. Kênh thu hút nhóm khán giả trẻ thích săn quán, thích nội dung ăn uống đời thường, ưu tiên món ngon dễ thử, dễ rủ hội bạn đi cùng; phù hợp với tệp Gen Z–young millennials mê khám phá địa điểm ăn uống phổ thông. Lý do phù hợp Nuchuu hợp để review gà rán theo góc độ “ngon thật – dễ ăn – dễ chốt kèo” vì nội dung thiên về trải nghiệm thật, món ăn phổ thông, dễ tạo cảm giác thèm ăn ngay. Format săn món ngon giá hợp lý cũng match với tinh thần tiếp cận rộng, tiện ăn, tiện rủ bạn bè của Fivestar. | S32: Có review quán ăn vặt của chủ kênh vào 23/1 (có món gà) | T32: PMAX Updated KPI | U32: Confirm
H33: 01 tháng Sử dụng hình ảnh không độc quyền trên digital only *Bao gồm: Code Ads và reup kênh brand có chạy quảng cáo | I33: TRUE | J33: Tháng | K33: =if(I33=True,1,if(I33=False,0)) -> 1 | L33: 17000000 | M33: 0 | N33: 0 | O33: - | P33: - | Q33: =iferror(L33*K33,"-") -> 17000000
A34: Considering | B34: Lên ký Cùng Khoa | C34: Tiktok | D34: 726.4K | E34: Micro | F34: Link | G34: Hồ Chí Minh | H34: Sản xuất và đăng tải 01 Tiktok Video Review sản phẩm tại điểm bán Five Star Kiosk, theo định hướng nội dung của nhãn hàng - Thời lượng: 60-120s - Chất lượng: phù hợp điện thoại - Địa điểm: tại các Five Star Kiosk ở Tp. HCM Map Five Star Kiosk: Link | I34: FALSE | J34: Video Post | K34: =if(I34=True,1,if(I34=False,0)) -> 0 | L34: 22000000 | M34: 100000 | N34: 3500 | O34: =IFERROR(Q34/M34,"-") -> 0 | P34: =IFERROR(Q34/N34,"-") -> 0 | Q34: =iferror(L34*K34,"-") -> 0 | R34: Giới thiệu Profile Creator food khá rõ nét, kênh chính chủ mô tả là nơi xem “review mới nhất”; trên YouTube có các tuyến nội dung như review quán ăn Sài Gòn, review hot trend, món miền Tây, công thức của mẹ. Tệp người xem thích cập nhật quán hot, món hot trend, món ăn đường phố/quen thuộc; phù hợp với khán giả trẻ thích thử món mới nhưng vẫn ưu tiên trải nghiệm dễ tiếp cận, giá không quá cao. Lý do phù hợp Khoa phù hợp để kéo review món + review điểm bán + bắt trend món mới. Nội dung kênh vừa có tính khám phá vừa có độ “đời”, nên dễ kể câu chuyện Fivestar không chỉ là gà rán mà còn là điểm dừng chân ăn nhanh, ngon, dễ ghé. | S34: ER hơi thấp (2%), cost per engagement cao | T34: PMAX Updated KPI | U34: Không phù hợp
H35: 01 tháng Sử dụng hình ảnh không độc quyền trên digital only *Bao gồm: Code Ads và reup kênh brand có chạy quảng cáo | I35: FALSE | J35: Tháng | K35: =if(I35=True,1,if(I35=False,0)) -> 0 | L35: 13000000 | M35: 0 | N35: 0 | O35: =IFERROR(Q35/M35,"-") -> - | P35: =IFERROR(Q35/N35,"-") -> - | Q35: =iferror(L35*K35,"-") -> 0
A36: Considering | B36: Ăn ngon cùng Puu | C36: Tiktok | D36: 345.4K | E36: Micro | F36: Link | G36: Hồ Chí Minh | H36: Sản xuất và đăng tải 01 Tiktok Video Review sản phẩm tại điểm bán Five Star Kiosk, theo định hướng nội dung của nhãn hàng - Thời lượng: 60-120s - Chất lượng: phù hợp điện thoại - Địa điểm: tại các Five Star Kiosk ở Tp. HCM Map Five Star Kiosk: Link | I36: TRUE | J36: Video Post | K36: =if(I36=True,1,if(I36=False,0)) -> 1 | L36: 17000000 | M36: 100000 | N36: 4000 | O36: =IFERROR(Q36/M36,"-") -> 170 | P36: =IFERROR(Q36/N36,"-") -> 4250 | Q36: =iferror(L36*K36,"-") -> 17000000 | R36: Giới thiệu Profile Kênh food review; Tệp người xem chủ động tìm nội dung ăn uống, ưu tiên recommendation nhanh về món/quán; phù hợp với nhóm khán giả trẻ mê food content, dễ bị tác động bởi visual món ăn và reaction khi ăn Lý do phù hợp Puu phù hợp với tuyến review món ăn trực diện, tập trung vào cảm nhận vị, độ hấp dẫn và trải nghiệm ăn thực tế. Với tên kênh và định vị khá rõ là “ăn ngon”, creator này match tốt với brief cần làm người xem thèm món ngay khi xem | S36: KPI View cao ER hơi thấp (2,67%) | T36: PMAX Updated KPI | U36: Confirm
H37: 01 tháng Sử dụng hình ảnh không độc quyền trên digital only *Bao gồm: Code Ads và reup kênh brand có chạy quảng cáo | I37: TRUE | J37: Tháng | K37: =if(I37=True,1,if(I37=False,0)) -> 1 | L37: 7000000 | M37: 0 | N37: 0 | O37: =IFERROR(Q37/M37,"-") -> - | P37: =IFERROR(Q37/N37,"-") -> - | Q37: =iferror(L37*K37,"-") -> 7000000
A38: Considering | B38: Thồn | C38: Tiktok | D38: 197.2K | E38: Micro | F38: Link | G38: Hồ Chí Minh | H38: Sản xuất và đăng tải 01 Tiktok Video Review sản phẩm tại điểm bán Five Star Kiosk, theo định hướng nội dung của nhãn hàng - Thời lượng: 60-120s - Chất lượng: phù hợp điện thoại - Địa điểm: tại các Five Star Kiosk ở Tp. HCM Map Five Star Kiosk: Link | I38: FALSE | J38: Video Post | K38: =if(I38=True,1,if(I38=False,0)) -> 0 | L38: 17000000 | M38: 60000 | N38: 2500 | O38: =IFERROR(Q38/M38,"-") -> 0 | P38: =IFERROR(Q38/N38,"-") -> 0 | Q38: =iferror(L38*K38,"-") -> 0 | R38: Giới thiệu Profile Creator food/travel có cá tính rõ, . Nhóm khán giả thích food content có cá tính, vừa xem để lấy gợi ý quán/món vừa xem vì persona creator thú vị; phù hợp với tệp trẻ thành thị thích nội dung review vui, dễ nhớ, có chút giải trí. Lý do phù hợp Điểm mạnh của Thồn là persona nhớ mặt nhớ giọng, tạo cảm giác review có màu riêng, không bị nhạt. Với Fivestar, creator này có thể làm nội dung gà rán theo hướng thử thật – reaction thật – kể chuyện có nét riêng, tăng độ ghi nhớ thương hiệu hơn kiểu review thông tin thuần túy | S38: ER cao nhưng KPI Engagement khá thấp ( chỉ 2000) -> đẩy cost per E lên cao Review khá đa dạng, | T38: PMAX Updated KPI | U38: Không phù hợp
H39: 01 tháng Sử dụng hình ảnh không độc quyền trên digital only *Bao gồm: Code Ads và reup kênh brand có chạy quảng cáo | I39: FALSE | J39: Tháng | K39: =if(I39=True,1,if(I39=False,0)) -> 0 | L39: 10000000 | M39: 0 | N39: 0 | O39: =IFERROR(Q39/M39,"-") -> - | P39: =IFERROR(Q39/N39,"-") -> - | Q39: =iferror(L39*K39,"-") -> 0
A40: New Propose | B40: Đi Ăn Chưa 🍪 | C40: Tiktok | D40: 289.3K | E40: Micro | F40: https://www.tiktok.com/@bobiengan?_t=ZS-8tu0m1Vyokq&_r=1u0odLK9R3&_r=1 | G40: Hà Nội | H40: Sản xuất và đăng tải 01 Tiktok Video Review sản phẩm tại điểm bán Five Star Kiosk, theo định hướng nội dung của nhãn hàng - Thời lượng: 60-120s - Chất lượng: phù hợp điện thoại - Địa điểm: tại các Five Star Kiosk ở Tp. HCM Map Five Star Kiosk: Link | I40: TRUE | J40: Video Post | K40: =if(I40=True,1,if(I40=False,0)) -> 1 | L40: 15000000 | M40: 65000 | N40: 3000 | O40: =IFERROR(Q40/M40,"-") -> 230.76923 | P40: =IFERROR(Q40/N40,"-") -> 5000 | Q40: =iferror(L40*K40,"-") -> 15000000 | R40: Giới thiệu Profile Kênh food review có định vị rõ về ăn uống, dễ tạo cảm giác rủ rê và kích thích người xem đi ăn ngay. Tên kênh mang tính call-to-action tự nhiên, phù hợp với nhóm khán giả chủ động tìm recommendation món/quán, thích nội dung review nhanh, visual ngon mắt và reaction thực tế. Lý do phù hợp Đi Ăn Chưa phù hợp để truyền tải Fivestar như một lựa chọn ăn uống tiện, ngon và dễ chốt kèo. Tinh thần “đi ăn chưa” match tốt với thông điệp rủ bạn bè cùng ăn gà rán, giúp nội dung brand trở nên tự nhiên, gần gũi và có khả năng kích thích hành động thử món. | U40: Confirm
H41: 01 tháng Sử dụng hình ảnh không độc quyền trên digital only *Bao gồm: Code Ads và reup kênh brand có chạy quảng cáo | I41: TRUE | J41: Tháng | K41: =if(I41=True,1,if(I41=False,0)) -> 1 | L41: 4000000 | M41: 0 | N41: 0 | O41: =IFERROR(Q41/M41,"-") -> - | P41: =IFERROR(Q41/N41,"-") -> - | Q41: =iferror(L41*K41,"-") -> 4000000
A42: Brand Propose | B42: A dinosaur in the kitchen | C42: Tiktok | D42: 294.8K | E42: Micro | F42: https://www.tiktok.com/@phamtrang.2401 | G42: Hà Nội | H42: Sản xuất và đăng tải 01 Tiktok Video Review sản phẩm tại điểm bán Five Star Kiosk, theo định hướng nội dung của nhãn hàng - Thời lượng: 60-120s - Chất lượng: phù hợp điện thoại - Địa điểm: tại các Five Star Kiosk ở Tp. HCM Map Five Star Kiosk: Link | I42: TRUE | J42: Video Post | K42: =if(I42=True,1,if(I42=False,0)) -> 1 | L42: 19000000 | M42: 65000 | N42: 3000 | O42: =IFERROR(Q42/M42,"-") -> 292.30769 | P42: =IFERROR(Q42/N42,"-") -> 6333.3333 | Q42: =iferror(L42*K42,"-") -> 19000000 | R42: Giới thiệu Profile Creator lifestyle/food nhẹ nhàng, nội dung mang tính daily life, trải nghiệm đa dạng món ăn Phong cách quay đẹp, nội dung lôi cuốn người xe và có tệp người xem thích vibe chill, nội dung dễ xem – dễ áp dụng. Lý do phù hợp Phù hợp lồng ghép Fivestar vào context ăn uống hằng ngày . Tăng cảm giác thương hiệu gần gũi, dễ trở thành lựa chọn quen thuộc. | U42: Confirm
H43: 01 tháng Sử dụng hình ảnh không độc quyền trên digital only *Bao gồm: Code Ads và reup kênh brand có chạy quảng cáo | I43: TRUE | J43: Tháng | K43: =if(I43=True,1,if(I43=False,0)) -> 1 | L43: 6000000 | M43: 0 | N43: 0 | O43: =IFERROR(Q43/M43,"-") -> - | P43: =IFERROR(Q43/N43,"-") -> - | Q43: =iferror(L43*K43,"-") -> 6000000
A44: Brand Propose | B44: Ăn Sập Hà Nội | C44: Tiktok | D44: 1.5M | E44: Macro | F44: https://www.tiktok.com/@ansaphanoi | G44: Hà Nội | H44: Sản xuất và đăng tải 01 Tiktok Video Review sản phẩm tại điểm bán Five Star Kiosk, theo định hướng nội dung của nhãn hàng - Thời lượng: 60-120s - Chất lượng: phù hợp điện thoại - Địa điểm: tại các Five Star Kiosk ở Tp. HCM Map Five Star Kiosk: Link | I44: FALSE | J44: Video Post | K44: =if(I44=True,1,if(I44=False,0)) -> 0 | L44: 0 | M44: 0 | N44: 0 | O44: =IFERROR(Q44/M44,"-") -> - | P44: =IFERROR(Q44/N44,"-") -> - | Q44: =iferror(L44*K44,"-") -> 0 | S44: KOC không nhận job | U44: Đề xuất thêm
H45: 01 tháng Sử dụng hình ảnh không độc quyền trên digital only *Bao gồm: Code Ads và reup kênh brand có chạy quảng cáo | I45: FALSE | J45: Tháng | K45: =if(I45=True,1,if(I45=False,0)) -> 0 | L45: 0 | M45: 0 | N45: 0 | O45: =IFERROR(Q45/M45,"-") -> - | P45: =IFERROR(Q45/N45,"-") -> - | Q45: =iferror(L45*K45,"-") -> 0
A46: Brand Propose | B46: Nguyên Hí Mắt To | C46: Tiktok | D46: 629.9K | E46: Micro | F46: https://www.tiktok.com/@nguyenhimatto | G46: Hồ Chí Minh | H46: Sản xuất và đăng tải 01 Tiktok Video Review sản phẩm tại điểm bán Five Star Kiosk, theo định hướng nội dung của nhãn hàng - Thời lượng: 60-120s - Chất lượng: phù hợp điện thoại - Địa điểm: tại các Five Star Kiosk ở Tp. HCM Map Five Star Kiosk: Link | I46: FALSE | J46: Video Post | K46: =if(I46=True,1,if(I46=False,0)) -> 0 | L46: 0 | M46: 0 | N46: 0 | O46: =IFERROR(Q46/M46,"-") -> - | P46: =IFERROR(Q46/N46,"-") -> - | Q46: =iferror(L46*K46,"-") -> 0 | S46: KOC không nhận job | U46: Đề xuất thêm
H47: 01 tháng Sử dụng hình ảnh không độc quyền trên digital only *Bao gồm: Code Ads và reup kênh brand có chạy quảng cáo | I47: FALSE | J47: Tháng | K47: =if(I47=True,1,if(I47=False,0)) -> 0 | L47: 0 | M47: 0 | N47: 0 | O47: =IFERROR(Q47/M47,"-") -> - | P47: =IFERROR(Q47/N47,"-") -> - | Q47: =iferror(L47*K47,"-") -> 0
A48: Brand Propose | B48: Ninh Tito | C48: Tiktok | D48: 459.7K | E48: Micro | F48: https://www.tiktok.com/@ninhtito | G48: Hà Nội | H48: Sản xuất và đăng tải 01 Tiktok Video Review sản phẩm tại điểm bán Five Star Kiosk, theo định hướng nội dung của nhãn hàng - Thời lượng: 60-120s - Chất lượng: phù hợp điện thoại - Địa điểm: tại các Five Star Kiosk ở Tp. HCM Map Five Star Kiosk: Link | I48: FALSE | J48: Video Post | K48: =if(I48=True,1,if(I48=False,0)) -> 0 | L48: 0 | M48: 0 | N48: 0 | O48: =IFERROR(Q48/M48,"-") -> - | P48: =IFERROR(Q48/N48,"-") -> - | Q48: =iferror(L48*K48,"-") -> 0 | S48: KOC không nhận job | U48: Đề xuất thêm
H49: 01 tháng Sử dụng hình ảnh không độc quyền trên digital only *Bao gồm: Code Ads và reup kênh brand có chạy quảng cáo | I49: FALSE | J49: Tháng | K49: =if(I49=True,1,if(I49=False,0)) -> 0 | L49: 0 | M49: 0 | N49: 0 | O49: =IFERROR(Q49/M49,"-") -> - | P49: =IFERROR(Q49/N49,"-") -> - | Q49: =iferror(L49*K49,"-") -> 0
A50: FOODY UGC | J50: Video Post | K50: =SUMIFS(K53:K113,J53:J113,"Video Post") -> 18 | M50: =sumif($I$53:$I$113,"TRUE",M53:M113) -> 516500 | N50: =sumif($I$53:$I$113,"TRUE",N53:N113) -> 30000 | Q50: =sum(Q53:Q113) -> 163000000
J51: SDHA | K51: =SUMIFS(K53:K113,J53:J113,"Tháng") -> 18
A52: a | B52: TP HCM | I52: FALSE
A53: Confirm | B53: Nhà Mây | C53: Tiktok | D53: 187.9K | E53: Micro | F53: link | G53: Hồ Chí Minh | H53: Sản xuất và đăng tải 01 Tiktok Video Review sản phẩm tại điểm bán Five Star Kiosk, theo định hướng nội dung của nhãn hàng - Thời lượng: 60-120s - Chất lượng: phù hợp điện thoại - Địa điểm: tại các Five Star Kiosk ở Tp. HCM Map Five Star Kiosk: Link | I53: TRUE | J53: Video Post | K53: =if(I53=True,1,if(I53=False,0)) -> 1 | L53: 6000000 | M53: 30000 | N53: 2000 | O53: =IFERROR(Q53/M53,"-") -> 200 | P53: =IFERROR(Q53/N53,"-") -> 3000 | Q53: =iferror(L53*K53,"-") -> 6000000 | R53: Giới thiệu Profile Creator UGC thiên về food/travel/life review. Tệp người xem thích nội dung ăn uống/lối sống gần gũi, xem để lấy gợi ý thực tế cho các dịp ăn nhanh, đi chơi hoặc ghé quán. Audience phù hợp với nhóm trẻ thích recommendation kiểu chân thật, ít dàn dựng. Lý do phù hợp Nhà Mây hợp với Fivestar ở vai trò UGC review trải nghiệm thật: ghé mua gà rán, quay phản ứng ăn thật, ghi lại cảm giác “tiện – ngon – dễ chốt món” theo kiểu rất đời thường. Đây là mẫu creator giúp brand tạo cảm giác “người dùng thật đang ăn thật”, thay vì một bài booking quá quảng cáo. | S53: Kênh gia đình, có trẻ phù hợp tệp khách của FS ER cao, giá hợp lý | U53: Confirm
H54: 01 tháng Sử dụng hình ảnh không độc quyền trên digital only *Bao gồm: Code Ads và reup kênh brand có chạy quảng cáo | I54: TRUE | J54: Tháng | K54: =if(I54=True,1,if(I54=False,0)) -> 1 | L54: 2000000 | M54: 0 | N54: 0 | O54: - | P54: - | Q54: =iferror(L54*K54,"-") -> 2000000
A55: Confirm | B55: Đi chill cùng Phương phiêu | C55: Tiktok | D55: 57.7K | E55: Nano | F55: link | G55: Hồ Chí Minh | H55: Sản xuất và đăng tải 01 Tiktok Video Review sản phẩm tại điểm bán Five Star Kiosk, theo định hướng nội dung của nhãn hàng - Thời lượng: 60-120s - Chất lượng: phù hợp điện thoại - Địa điểm: tại các Five Star Kiosk ở Tp. HCM Map Five Star Kiosk: Link | I55: TRUE | J55: Video Post | K55: =if(I55=True,1,if(I55=False,0)) -> 1 | L55: 5000000 | M55: 20000 | N55: 1500 | O55: =IFERROR(Q55/M55,"-") -> 250 | P55: =IFERROR(Q55/N55,"-") -> 3333.3333 | Q55: =iferror(L55*K55,"-") -> 5000000 | R55: Giới thiệu Profile Creator theo hướng food/travel/chill experiences; dù dữ liệu public không quá nhiều, tên kênh và format self-branding cho thấy đây là kiểu creator gắn với trải nghiệm đi ăn – đi chơi – đi chill. Tệp người xem trẻ thích lifestyle nhẹ nhàng, thích gợi ý địa điểm ăn chơi cuối tuần, ưu tiên những nội dung mang mood vui – tiện – dễ bắt chước. Lý do phù hợp Phương phiêu phù hợp khi Fivestar muốn kể câu chuyện “đi chill ghé ăn”: món gà rán xuất hiện như một phần của hành trình đi chơi, đi dạo, tụ tập bạn bè. UGC kiểu này rất hợp để làm cho thương hiệu trông gần gũi, bắt nhịp sống thật của người trẻ hơn. | S55: Tệp khán giả học sinh sinh viên phù hợp ER thấp nhưng do KPI view cao -> ok | U55: Confirm
H56: 01 tháng Sử dụng hình ảnh không độc quyền trên digital only *Bao gồm: Code Ads và reup kênh brand có chạy quảng cáo | I56: TRUE | J56: Tháng | K56: =if(I56=True,1,if(I56=False,0)) -> 1 | L56: 2000000 | M56: 0 | N56: 0 | O56: =IFERROR(Q56/M56,"-") -> - | P56: =IFERROR(Q56/N56,"-") -> - | Q56: =iferror(L56*K56,"-") -> 2000000
A57: Confirm | B57: 🍊𝐕 𝐈 𝐓 𝐀 𝐌 𝐈 𝐍 𝐂🍊 | C57: Tiktok | D57: 10.1K | E57: Nano | F57: link | G57: Hồ Chí Minh | H57: Sản xuất và đăng tải 01 Tiktok Video Review sản phẩm tại điểm bán Five Star Kiosk, theo định hướng nội dung của nhãn hàng - Thời lượng: 60-120s - Chất lượng: phù hợp điện thoại - Địa điểm: tại các Five Star Kiosk ở Tp. HCM Map Five Star Kiosk: Link | I57: TRUE | J57: Video Post | K57: =if(I57=True,1,if(I57=False,0)) -> 1 | L57: 3000000 | M57: 20000 | N57: 1500 | O57: =IFERROR(Q57/M57,"-") -> 150 | P57: =IFERROR(Q57/N57,"-") -> 2000 | Q57: =iferror(L57*K57,"-") -> 3000000 | R57: Giới thiệu Profile Creator thuộc nhóm food/travel; trong post booking public, tệp khán giả trẻ xem nội dung food/travel để lấy cảm hứng đi ăn, đi chơi, săn quán. Đây là nhóm dễ chuyển đổi bằng visual món ngon và bối cảnh đời thường. Lý do phù hợp Vitamin C hợp với vai trò UGC phủ thêm lớp review tự nhiên, gần vibe người dùng thật. Với Fivestar, creator này phù hợp cho các clip ngắn kiểu “ăn thử nhanh”, “ghé quán sau giờ làm/đi chơi”, giúp thương hiệu xuất hiện tự nhiên hơn trong feed | S57: Cost ổn với KPI, quay đồ ăn khá đẹp Nội dung xoay quanh ăn uống | U57: Confirm
H58: 01 tháng Sử dụng hình ảnh không độc quyền trên digital only *Bao gồm: Code Ads và reup kênh brand có chạy quảng cáo | I58: TRUE | J58: Tháng | K58: =if(I58=True,1,if(I58=False,0)) -> 1 | L58: 2000000 | M58: 0 | N58: 0 | O58: =IFERROR(Q58/M58,"-") -> - | P58: =IFERROR(Q58/N58,"-") -> - | Q58: =iferror(L58*K58,"-") -> 2000000
A59: Considering | B59: NHÀ MOM DIỆP | C59: Tiktok | D59: 108K | E59: Micro | F59: link | G59: Hồ Chí Minh | H59: Sản xuất và đăng tải 01 Tiktok Video Review sản phẩm tại điểm bán Five Star Kiosk, theo định hướng nội dung của nhãn hàng - Thời lượng: 60-120s - Chất lượng: phù hợp điện thoại - Địa điểm: tại các Five Star Kiosk ở Tp. HCM Map Five Star Kiosk: Link | I59: FALSE | J59: Video Post | K59: =if(I59=True,1,if(I59=False,0)) -> 0 | L59: 6000000 | M59: 30000 | N59: 2000 | O59: =IFERROR(Q59/M59,"-") -> 0 | P59: =IFERROR(Q59/N59,"-") -> 0 | Q59: =iferror(L59*K59,"-") -> 0 | R59: Giới thiệu Profile Creator có định vị gắn với gia đình; Khán giả chính là nhóm mẹ trẻ, gia đình trẻ và người xem yêu thích content đời sống gia đình, ăn uống hàng ngày. Tệp này phù hợp để kéo cảm xúc “món ăn quen thuộc cho những khoảnh khắc gần gũi cùng con”. Lý do phù hợp Đây là gương mặt rất hợp để khai thác góc “mẹ mua gà cho con ăn”. So với food reviewer thông thường, Mom Diệp cho Fivestar một lớp nội dung mềm hơn: gà rán không chỉ là món ngon mà còn là khoảnh khắc gia đình nhỏ, mẹ chiều con, bữa ăn tiện mà vẫn vui. | S59: Kênh gia đình, có bé, ER thấp, giá cost khá cao so với các kênh tương tự, ít focus vào food | U59: Không phù hợp
H60: 01 tháng Sử dụng hình ảnh không độc quyền trên digital only *Bao gồm: Code Ads và reup kênh brand có chạy quảng cáo | I60: FALSE | J60: Tháng | K60: =if(I60=True,1,if(I60=False,0)) -> 0 | L60: 2000000 | M60: 0 | N60: 0 | O60: =IFERROR(Q60/M60,"-") -> - | P60: =IFERROR(Q60/N60,"-") -> - | Q60: =iferror(L60*K60,"-") -> 0
A61: Considering | B61: Chu Cao Food | C61: Tiktok | D61: 67.4K | E61: Nano | F61: Link | G61: Hồ Chí Minh | H61: Sản xuất và đăng tải 01 Tiktok Video Review sản phẩm tại điểm bán Five Star Kiosk, theo định hướng nội dung của nhãn hàng - Thời lượng: 60-120s - Chất lượng: phù hợp điện thoại - Địa điểm: tại các Five Star Kiosk ở Tp. HCM Map Five Star Kiosk: Link | I61: TRUE | J61: Video Post | K61: =if(I61=True,1,if(I61=False,0)) -> 1 | L61: 5000000 | M61: 20000 | N61: 1500 | O61: =IFERROR(Q61/M61,"-") -> 250 | P61: =IFERROR(Q61/N61,"-") -> 3333.3333 | Q61: =iferror(L61*K61,"-") -> 5000000 | R61: Giới thiệu Profile Creator UGC thiên về food/travel; kênh “chuyên review FOOD & TRAVEL”. Tệp khán giả trẻ thích xem review quán/món ngắn gọn, thiên về nhu cầu “ăn gì hôm nay”, “đi đâu ăn nhanh”, “món nào đáng thử”. Đây là nhóm rất hợp với sản phẩm tiện lợi, dễ tiếp cận như gà rán Fivestar. Lý do phù hợp Chu Cao Food phù hợp với vai trò UGC food review trực diện: tập trung vào món, vị, phần ăn, cảm giác ăn thật tại điểm bán. Với Fivestar, creator này hợp để làm các clip kiểu “ghé ăn nhanh”, “thử combo”, “review món hot” theo format ngắn, dễ xem, dễ kích thích nhu cầu ăn ngay. | S61: gần 1 tháng chưa ra video mới, chất lượng video hình ảnh âm thanh chưa thật sự tốt Giá cao so với mặt bằng Tuy nhiên đọc bình luận thấy có tệp khách hàng trung thành với kênh | U61: Confirm
H62: 01 tháng Sử dụng hình ảnh không độc quyền trên digital only *Bao gồm: Code Ads và reup kênh brand có chạy quảng cáo | I62: TRUE | J62: Tháng | K62: =if(I62=True,1,if(I62=False,0)) -> 1 | L62: 3000000 | M62: 0 | N62: 0 | O62: =IFERROR(Q62/M62,"-") -> - | P62: =IFERROR(Q62/N62,"-") -> - | Q62: =iferror(L62*K62,"-") -> 3000000
A63: Considering | B63: Hi Ân nè | C63: Tiktok | D63: 6489 | E63: Nano | F63: link | G63: Hồ Chí Minh | H63: Sản xuất và đăng tải 01 Tiktok Video Review sản phẩm tại điểm bán Five Star Kiosk, theo định hướng nội dung của nhãn hàng - Thời lượng: 60-120s - Chất lượng: phù hợp điện thoại - Địa điểm: tại các Five Star Kiosk ở Tp. HCM Map Five Star Kiosk: Link | I63: TRUE | J63: Video Post | K63: =if(I63=True,1,if(I63=False,0)) -> 1 | L63: 3000000 | M63: 15000 | N63: 1000 | O63: =IFERROR(Q63/M63,"-") -> 200 | P63: =IFERROR(Q63/N63,"-") -> 3000 | Q63: =iferror(L63*K63,"-") -> 3000000 | R63: Giới thiệu Profile Creator có định vị khá rõ là food review. Tệp người xem trẻ, theo dõi food content để cập nhật món/quán mới và quyết định đi thử nhanh; đồng thời có độ linh hoạt khu vực, phù hợp cho các nội dung phủ rộng hơn. Lý do phù hợp Hi Ân là kiểu UGC creator rất hợp với Fivestar vì content mang cảm giác người dùng thật đi ăn thật, giọng điệu tự nhiên, gần với style recommendation trên social hơn là quảng cáo. Nếu muốn clip vừa thân thiện vừa dễ tạo niềm tin, đây là lựa chọn tốt. | S63: Chủ yếu về thức ăn Giá hơi cao so với mặt bằng nếu tính ra Cost per view/Engagement | T63: PMAX Updated KPI | U63: Confirm
H64: 01 tháng Sử dụng hình ảnh không độc quyền trên digital only *Bao gồm: Code Ads và reup kênh brand có chạy quảng cáo | I64: TRUE | J64: Tháng | K64: =if(I64=True,1,if(I64=False,0)) -> 1 | L64: 2000000 | M64: 0 | N64: 0 | O64: =IFERROR(Q64/M64,"-") -> - | P64: =IFERROR(Q64/N64,"-") -> - | Q64: =iferror(L64*K64,"-") -> 2000000
A65: Brand Propose | B65: vuvicungyuhi | C65: Tiktok | D65: 82.9K | E65: Nano | F65: https://www.tiktok.com/@vuvicungyuhi | G65: Hồ Chí Minh | H65: Sản xuất và đăng tải 01 Tiktok Video Review sản phẩm tại điểm bán Five Star Kiosk, theo định hướng nội dung của nhãn hàng - Thời lượng: 60-120s - Chất lượng: phù hợp điện thoại - Địa điểm: tại các Five Star Kiosk ở Tp. HCM Map Five Star Kiosk: Link | I65: TRUE | J65: Video Post | K65: =if(I65=True,1,if(I65=False,0)) -> 1 | L65: 11000000 | M65: 46000 | N65: 2000 | O65: =IFERROR(Q65/M65,"-") -> 239.13043 | P65: =IFERROR(Q65/N65,"-") -> 5500 | Q65: =iferror(L65*K65,"-") -> 11000000 | R65: Giới thiệu Profile Creator lifestyle/food nhẹ nhàng, trải nghiệm các quán ăn đa dạng, ăn uống gần gũi. Tệp người xem thích vibe chill, nội dung dễ xem – dễ áp dụng. Lý do phù hợp Phù hợp lồng ghép Fivestar vào context ăn uống hằng ngày (ăn vặt, ăn nhanh). Tăng cảm giác thương hiệu gần gũi, dễ trở thành lựa chọn quen thuộc. | U65: Confirm
H66: 01 tháng Sử dụng hình ảnh không độc quyền trên digital only *Bao gồm: Code Ads và reup kênh brand có chạy quảng cáo | I66: TRUE | J66: Tháng | K66: =if(I66=True,1,if(I66=False,0)) -> 1 | L66: 2000000 | M66: 0 | N66: 0 | O66: =IFERROR(Q66/M66,"-") -> - | P66: =IFERROR(Q66/N66,"-") -> - | Q66: =iferror(L66*K66,"-") -> 2000000
A67: Brand Propose | B67: Koi Nam Ăng | C67: Tiktok | D67: 70.5K | E67: Nano | F67: https://www.tiktok.com/@koinamang | G67: Hồ Chí Minh | H67: Sản xuất và đăng tải 01 Tiktok Video Review sản phẩm tại điểm bán Five Star Kiosk, theo định hướng nội dung của nhãn hàng - Thời lượng: 60-120s - Chất lượng: phù hợp điện thoại - Địa điểm: tại các Five Star Kiosk ở Tp. HCM Map Five Star Kiosk: Link | I67: TRUE | J67: Video Post | K67: =if(I67=True,1,if(I67=False,0)) -> 1 | L67: 10000000 | M67: 40500 | N67: 2000 | O67: =IFERROR(Q67/M67,"-") -> 246.91358 | P67: =IFERROR(Q67/N67,"-") -> 5000 | Q67: =iferror(L67*K67,"-") -> 10000000 | R67: Giới thiệu Profile Kênh food review tập trung ăn uống bình dân, trải nghiệm thực tế, giọng điệu thẳng – thật. Tệp người xem thích review nhanh, rõ ràng, đáng tin. Lý do phù hợp Phù hợp tuyến review trực diện món (taste test, value). Giúp truyền tải rõ điểm mạnh “ngon – giá ổn – dễ ăn” của Fivestar. | U67: Confirm
H68: 01 tháng Sử dụng hình ảnh không độc quyền trên digital only *Bao gồm: Code Ads và reup kênh brand có chạy quảng cáo | I68: TRUE | J68: Tháng | K68: =if(I68=True,1,if(I68=False,0)) -> 1 | L68: 3000000 | M68: 0 | N68: 0 | O68: =IFERROR(Q68/M68,"-") -> - | P68: =IFERROR(Q68/N68,"-") -> - | Q68: =iferror(L68*K68,"-") -> 3000000
A69: New propose | B69: Vie ở sài gòn | C69: Tiktok | D69: 64.7K | E69: Nano | F69: link | G69: Hồ Chí Minh | H69: Sản xuất và đăng tải 01 Tiktok Video Review sản phẩm tại điểm bán Five Star Kiosk, theo định hướng nội dung của nhãn hàng - Thời lượng: 60-120s - Chất lượng: phù hợp điện thoại - Địa điểm: tại các Five Star Kiosk ở Tp. HCM Map Five Star Kiosk: Link | I69: TRUE | J69: Video Post | K69: =if(I69=True,1,if(I69=False,0)) -> 1 | L69: 12000000 | M69: 60000 | N69: 3000 | O69: =IFERROR(Q69/M69,"-") -> 200 | P69: =IFERROR(Q69/N69,"-") -> 4000 | Q69: =iferror(L69*K69,"-") -> 12000000 | R69: Giới thiệu Profile Creator làm nội dung nấu ăn + food/travel. Public results cho thấy Tiểu Mị Lon Ton có YouTube với các clip nấu món như “Gà xào kiểu Thái…”, Nhóm người xem thích food content gần gũi, vừa xem review món, vừa xem các trải nghiệm ăn uống hàng ngày. Tệp này phù hợp với các nội dung dễ khơi gợi cơn thèm và quyết định thử món nhanh. Lý do phù hợp Tiểu Mị Lon Ton hợp với Fivestar vì có thể làm nội dung theo hướng thích ăn thật, biết nói về món ăn, reaction tự nhiên. Nếu muốn clip có cảm giác “một người mê ăn thật sự đang thử món”, đây là kiểu creator khá hợp để tạo độ tin. | U69: Confirm
H70: 01 tháng Sử dụng hình ảnh không độc quyền trên digital only *Bao gồm: Code Ads và reup kênh brand có chạy quảng cáo | I70: TRUE | J70: Tháng | K70: =if(I70=True,1,if(I70=False,0)) -> 1 | L70: 8000000 | M70: 0 | N70: 0 | O70: =IFERROR(Q70/M70,"-") -> - | P70: =IFERROR(Q70/N70,"-") -> - | Q70: =iferror(L70*K70,"-") -> 8000000
A71: New propose | B71: Tô thu hà | C71: Tiktok | D71: 28k | E71: Nano | F71: link | G71: Hồ Chí Minh | H71: Sản xuất và đăng tải 01 Tiktok Video Review sản phẩm tại điểm bán Five Star Kiosk, theo định hướng nội dung của nhãn hàng - Thời lượng: 60-120s - Chất lượng: phù hợp điện thoại - Địa điểm: tại các Five Star Kiosk ở Tp. HCM Map Five Star Kiosk: Link | I71: FALSE | J71: Video Post | K71: =if(I71=True,1,if(I71=False,0)) -> 0 | L71: 6000000 | M71: 25000 | N71: 2000 | O71: =IFERROR(Q71/M71,"-") -> 0 | P71: =IFERROR(Q71/N71,"-") -> 0 | Q71: =iferror(L71*K71,"-") -> 0 | R71: Giới thiệu Profile Creator food review; nội dung khám phá buffet sushi tại HCM, Tệp người xem thích food review đời thường, theo dõi creator để tìm món/quán dễ thử trong tầm giá phổ thông. Đây là nhóm rất dễ match với sản phẩm gà rán mang tính everyday choice. Lý do phù hợp Huy Huỳnh hợp cho nhóm UGC cần cảm giác review quán/món thực tế, không quá chỉn chu, tập trung vào phản ứng ăn thật và tính recommendation. Với Fivestar, creator này có thể làm tốt dạng “ghé thử món – chấm điểm nhanh – rủ bạn đi ăn” | U71: Đề xuất thêm
H72: 01 tháng Sử dụng hình ảnh không độc quyền trên digital only *Bao gồm: Code Ads và reup kênh brand có chạy quảng cáo | I72: FALSE | J72: Tháng | K72: =if(I72=True,1,if(I72=False,0)) -> 0 | L72: 2000000 | M72: 0 | N72: 0 | O72: =IFERROR(Q72/M72,"-") -> - | P72: =IFERROR(Q72/N72,"-") -> - | Q72: =iferror(L72*K72,"-") -> 0
A73: New propose | B73: Phước đi đâu ? 🏇🏻 | C73: Tiktok | D73: 639K | E73: Micro | F73: link | G73: Hồ Chí Minh | H73: Sản xuất và đăng tải 01 Tiktok Video Review sản phẩm tại điểm bán Five Star Kiosk, theo định hướng nội dung của nhãn hàng - Thời lượng: 60-120s - Chất lượng: phù hợp điện thoại - Địa điểm: tại các Five Star Kiosk ở Tp. HCM Map Five Star Kiosk: Link | I73: FALSE | J73: Video Post | K73: =if(I73=True,1,if(I73=False,0)) -> 0 | L73: 22000000 | M73: 90000 | N73: 4000 | O73: =IFERROR(Q73/M73,"-") -> 0 | P73: =IFERROR(Q73/N73,"-") -> 0 | Q73: =iferror(L73*K73,"-") -> 0 | R73: Giới thiệu Profile Creator thiên về ăn uống/nấu ăn, nổi tiếng với các clip xuất hiện trong các nội dung khám phá buffet sushi. Tệp người xem quan tâm ăn uống, món ngon, trải nghiệm quán xá; phù hợp với nhóm thích các clip review nhanh, bắt mắt, kích thích vị giác. Lý do phù hợp Kun Cooking phù hợp với Fivestar vì vừa có màu foodie, vừa có lợi thế từ tên kênh gợi liên tưởng đến người yêu bếp/đồ ăn. Điều này giúp nội dung review gà rán dễ tạo cảm giác đáng tin, đặc biệt ở các clip đánh giá món ăn, phần ăn, độ ngon và trải nghiệm thực tế. | U73: Đề xuất thêm
H74: 01 tháng Sử dụng hình ảnh không độc quyền trên digital only *Bao gồm: Code Ads và reup kênh brand có chạy quảng cáo | I74: FALSE | J74: Tháng | K74: =if(I74=True,1,if(I74=False,0)) -> 0 | L74: 6000000 | M74: 0 | N74: 0 | O74: =IFERROR(Q74/M74,"-") -> - | P74: =IFERROR(Q74/N74,"-") -> - | Q74: =iferror(L74*K74,"-") -> 0
A75: b | B75: Khu Vực miền Bắc
A76: New Propose | B76: Dương Bảo Anh | C76: Tiktok | D76: 20.1K | E76: Nano | F76: https://www.tiktok.com/@duongbaoanh2kk?_r=1&_t=ZS-94n5aTW7D9A | G76: Hà Nội | H76: Sản xuất và đăng tải 01 Tiktok Video Review sản phẩm tại điểm bán Five Star Kiosk, theo định hướng nội dung của nhãn hàng - Thời lượng: 60-120s - Chất lượng: phù hợp điện thoại - Địa điểm: tại các Five Star Kiosk ở Tp. HCM Map Five Star Kiosk: Link | I76: TRUE | J76: Video Post | K76: =if(I76=True,1,if(I76=False,0)) -> 1 | L76: 4000000 | M76: 20000 | N76: 1500 | O76: =IFERROR(Q76/M76,"-") -> 200 | P76: =IFERROR(Q76/N76,"-") -> 2666.6667 | Q76: =iferror(L76*K76,"-") -> 4000000 | R76: Giới thiệu Profile Creator thuộc khu vực miền Bắc, xây dựng nội dung xoay quanh trải nghiệm ăn uống, review quán xá địa phương và khám phá các món ăn phổ biến. Nội dung mang màu sắc chân thực, gần gũi, thường là các clip ngắn ghi lại trải nghiệm thực tế tại quán, tập trung vào cảm nhận hương vị, không gian và mức giá. Tệp người xem chủ yếu là giới trẻ miền Bắc, quan tâm đến ăn uống, địa điểm mới và các gợi ý “ăn gì hôm nay”. Lý do phù hợp Creator phù hợp với Fivestar nhờ lợi thế nội dung mang tính địa phương cao, dễ tạo sự đồng cảm và tin tưởng từ người xem trong khu vực miền Bắc. Phong cách review nhanh, trực quan giúp làm nổi bật hình ảnh sản phẩm gà rán thông qua trải nghiệm thực tế, từ đó tăng khả năng kích thích nhu cầu thử món và ghé quán. Ngoài ra, việc am hiểu khẩu vị và hành vi người dùng miền Bắc cũng giúp nội dung dễ dàng tiếp cận đúng insight khách hàng mục tiêu. | S76: Nội dung dàn trải nhiều chủ đề, khu vực Hà Nội, có ER cao | U76: Confirm
H77: 01 tháng Sử dụng hình ảnh không độc quyền trên digital only *Bao gồm: Code Ads và reup kênh brand có chạy quảng cáo | I77: TRUE | J77: Tháng | K77: =if(I77=True,1,if(I77=False,0)) -> 1 | L77: 2000000 | M77: 0 | N77: 0 | O77: =IFERROR(Q77/M77,"-") -> - | P77: =IFERROR(Q77/N77,"-") -> - | Q77: =iferror(L77*K77,"-") -> 2000000
A78: New Propose | B78: Nguyệt Thư | C78: Tiktok | D78: 45000 | E78: Nano | F78: tiktok.com/@vunguyetthu | G78: Hải Dương | H78: Sản xuất và đăng tải 01 Tiktok Video Review sản phẩm tại điểm bán Five Star Kiosk, theo định hướng nội dung của nhãn hàng - Thời lượng: 60-120s - Chất lượng: phù hợp điện thoại - Địa điểm: tại các Five Star Kiosk ở Tp. HCM Map Five Star Kiosk: Link | I78: TRUE | J78: Video Post | K78: =if(I78=True,1,if(I78=False,0)) -> 1 | L78: 5000000 | M78: 20000 | N78: 1500 | O78: =IFERROR(Q78/M78,"-") -> 250 | P78: =IFERROR(Q78/N78,"-") -> 3333.3333 | Q78: =iferror(L78*K78,"-") -> 5000000 | S78: Khu vực Hải Dương, thường review nhà hàng và thời trang, ER + View ổn | U78: Confirm
H79: 01 tháng Sử dụng hình ảnh không độc quyền trên digital only *Bao gồm: Code Ads và reup kênh brand có chạy quảng cáo | I79: TRUE | J79: Tháng | K79: =if(I79=True,1,if(I79=False,0)) -> 1 | L79: 2000000 | M79: 0 | N79: 0 | O79: =IFERROR(Q79/M79,"-") -> - | P79: =IFERROR(Q79/N79,"-") -> - | Q79: =iferror(L79*K79,"-") -> 2000000
A80: New Propose | B80: phương thảo | C80: Tiktok | D80: 18K | E80: Nano | F80: https://www.tiktok.com/@phuonggthaoo155?_r=1&_d=secCgYIASAHKAESPgo8rJmnnWlHZUkhbZZ3X7bbu%2BpVNROGUxmH8Bp%2BrbWlf45hqhUYGBCwtBQ8g%2BXSrx4OwI%2BIpJWHrVLLunWHGgA%3D&_svg=1&checksum=d29afffc63226d6ec094b009585e48a92b16dcf45bd1a7ed6bbabcdd3790180c&item_author_type=1&sec_uid=MS4wLjABAAAAYm4z8eBamGKjHwCkQhnT11kOCMYpAsr2Qvlnr0IV4OZudRSEjT-pKHMM96QnQ479&sec_user_id=MS4wLjABAAAAYm4z8eBamGKjHwCkQhnT11kOCMYpAsr2Qvlnr0IV4OZudRSEjT-pKHMM96QnQ479&share_app_id=1180&share_author_id=6560476734818385922&share_link_id=5337E2FE-8F9C-49EF-8042-0E8DC3ECC050&share_region=VN&share_scene=1&sharer_language=vi&social_share_type=4&source=h5_t&timestamp=1769680772&tt_from=copy&u_code=d0894j604lb1i0&ug_btm=b8727%2Cb0&user_id=6560476734818385922&utm_campaign=client_share&utm_medium=ios&utm_source=copy | G80: Hà Nội | H80: Sản xuất và đăng tải 01 Tiktok Video Review sản phẩm tại điểm bán Five Star Kiosk, theo định hướng nội dung của nhãn hàng - Thời lượng: 60-120s - Chất lượng: phù hợp điện thoại - Địa điểm: tại các Five Star Kiosk ở Tp. HCM Map Five Star Kiosk: Link | I80: FALSE | J80: Video Post | K80: =if(I80=True,1,if(I80=False,0)) -> 0 | L80: 4000000 | M80: 20000 | N80: 2000 | O80: =IFERROR(Q80/M80,"-") -> 0 | P80: =IFERROR(Q80/N80,"-") -> 0 | Q80: =iferror(L80*K80,"-") -> 0 | S80: Khu vực Hà Nội, review đa dạng, tương tác thấp nhưng view khá cao | T80: PMAX Updated KPI | U80: Cân nhắc
H81: 01 tháng Sử dụng hình ảnh không độc quyền trên digital only *Bao gồm: Code Ads và reup kênh brand có chạy quảng cáo | I81: FALSE | J81: Tháng | K81: =if(I81=True,1,if(I81=False,0)) -> 0 | L81: 2000000 | M81: 0 | N81: 0 | O81: =IFERROR(Q81/M81,"-") -> - | P81: =IFERROR(Q81/N81,"-") -> - | Q81: =iferror(L81*K81,"-") -> 0
A82: New Propose | B82: Nhà Em Bơ Xinh 🌤️ | C82: Tiktok | D82: 76600 | E82: Nano | F82: https://www.tiktok.com/@nhaembebo2025?_t=ZS-8xFQzvmAh6O&_r=1 | G82: Hải Phòng | H82: Sản xuất và đăng tải 01 Tiktok Video Review sản phẩm tại điểm bán Five Star Kiosk, theo định hướng nội dung của nhãn hàng - Thời lượng: 60-120s - Chất lượng: phù hợp điện thoại - Địa điểm: tại các Five Star Kiosk ở Tp. HCM Map Five Star Kiosk: Link | I82: FALSE | J82: Video Post | K82: =if(I82=True,1,if(I82=False,0)) -> 0 | L82: 5000000 | M82: 30000 | N82: 2000 | O82: =IFERROR(Q82/M82,"-") -> 0 | P82: =IFERROR(Q82/N82,"-") -> 0 | Q82: =iferror(L82*K82,"-") -> 0 | S82: Khu vực Hải Phòng, View cao nhưng ER thấp, tuy nhiên duy trì ổn định, chủ đề mẹ và bé chủ yếu | U82: Cân nhắc
H83: 01 tháng Sử dụng hình ảnh không độc quyền trên digital only *Bao gồm: Code Ads và reup kênh brand có chạy quảng cáo | I83: FALSE | J83: Tháng | K83: =if(I83=True,1,if(I83=False,0)) -> 0 | L83: 2000000 | M83: 0 | N83: 0 | O83: - | P83: - | Q83: =iferror(L83*K83,"-") -> 0
A84: New Propose | B84: Mẹ bé Nai | C84: Tiktok | D84: 62K | E84: Nano | F84: https://www.tiktok.com/@minhphuong130595?_r=1&_t=ZS-94ac29NM9v3 | G84: Hải Phòng | H84: Sản xuất và đăng tải 01 Tiktok Video Review sản phẩm tại điểm bán Five Star Kiosk, theo định hướng nội dung của nhãn hàng - Thời lượng: 60-120s - Chất lượng: phù hợp điện thoại - Địa điểm: tại các Five Star Kiosk ở Tp. HCM Map Five Star Kiosk: Link | I84: FALSE | J84: Video Post | K84: =if(I84=True,1,if(I84=False,0)) -> 0 | L84: 4000000 | M84: 30000 | N84: 2000 | O84: =IFERROR(Q84/M84,"-") -> 0 | P84: =IFERROR(Q84/N84,"-") -> 0 | Q84: =iferror(L84*K84,"-") -> 0 | S84: Khu vực Hải Phòng, tần suất đăng video khá thấp, view ít trong giai đoạn 3 tháng trở lại đây, chủ đề mẹ và bé chủ yếu | U84: Cân nhắc
H85: 01 tháng Sử dụng hình ảnh không độc quyền trên digital only *Bao gồm: Code Ads và reup kênh brand có chạy quảng cáo | I85: FALSE | J85: Tháng | K85: =if(I85=True,1,if(I85=False,0)) -> 0 | L85: 2000000 | M85: 0 | N85: 0 | O85: - | P85: - | Q85: =iferror(L85*K85,"-") -> 0
A86: Brand propose | B86: Khánh Huyền (Đói chưa ><) | C86: Tiktok | D86: 80.9K | E86: Nano | F86: link | G86: Hà Nội | H86: Sản xuất và đăng tải 01 Tiktok Video Review sản phẩm tại điểm bán Five Star Kiosk, theo định hướng nội dung của nhãn hàng - Thời lượng: 60-120s - Chất lượng: phù hợp điện thoại - Địa điểm: tại các Five Star Kiosk ở Tp. HCM Map Five Star Kiosk: Link | I86: FALSE | J86: Video Post | K86: =if(I86=True,1,if(I86=False,0)) -> 0 | L86: 16000000 | M86: 70000 | N86: 4000 | O86: =IFERROR(Q86/M86,"-") -> 0 | P86: =IFERROR(Q86/N86,"-") -> 0 | Q86: =iferror(L86*K86,"-") -> 0 | R86: Giới thiệu Profile Kênh food/travel; Tệp khán giả thích xem gợi ý ăn uống kết hợp khám phá địa điểm, đặc biệt là người trẻ muốn nội dung nhanh, dễ áp dụng vào các cuộc hẹn hoặc cuối tuần. Lý do phù hợp Dun phù hợp với Fivestar ở góc review trải nghiệm thật trong hành trình đi đâu ăn đó. Đây là kiểu creator giúp brand không chỉ hiện lên như món ăn đơn lẻ mà còn như điểm dừng chân tiện, ngon, hợp mood đi chơi. Rất hợp cho tuyến UGC đi đường, ghé mua, ăn cùng bạn. | U86: Đề xuất thêm
H87: 01 tháng Sử dụng hình ảnh không độc quyền trên digital only *Bao gồm: Code Ads và reup kênh brand có chạy quảng cáo | I87: FALSE | J87: Tháng | K87: =if(I87=True,1,if(I87=False,0)) -> 0 | L87: 8000000 | M87: 0 | N87: 0 | O87: =IFERROR(Q87/M87,"-") -> - | P87: =IFERROR(Q87/N87,"-") -> - | Q87: =iferror(L87*K87,"-") -> 0
A88: Brand Propose | B88: Nguyen Mai Ha My | C88: Tiktok | D88: 47.9K | E88: Nano | F88: https://www.tiktok.com/@ng.hamii | G88: Hà Nội | H88: Sản xuất và đăng tải 01 Tiktok Video Review sản phẩm tại điểm bán Five Star Kiosk, theo định hướng nội dung của nhãn hàng - Thời lượng: 60-120s - Chất lượng: phù hợp điện thoại - Địa điểm: tại các Five Star Kiosk ở Tp. HCM Map Five Star Kiosk: Link | I88: TRUE | J88: Video Post | K88: =if(I88=True,1,if(I88=False,0)) -> 1 | L88: 10000000 | M88: 35000 | N88: 1500 | O88: =IFERROR(Q88/M88,"-") -> 285.71429 | P88: =IFERROR(Q88/N88,"-") -> 6666.6667 | Q88: =iferror(L88*K88,"-") -> 10000000 | R88: Giới thiệu Profile Creator lifestyle/food nhẹ, thiên về trải nghiệm cá nhân và ăn uống đơn giản. Tệp người xem trẻ, nữ, thích nội dung dễ thương – gần gũi. Lý do phù hợp Phù hợp lồng ghép Fivestar như lựa chọn ăn nhanh trong routine hằng ngày. Tăng độ relatable và khả năng chuyển đổi nhẹ nhàng. | U88: Confirm
H89: 01 tháng Sử dụng hình ảnh không độc quyền trên digital only *Bao gồm: Code Ads và reup kênh brand có chạy quảng cáo | I89: TRUE | J89: Tháng | K89: =if(I89=True,1,if(I89=False,0)) -> 1 | L89: 2000000 | M89: 0 | N89: 0 | O89: =IFERROR(Q89/M89,"-") -> - | P89: =IFERROR(Q89/N89,"-") -> - | Q89: =iferror(L89*K89,"-") -> 2000000
A90: Brand Propose | B90: Bộ trưởng bộ tích cực | C90: Tiktok | D90: 20.5K | E90: Nano | F90: https://www.tiktok.com/@ahthunek_ | G90: Hà Nội | H90: Sản xuất và đăng tải 01 Tiktok Video Review sản phẩm tại điểm bán Five Star Kiosk, theo định hướng nội dung của nhãn hàng - Thời lượng: 60-120s - Chất lượng: phù hợp điện thoại - Địa điểm: tại các Five Star Kiosk ở Tp. HCM Map Five Star Kiosk: Link | I90: TRUE | J90: Video Post | K90: =if(I90=True,1,if(I90=False,0)) -> 1 | L90: 7000000 | M90: 25000 | N90: 1500 | O90: =IFERROR(Q90/M90,"-") -> 280 | P90: =IFERROR(Q90/N90,"-") -> 4666.6667 | Q90: =iferror(L90*K90,"-") -> 7000000 | R90: Giới thiệu Profile Creator thiên về nội dung tích cực, vui vẻ, có yếu tố giải trí. Food chỉ là một phần trong lifestyle content. Tệp người xem thích nội dung vui – năng lượng tốt. Lý do phù hợp Phù hợp triển khai nội dung ăn uống theo hướng vui vẻ, giải trí. Giúp Fivestar xuất hiện như một “mood booster” – ăn ngon, vui. | U90: Confirm
H91: 01 tháng Sử dụng hình ảnh không độc quyền trên digital only *Bao gồm: Code Ads và reup kênh brand có chạy quảng cáo | I91: TRUE | J91: Tháng | K91: =if(I91=True,1,if(I91=False,0)) -> 1 | L91: 3000000 | M91: 0 | N91: 0 | O91: =IFERROR(Q91/M91,"-") -> - | P91: =IFERROR(Q91/N91,"-") -> - | Q91: =iferror(L91*K91,"-") -> 3000000
A92: Brand Propose | B92: Tuấn food không phét | C92: Tiktok | D92: 18.5K | E92: Nano | F92: https://www.tiktok.com/@tuanfoodkhongphet | G92: Hà Nội | H92: Sản xuất và đăng tải 01 Tiktok Video Review sản phẩm tại điểm bán Five Star Kiosk, theo định hướng nội dung của nhãn hàng - Thời lượng: 60-120s - Chất lượng: phù hợp điện thoại - Địa điểm: tại các Five Star Kiosk ở Tp. HCM Map Five Star Kiosk: Link | I92: TRUE | J92: Video Post | K92: =if(I92=True,1,if(I92=False,0)) -> 1 | L92: 9000000 | M92: 30000 | N92: 1500 | O92: =IFERROR(Q92/M92,"-") -> 300 | P92: =IFERROR(Q92/N92,"-") -> 6000 | Q92: =iferror(L92*K92,"-") -> 9000000 | R92: Giới thiệu Profile Kênh food review với định vị có sao nói vậy, nhấn mạnh trải nghiệm thật, đánh giá thẳng. Tệp người xem tin vào tính honest, thích review rõ ràng. Lý do phù hợp Phù hợp làm review sản phẩm/món theo hướng chân thật, tăng độ tin cậy cho Fivestar. Dễ tạo cảm giác “đáng thử” nhờ yếu tố honest review. | U92: Confirm
H93: 01 tháng Sử dụng hình ảnh không độc quyền trên digital only *Bao gồm: Code Ads và reup kênh brand có chạy quảng cáo | I93: TRUE | J93: Tháng | K93: =if(I93=True,1,if(I93=False,0)) -> 1 | L93: 3000000 | M93: 0 | N93: 0 | O93: =IFERROR(Q93/M93,"-") -> - | P93: =IFERROR(Q93/N93,"-") -> - | Q93: =iferror(L93*K93,"-") -> 3000000
A94: New Propose | B94: Hương | C94: Tiktok | D94: 86K | E94: Nano | F94: https://www.tiktok.com/@tranngocyen230 | G94: Hà Nội | H94: Sản xuất và đăng tải 01 Tiktok Video Review sản phẩm tại điểm bán Five Star Kiosk, theo định hướng nội dung của nhãn hàng - Thời lượng: 60-120s - Chất lượng: phù hợp điện thoại - Địa điểm: tại các Five Star Kiosk ở Tp. HCM Map Five Star Kiosk: Link | I94: FALSE | J94: Video Post | K94: =if(I94=True,1,if(I94=False,0)) -> 0 | L94: 6000000 | M94: 20000 | N94: 1000 | O94: =IFERROR(Q94/M94,"-") -> 0 | P94: =IFERROR(Q94/N94,"-") -> 0 | Q94: =iferror(L94*K94,"-") -> 0 | U94: Đề xuất thêm
H95: 01 tháng Sử dụng hình ảnh không độc quyền trên digital only *Bao gồm: Code Ads và reup kênh brand có chạy quảng cáo | I95: FALSE | J95: Tháng | K95: =if(I95=True,1,if(I95=False,0)) -> 0 | L95: 3000000 | M95: 0 | N95: 0 | O95: =IFERROR(Q95/M95,"-") -> - | P95: =IFERROR(Q95/N95,"-") -> - | Q95: =iferror(L95*K95,"-") -> 0
A96: New Propose | B96: Mẹ Tấm Cám | C96: Tiktok | D96: 146K | E96: Nano | F96: https://www.tiktok.com/@thanhhuongrv | G96: Hải Phòng | H96: Sản xuất và đăng tải 01 Tiktok Video Review sản phẩm tại điểm bán Five Star Kiosk, theo định hướng nội dung của nhãn hàng - Thời lượng: 60-120s - Chất lượng: phù hợp điện thoại - Địa điểm: tại các Five Star Kiosk ở Tp. HCM Map Five Star Kiosk: Link | I96: FALSE | J96: Video Post | K96: =if(I96=True,1,if(I96=False,0)) -> 0 | L96: 8000000 | M96: 20000 | N96: 1500 | O96: =IFERROR(Q96/M96,"-") -> 0 | P96: =IFERROR(Q96/N96,"-") -> 0 | Q96: =iferror(L96*K96,"-") -> 0 | U96: Đề xuất thêm
H97: 01 tháng Sử dụng hình ảnh không độc quyền trên digital only *Bao gồm: Code Ads và reup kênh brand có chạy quảng cáo | I97: FALSE | J97: Tháng | K97: =if(I97=True,1,if(I97=False,0)) -> 0 | L97: 4000000 | M97: 0 | N97: 0 | O97: =IFERROR(Q97/M97,"-") -> - | P97: =IFERROR(Q97/N97,"-") -> - | Q97: =iferror(L97*K97,"-") -> 0
A98: c | B98: Khu vực miền Nam | I98: FALSE
A99: Confirm | B99: Zăn Zăn Daily ✨ | C99: Tiktok | D99: 60K | E99: Nano | F99: https://www.tiktok.com/@zan.riviu?_r=1&_t=ZS-94n3uOkLyE8 | G99: Bình Dương | H99: Sản xuất và đăng tải 01 Tiktok Video Review sản phẩm tại điểm bán Five Star Kiosk, theo định hướng nội dung của nhãn hàng - Thời lượng: 60-120s - Chất lượng: phù hợp điện thoại - Địa điểm: tại các Five Star Kiosk ở Tp. HCM Map Five Star Kiosk: Link | I99: TRUE | J99: Video Post | K99: =if(I99=True,1,if(I99=False,0)) -> 1 | L99: 5000000 | M99: 40000 | N99: 2000 | O99: =IFERROR(Q99/M99,"-") -> 125 | P99: =IFERROR(Q99/N99,"-") -> 2500 | Q99: =iferror(L99*K99,"-") -> 5000000 | R99: Giới thiệu Profile Creator khu vực miền Nam, tập trung xây dựng nội dung ăn uống và review quán xá với phong cách sôi động, bắt mắt và giàu năng lượng. Nội dung thường xoay quanh trải nghiệm thực tế tại quán, từ hương vị món ăn, phần ăn đến không gian và mức giá. Tệp người xem chủ yếu là giới trẻ, yêu thích khám phá các địa điểm ăn uống mới, ưu tiên những video ngắn, hấp dẫn và mang tính giải trí cao. Lý do phù hợp Creator phù hợp với Fivestar nhờ màu sắc nội dung foodie rõ nét, dễ kích thích vị giác và tạo cảm giác “thèm ăn” ngay khi xem. Phong cách review nhanh, trực quan giúp làm nổi bật sản phẩm gà rán thông qua trải nghiệm thực tế, từ đó tăng độ tin tưởng và thúc đẩy nhu cầu thử món. Bên cạnh đó, sự năng động và gần gũi trong cách thể hiện cũng giúp nội dung dễ lan tỏa, phù hợp với hành vi tiêu thụ nội dung của người dùng miền Nam. | S99: Khu vực Bình Dương, nội dung đa dạng, ER cao (nhưng chủ yếu là tim) | U99: Confirm
H100: 01 tháng Sử dụng hình ảnh không độc quyền trên digital only *Bao gồm: Code Ads và reup kênh brand có chạy quảng cáo | I100: TRUE | J100: Tháng | K100: =if(I100=True,1,if(I100=False,0)) -> 1 | L100: 2000000 | M100: 0 | N100: 0 | O100: =IFERROR(Q100/M100,"-") -> - | P100: =IFERROR(Q100/N100,"-") -> - | Q100: =iferror(L100*K100,"-") -> 2000000
A101: Considering | B101: Phương Đi Chill 🌈 | C101: Tiktok | D101: 13600 | E101: Nano | F101: https://www.tiktok.com/@phuongoychillthoy | G101: Đồng Nai | H101: Sản xuất và đăng tải 01 Tiktok Video Review sản phẩm tại điểm bán Five Star Kiosk, theo định hướng nội dung của nhãn hàng - Thời lượng: 60-120s - Chất lượng: phù hợp điện thoại - Địa điểm: tại các Five Star Kiosk ở Tp. HCM Map Five Star Kiosk: Link | I101: TRUE | J101: Video Post | K101: =if(I101=True,1,if(I101=False,0)) -> 1 | L101: 5000000 | M101: 25000 | N101: 1500 | O101: =IFERROR(Q101/M101,"-") -> 200 | P101: =IFERROR(Q101/N101,"-") -> 3333.3333 | Q101: =iferror(L101*K101,"-") -> 5000000 | S101: RE cao nhưng view thấp, Chủ yếu về ăn uống, TA phù hợp FS, giá cao | T101: PMAX Updated KPI | U101: Confirm
H102: 01 tháng Sử dụng hình ảnh không độc quyền trên digital only *Bao gồm: Code Ads và reup kênh brand có chạy quảng cáo | I102: TRUE | J102: Tháng | K102: =if(I102=True,1,if(I102=False,0)) -> 1 | L102: 2000000 | M102: 0 | N102: 0 | O102: =IFERROR(Q102/M102,"-") -> - | P102: =IFERROR(Q102/N102,"-") -> - | Q102: =iferror(L102*K102,"-") -> 2000000
A103: Considering | B103: Đức Tân Bình | C103: Tiktok | D103: 42.4K | E103: Nano | F103: https://www.tiktok.com/@huynhhongocduc | G103: Bình Dương | H103: Sản xuất và đăng tải 01 Tiktok Video Review sản phẩm tại điểm bán Five Star Kiosk, theo định hướng nội dung của nhãn hàng - Thời lượng: 60-120s - Chất lượng: phù hợp điện thoại - Địa điểm: tại các Five Star Kiosk ở Tp. HCM Map Five Star Kiosk: Link | I103: TRUE | J103: Video Post | K103: =if(I103=True,1,if(I103=False,0)) -> 1 | L103: 5000000 | M103: 20000 | N103: 1000 | O103: =IFERROR(Q103/M103,"-") -> 250 | P103: =IFERROR(Q103/N103,"-") -> 5000 | Q103: =iferror(L103*K103,"-") -> 5000000 | S103: ER cao nhưng view thấp -> Awareness không cao Nội dung xoay quanh ẩm thực chủ yếu | T103: PMAX Updated KPI | U103: Confirm
H104: 01 tháng Sử dụng hình ảnh không độc quyền trên digital only *Bao gồm: Code Ads và reup kênh brand có chạy quảng cáo | I104: TRUE | J104: Tháng | K104: =if(I104=True,1,if(I104=False,0)) -> 1 | L104: 2000000 | M104: 0 | N104: 0 | O104: =IFERROR(Q104/M104,"-") -> - | P104: =IFERROR(Q104/N104,"-") -> - | Q104: =iferror(L104*K104,"-") -> 2000000
...

Sheet INT | Influencer Execution Trac
A1: PMAX | C.P.GROUP VIETNAM - INFLUENCERS WORKPLAN | H1: XM | J1: Meci | N1: T5A
J2: =counta(J5:J970) &"/37" -> 38/37 | K2: =counta(K5:K970) &"/37" -> 0/37 | L2: =counta(L5:L970) &"/37" -> 0/37 | M2: =counta(M5:M970) &"/37" -> 35/37 | N2: =counta(N5:N970) &"/37" -> 37/37 | O2: =counta(O5:O970) &"/37" -> 7/37 | P2: =counta(P5:P970) &"/37" -> 36/37 | Q2: =counta(Q5:Q970) &"/37" -> 35/37 | ... S2: =counta(S5:S970) &"/37" -> 36/37 | U2: =counta(U4:U970) &"/37" -> 37/37 | V2: =counta(V5:V970) &"/37" -> 3/37 | W2: =counta(W4:W970) &"/37" -> 37/37 | X2: =counta(X4:X970) &"/37" -> 37/37 | Y2: =counta(Y5:Y970) &"/37" -> 4/37 | Z2: =counta(Z4:Z970) &"/37" -> 35/37 | AA2: =counta(AA4:AA970) &"/37" -> 31/37 | AB2: =counta(AB5:AB970) &"/37" -> 30/37 | AD2: =counta(AD4:AD970) &"/37" -> 37/37 | AE2: =counta(AE4:AE970) &"/37" -> 27/37 | AF2: =counta(AF4:AF970) &"/37" -> 11/37 | AG2: =counta(AG6:AG970) &"/37" -> 36/37 | AH2: =counta(AH4:AH970) &"/37" -> 18/37
A3: No. | B3: Influencer | C3: Platform | D3: Followers | E3: Tiers | F3: Link | G3: Location | H3: SOW | I3: Outfit Tracking | J3: Địa điểm quay + thời gian | K3: Outfit | L3: Outfit | M3: Tình trạng | N3: SCRIPT R1 | O3: Feedback PMAX R1 | P3: Feedback Brand team R1 | Q3: SCRIPT R2 | R3: Feedback PMAX R2 | S3: Feedback Brand team R2 | U3: DEMO R1 | V3: Feedback PMAX R1 | W3: Feedback Brand team R1 | X3: DEMO R2 | Y3: Feedback PMAX R2 | Z3: Feedback Brand team R2 | AA3: Final Demo | AB3: Status | AC3: Final Demo Revise | AD3: Caption | AE3: Feedbacks caption | AF3: Caption Revised | AG3: Lịch Air dự kiến | AH3: LINK AIR | AI3: GHI CHÚ
A4: FOODY REVIEWER
A5: 1 | B5: Thắng Lợi | C5: Tiktok | D5: 426.5K | E5: Micro | F5: Link | G5: Đồng Nai | H5: Sản xuất và đăng tải 01 Tiktok Video Review sản phẩm tại điểm bán Five Star Kiosk, theo định hướng nội dung của nhãn hàng - Thời lượng: 60-120s - Chất lượng: phù hợp điện thoại - Địa điểm: tại các Five Star Kiosk ở nơi sinh sống Map Five Star Kiosk: Link 01 tháng Sử dụng hình ảnh không độc quyền trên digital only *Bao gồm: Code Ads và reup kênh brand có chạy quảng cáo | I5: FALSE | J5: 13/5 19h00 BASIC SHOP - Nguyễn Thị Thuận - Số 67 Đường 9, phường Trường Thọ, TP. Thủ Đức, TP. HCM | M5: Đã quay | N5: =Draft!M5 -> https://docs.google.com/spreadsheets/d/1sek28q8dSpx6DU8QYhlKU5FqtCePEZaUhxd1o63zgyI/edit?gid=1935125103#gid=1935125103 | O5: =Draft!N5 | P5: - Câu hook đầu tiên có thể gắn thêm context rõ ràng để tạo sự quen thuộc > ví dụ: có những hôm trời mưa lạnh lạnh bụng thì đói mà không đi đâu xa được, đang đi trên đường mà bụng đói,v.v. - “Chỗ cứu đói cực nhanh” hiện còn khá generic, vì brand fastfood nào cũng có thể nói vậy. Có thể bổ sung chi tiết về kiosk Five Star nổi bật hoặc độ phủ quen thuộc ở nhiều góc phố để tạo cảm giác gần gũi. - Phần review món ăn hiện tại hơi flat > có thể thêm reaction, thêm chi tiết về món ăn (hương vị, độ giòn,v.v.) để tạo sự hấp dẫn - CTA chưa đủ mạnh, có thể thay bằng “Món nào ở Five Star mọi người thấy underrated nhất?”; “Ai giống mình, đi ngang chỉ định mua 1 món nhưng cuối cùng cầm nguyên bịch?”; “Có ai ban đầu không kỳ vọng nhiều nhưng ăn rồi bị ghiền không?” - Gắn thêm địa chỉ về địa điểm Five Star mà bạn đã ghé | Q5: https://docs.google.com/spreadsheets/d/1sek28q8dSpx6DU8QYhlKU5FqtCePEZaUhxd1o63zgyI/edit?gid=771502114#gid=771502114 | R5: Đã update script và Outfit chờ team check | S5: Remove từ kiosk Còn lại ok | U5: https://drive.google.com/drive/folders/15ODXPBRTw5WmN8MAY5ueU-3G_tHaar-8 | V5: =Draft!U5 | W5: 0:04 Bỏ địa chỉ, thời gian 0:20 - Mention tên các món xiên que đặc biệt thay vì chỉ nói bò viên cá viên - Xúc xích toperdo, chả giò gai jor, gà nugget Cho màu món ăn tươi hơn, tăng saturation, sáng hơn | X5: https://drive.google.com/file/d/1W_rLKrdvJSUqVmyRZnA2Vx3-PkXcG-_A/view?usp=drive_link | Y5: =Draft!X5 | Z5: chỉnh text giá tham khảo rẻ > giá hợp lý 1:01 - Five Star chi nhánh .. ghi địa chỉ, bỏ basic shop Add cta kêu gọi ghé five star gần nhà Leo's comment: 0:28: Gà miếng nhưng text là "gà nugget" => Sai tên sản phẩm, sửa thành "gà giòn giòn" 0:31: "Gà không bị khô đâu" nhưng cảnh xé gá hơi lâu => Cắt ngắn cảnh xé gà lại 0:35: Bỏ text "bò viên, cá viên" đổi thành "chả cá hàn quốc, chả giò gai jor thái lan" 0:41: Bỏ text "xúc xích toperdo, chả giò gai jor" đổi thành "xúc xích sumo, gà nugget, gà popcorn" | AA5: https://drive.google.com/file/d/1h74wlhoDoRD_Y03lKWFQV6RdRRRdzK7N/view?usp=drivesdk | AB5: Confirm | AD5: Nếu hnay bạn phân vân ăn gì thử có thể cân nhắc Fivestar nhé #FiveStarVietnam #GaDau | AG5: 46087 | AH5: https://vt.tiktok.com/ZSQ1XDNsR/
A6: 2 | B6: Lulu Review | C6: Tiktok | D6: 336.4K | E6: Micro | F6: Link | G6: Hồ Chí Minh | H6: Sản xuất và đăng tải 01 Tiktok Video Review sản phẩm tại điểm bán Five Star Kiosk, theo định hướng nội dung của nhãn hàng - Thời lượng: 60-120s - Chất lượng: phù hợp điện thoại - Địa điểm: tại các Five Star Kiosk ở nơi sinh sống Map Five Star Kiosk: Link 01 tháng Sử dụng hình ảnh không độc quyền trên digital only *Bao gồm: Code Ads và reup kênh brand có chạy quảng cáo | I6: FALSE | J6: 11h00 sáng T6-15/5: Địa điểm quay: B8/28M Đường Hưng Nhơn, xã Tân Nhựt, huyện Bình Chánh | M6: Đã quay | N6: =Draft!M6 -> https://docs.google.com/spreadsheets/d/1vaRBTbnZy9dvsd-SpvXhO76Gg-InJKD2u8IGmvjbPTo/edit?gid=0#gid=0 | O6: =Draft!N6 | P6: Cảnh 2: - Chỉnh lại lời thoại — chi tiết “màu vàng huyền thoại của Five Star” chưa thật sự đúng vì màu nhận diện chính của Five Star là đỏ và vàng. - Thêm lời thoại theo hướng đi ngang nghe tiếng “xèo xèo” hoặc ngửi thấy mùi gà chiên quá hấp dẫn nên bị thu hút và quẹo vào mua, dù ban đầu chỉ định ghé mua nước. Cảnh 3: Chỉnh text - Gần 1000 điểm bán trên 30+ tỉnh thành Cảnh 4: - Chỉnh text - Menu siêu đa dạng Nhanh - Gọn - Ngon > mình ko nhấn mạnh về giá rẻ >> Note point này cho các bạn KOL luôn nha Cảnh 5: Câu thoại đầu chưa link rõ ràng tới đoạn sau > gợi ý có thể nói rõ là tại sao những món này lại phù hợp với người lười đợi từ đầu luôn. Gắn text thêm địa chỉ về địa điểm Five Star mà bạn đã ghé Overall ok có thể quay cận món nhiều hơn | Q6: =Draft!P6 -> https://docs.google.com/spreadsheets/d/1vaRBTbnZy9dvsd-SpvXhO76Gg-InJKD2u8IGmvjbPTo/edit?gid=1396100120#gid=1396100120 | R6: =Draft!Q6 -> Đã input thêm Outfit Team KOC đã điều chỉnh theo feedback của brand | S6: Do có thay đổi về địa chỉ review nên nhờ bạn thay bằng share link trong caption để mn có thể tìm các quán fivestar gần các bạn: https://fivestarnearyou.cp.com.vn/ ko cần add text địa chỉ lên clip nữa nhé mà chỉ kêu gọi vào link để tìm quán nha. | U6: https://drive.google.com/drive/folders/1WLes2-C3PZsK0zl4ZA5D5yJ1xAYDkhWR | V6: =Draft!U6 | W6: Gà tatsutaage /ta-chư-ta-gê/ > đọc chỉnh lại 0:23 - thay đoạn này bằng đoạn zoom in vô menu (như khúc sau) nếu còn source nha Leo's comment: 1. Đoạn 00:46 - Tên đúng "chả giò gai jor" | X6: https://drive.google.com/drive/folders/1WLes2-C3PZsK0zl4ZA5D5yJ1xAYDkhWR | Z6: Leo's comment: Phần sửa lồng vào sau nghe hơi miễn cưỡng. Còn lại ổn => VO sẽ đổi thành text add in | AA6: https://drive.google.com/file/d/1pmsQfzjtuZdATJQ_yn_7jK7w3fMZe-n8/view | AB6: Confirm | AD6: Gà chiên nóng hổi, cắn một miếng da giòn rụm, thịt bên trong vẫn mọng nước. #FiveStarVietnam #GaDau #FiveStar #GaRanFiveStar | AG6: 27/5 | AH6: https://www.tiktok.com/@lulureview_/video/7644513610072460551?_r=1&_t=ZS-96jI4dZLIL1
A7: 3 | B7: Hello Lập Đây | C7: Tiktok | D7: 260K | E7: Micro | F7: Link | G7: Hồ Chí Minh | H7: Sản xuất và đăng tải 01 Tiktok Video Review sản phẩm tại điểm bán Five Star Kiosk, theo định hướng nội dung của nhãn hàng - Thời lượng: 60-120s - Chất lượng: phù hợp điện thoại - Địa điểm: tại các Five Star Kiosk ở nơi sinh sống Map Five Star Kiosk: Link "01 tháng Sử dụng hình ảnh không độc quyền trên digital only *Bao gồm: Code Ads và reup kênh brand có chạy quảng cáo" | I7: TRUE | J7: Đã đi quay - 16h ngày 12/5 - OUTLET - HKD GÀ RÁN FIVE STAR THU HÀ - 37/3 Huỳnh Tấn Phát, Xã Nhà Bè, TPHCM | M7: Đã quay | N7: =Draft!M7 -> https://docs.google.com/spreadsheets/d/161njDQndXtRs8o07Zhz1nU0rtGGgw4RpJvwe5s0bWPc/edit?gid=0#gid=0 | O7: =Draft!N7 | P7: Trang phục: nhờ bạn chọn áo màu tươi hơn (đỏ hoặc vàng) Phân cảnh Body: - Đã đi ăn ngoài phải chọn ăn ngon > Sau câu này thêm 1 câu tại sao lại chọn Five Star > gợi ý: do gần nhà, do đi ngang qua thấy thèm, v.v. - Về giá > mình ko nhắc từ khóa rẻ hay mắc > chỉnh lại theo hướng phần ăn đầy đặn / xịn so với mức giá hoặc sử dụng các từ khóa như giá dễ chịu, ai cũng mua dc Cảnh outro: Câu còn lập thì có quan tâm ko > hơi bị khó hiểu Gắn text thêm địa chỉ về địa điểm Five Star mà bạn đã ghé | Q7: =Draft!P7 -> https://docs.google.com/spreadsheets/d/161njDQndXtRs8o07Zhz1nU0rtGGgw4RpJvwe5s0bWPc/edit?gid=972901149#gid=972901149 | R7: =Draft!Q7 -> Team KOC đã review nội dung và thay đổi outfit tươi hơn Hiện đang thiêu Địa chỉ cụ thể. team sẽ input sau | S7: Remove từ kiosk Ko cần add địa chỉ lên video > đổi thành share link website sang phần comment | U7: Demo Hello Lập Đây.mp4 | V7: =Draft!U7 | W7: 1:11 - zoom in hoặc là thay cảnh > để ko thấy rõ cái dây điện với đống bụi ở trên tường vì khúc đó mình đang nói về việc sạch sẽ 1:24 - Text trên clip - "Tập đoàn C.P. đến từ Thái Lan" ko phải là "tập đoàn C.P. Thái Lan" | X7: Revised R1.mp4 | Z7: Phần feedback sau sẽ được gom để xử lý ở demo R2 Leo's comment: 1. 00:24 - liệt kê các món xiên que: "Cá viên, bò viên, chả cá..." đổi thành "cá viên, bò viên, xúc xích phô mai.. đặc biệt còn có chả giò kiểu thái (or) chả giò gai jor" nghe có signature hơn là chỉ liệt kê những món bình thường 2. 00:36 - remove cảnh + thoại "khách đông cỡ này luôn" - cảnh thật chưa đủ đông, nghe hơi miễn cưỡng. 3. Đoạn 01:12 - "cửa hàng sạch sẻ" nên đổi cảnh quay cửa hàng, đang lồng trên cảnh staff chế biến gà, không match phần hình và phần tiếng. | AA7: Five star (fix 3).mp4 | AB7: Confirm | AD7: CAPTION: Brand gà rán này xứng đáng viral hơn gấp 10 lần | AE7: Chỉnh lại Brand gà rán > Thương hiệu / Brand thức ăn nhanh | AF7: Thương hiệu gà rán này xứng đáng viral hơn gấp 10 lần #hellolapday #FiveStarVietnam #GaDau #FiveStar #GaRanFiveStar | AG7: 46059 | AH7: - tiktok: https://vt.tiktok.com/ZSxt8cXaM/ - reup insta: https://www.instagram.com/reel/DY9hZnczdim/?igsh=MWk3cnVvcjlwZ3VndA==
A8: 4 | B8: Huyền Nhi | C8: Tiktok | D8: 118.1K | E8: Micro | F8: Link | G8: Hồ Chí Minh | H8: Sản xuất và đăng tải 01 Tiktok Video Review sản phẩm tại điểm bán Five Star Kiosk, theo định hướng nội dung của nhãn hàng - Thời lượng: 60-120s - Chất lượng: phù hợp điện thoại - Địa điểm: tại các Five Star Kiosk ở nơi sinh sống Map Five Star Kiosk: Link "01 tháng Sử dụng hình ảnh không độc quyền trên digital only *Bao gồm: Code Ads và reup kênh brand có chạy quảng cáo" | I8: TRUE | J8: 11h00 t7 16/5 quay, ĐỊa điểm: BASIC SHOP - Nguyễn Thị Thuận - Số 67 Đường 9, phường Trường Thọ, TP. Thủ Đức, TP. HCM | M8: Đã quay | N8: =Draft!M8 -> https://docs.google.com/spreadsheets/d/1TlMiQyjUC_8vG--FMqD48heIruNjrv0a_-BycV6vMug/edit?gid=2103508750#gid=2103508750 | O8: =Draft!N8 | P8: Trang phục ok Tập đoàn CP Group > Bỏ chữ Group Bổ sung thêm ý về việc an tâm về chất lượng và an toàn thực phẩm Bỏ đoạn "mà ko thấy áp lực chi phí" - Add thêm địa chỉ Five Star | Q8: https://docs.google.com/spreadsheets/d/1TlMiQyjUC_8vG--FMqD48heIruNjrv0a_-BycV6vMug/edit?gid=80012582#gid=80012582 | R8: Đã input thêm Outfit Team KOC đã điều chỉnh theo feedback của brand | S8: Remove từ kiosk Remove địa chỉ > add website tìm quán ở comment Còn lại ok | U8: https://drive.google.com/file/d/1BQQEQ3ggRs06IXWejYz58QsoKTgGPsd1/view | V8: =Draft!U8 | W8: 0:03: chỉnh text theo hướng - Five Star - Thế giới ăn vặt, thiên đường ăn no có món gà rán siêu đỉnh > highlight về sự đa dạng và món gà rán signature 0:27 > hình món khoai tây chiên hơi thường > đẩy món gà rán lên, có các món khác thì mình cho lên nha - Có mấy góc bạn cầm đĩa gà hình như bị lặp lại 2-3 lần trong clip, mình còn góc khác thì thay giúp chị nha Các món xiên que > khi liệt kê add 1 món signature chả giò gai jor (trong đĩa bạn có order) > gọi tên món thay vì chỉ gọi là xiên que thông thường Text: Đa dạng các loại xiêu que > chỉnh chút theo hướng "Menu xiên que đa dạng với nhiều món ngon lạ miệng" 1:00 - hot dog tên món là "hot dog Torpedo" 1:05 - remove cảnh bàn trống có 1 ng ngồi Nên add CTA kêu gọi ghé quán > địa chỉ nằm ở link | X8: https://drive.google.com/file/d/1FHJD-DVN5yvqkgqVIHgOR6tfsrWjR9ht/view?usp=drivesdk | Y8: =Draft!X8 | Z8: Chỉnh text: Tập đoàn C.P. Việt Nam 0:26 - highlight món gà nugget ngôi sao Còn lại ok | AA8: https://drive.google.com/file/d/1qJxaezCXrSlDXG29sDkksX_jZKoB9ZqM/view?usp=drivesdk | AB8: Confirm | AD8: Fan gà rán thì lưu ngay quán Five Star nha mọi người ơii, có thêm đồ ăn vặt và các món ăn no nữa nè #FiveStarVietnam #GaDau #FiveStar #GaRanFiveStar | AG8: 29/5 | AH8: https://www.tiktok.com/@hhuyennhiii/video/7644779715093482772?_r=1&_t=ZS-96jFcDqShi1
A9: 5 | B9: Thư Bonny | C9: Tiktok | D9: 114.7K | E9: Micro | F9: Link | G9: Hồ Chí Minh | H9: Sản xuất và đăng tải 01 Tiktok Video Review sản phẩm tại điểm bán Five Star Kiosk, theo định hướng nội dung của nhãn hàng - Thời lượng: 60-120s - Chất lượng: phù hợp điện thoại - Địa điểm: tại các Five Star Kiosk ở nơi sinh sống Map Five Star Kiosk: Link "01 tháng Sử dụng hình ảnh không độc quyền trên digital only *Bao gồm: Code Ads và reup kênh brand có chạy quảng cáo" | I9: TRUE | J9: Đã đi quay Lịch quay: 10h 12/5 Địa điểm: BASIC SHOP - Nguyễn Thị Thuận - Số 67 Đường 9, phường Trường Thọ, TP. Thủ Đức, TP. HCM | M9: Đã quay | N9: =Draft!M9 -> https://docs.google.com/spreadsheets/d/11qQ5wa_wLzoqxwxYWqwWOeh0TAKOK7_d4tXx9pgrw0M/edit?gid=0#gid=0 | O9: =Draft!N9 | P9: - Highlight thêm về sự tiện lợi, giá dễ chịu / khẩu phần đầy đặn so với mức giá / ai cũng có thể thưởng thức - Gắn thêm địa chỉ về địa điểm Five Star mà bạn đã ghé và thêm CTA | Q9: =Draft!P9 -> https://docs.google.com/spreadsheets/d/11qQ5wa_wLzoqxwxYWqwWOeh0TAKOK7_d4tXx9pgrw0M/edit?gid=1343518029#gid=1343518029 | R9: =Draft!Q9 -> Đã add thêm outfit KOC NOTE: chi tiết khẩu phần. mức giá thì sau khi trải nghiệm KOC mới có cơ sở để đánh giá nên sẽ tinh chỉnh kịch bản sau KOC đã thêm địa chỉ và CTA vào script | S9: Script ok Do có thay đổi về địa chỉ review nên nhờ bạn thay bằng share link trong caption để mn có thể tìm các quán fivestar gần các bạn: https://fivestarnearyou.cp.com.vn/ ko cần add text địa chỉ lên clip nữa nhé mà chỉ kêu gọi vào link để tìm quán nha. | U9: Demo Five Star - Thư Bonny | V9: =Draft!U9 | W9: Mình remove đoạn bạn nói order về nhà thì ok hơn (1:51-1:52) Leo's comment: 1. Clip có quá nhiều tạp âm, khó giữ người xem hết 2. Remove 01:12 - 01:22, màu xiên gà hơi tối, nhìn không đủ hấp dẫn, cũng khó hình dung là món gì. 3. 01:35 - Bổ sung "đùi góc tư tẩm ướp" | X9: https://drive.google.com/file/d/1QjurRtSs_004WtM0egChyuALFNen9LNO/view?usp=drivesdk | Y9: =Draft!X9 | Z9: Vẫn còn tạp âm > tiếng xe to Nhi's comment Nên mention thêm đến giá cả của FS ví dụ "Giá cả hợp lý" Còn lại ok | AA9: https://drive.google.com/file/d/1OyIKU1LjE8w9vI3IK6QMT15pNHB9X5v3/view?usp=drivesdk | AB9: Confirm | AD9: Nhớ tới hương vị của Five Star là phải đi ăn NGAY VÀ LUÔN #FiveStarVietnam #GaDau #FiveStar #GaRanFiveStar | AE9: có thể chỉnh theo hướng nhớ là phải đi liền ko Leo's comment: Cả clip vẫn còn tạp âm (tiếng xe, tiếng gà gáy..) 0:41: Tiếng xe to hơn tiếng nhai da gà. Hình ảnh ổn, trừ âm thanh => Cố gắng fix âm thanh | AF9: "Nhớ tới hương vị của Five Star là phải đi ăn NGAY VÀ LUÔN #FiveStarVietnam #GaDau #FiveStar #GaRanFiveStar " | AG9: 46059 | AH9: https://www.tiktok.com/@thubonny/video/7646757218007715079?_r=1&_t=ZS-96sF5iS0M78
A10: 6 | B10: Nuchuu nè | C10: Tiktok | D10: 756K | E10: Micro | F10: Link | G10: Hồ Chí Minh | H10: Sản xuất và đăng tải 01 Tiktok Video Review sản phẩm tại điểm bán Five Star Kiosk, theo định hướng nội dung của nhãn hàng - Thời lượng: 60-120s - Chất lượng: phù hợp điện thoại - Địa điểm: tại các Five Star Kiosk ở nơi sinh sống Map Five Star Kiosk: Link "01 tháng Sử dụng hình ảnh không độc quyền trên digital only *Bao gồm: Code Ads và reup kênh brand có chạy quảng cáo" | I10: FALSE | J10: - 15-17h ngày 13/5 - PREAMIUM KIOSK 3*3 - HKD FIVE STAR ĐINH ĐỨC THIỆN - 1/26 Đinh Đức Thiện, xã Bình Chánh, TP HCM | M10: Đã quay | N10: =Draft!M10 -> https://docs.google.com/spreadsheets/d/1SNimKtZBUz4pm9ejeDfbgV1a815ex8d26sGSutaoT0A/edit?gid=0#gid=0 | O10: =Draft!N10 | P10: - Nhờ bạn chọn áo nào màu tươi hơn, năng động hơn nhe - Bên cạnh mùi vị tuổi thơ > add thêm những câu nhận xét là so với ký ức tuổi thơ thì Five Star có gì mới hơn (ví dụ store nhìn chuẩn chỉnh hơn, chuyên nghiệp hơn, món ăn đa dạng hơn, v.v) - Ko nhắc tới từ khóa "rẻ" > thay bằng giá dễ chịu, giá hợp lý, khẩu phần chất lượng hơn so với giá - Gắn thêm địa chỉ về địa điểm Five Star mà bạn đã ghé | Q10: =Draft!P10 -> https://docs.google.com/spreadsheets/d/1SNimKtZBUz4pm9ejeDfbgV1a815ex8d26sGSutaoT0A/edit?gid=1256513125#gid=1256513125 | R10: =Draft!Q10 -> Hiện team KOC đã update nội dung nhưng thiếu địa chỉ cụ thể Đã thay đổi option outfit chờ team check | S10: Script ok nhé, thay chữ kiosk bằng "quán" giúp chị nha. Do có thay đổi về địa chỉ review nên nhờ bạn thay bằng share link trong caption để mn có thể tìm các quán fivestar gần các bạn: https://fivestarnearyou.cp.com.vn/ ko cần add text địa chỉ lên clip nữa nhé mà chỉ kêu gọi vào link để tìm quán nha. | U10: Fivestar.mov | W10: Màu sắc món > tươi hơn, tăng saturation 0:39 - có thể kéo dài đoạn đổ sốt một chút ko 1:19 > remove đoạn chiên > dầu hơi nâu Sai chính tả "Chuẩn Chỉnh" Leo's comment: 1. Đoạn 00:59 - add sai tên món => Đổi lại tên món "Gà Nugget" + thoại: hình ngôi sao nhìn thú vị.. 2. Đoạn 01:31 - đổi "đám bạn" thành "nhóm bạn" | X10: FIVESTARFIX.mov | Z10: Ức gà - ko bị khô > đổi thành ức gà mọng nước juicy 0:43: "lười có xương" -> bỏ đoạn này | AA10: Fivestar | AB10: Confirm | AD10: CAPTION: Món ăn tuổi thơ của tôi | AG10: 28/5 | AH10: https://vt.tiktok.com/ZSx45rKrU/
A11: 7 | B11: Ăn ngon cùng Puu | C11: Tiktok | D11: 345.4K | E11: Micro | F11: Link | G11: Hồ Chí Minh | H11: Sản xuất và đăng tải 01 Tiktok Video Review sản phẩm tại điểm bán Five Star Kiosk, theo định hướng nội dung của nhãn hàng - Thời lượng: 60-120s - Chất lượng: phù hợp điện thoại - Địa điểm: tại các Five Star Kiosk ở nơi sinh sống Map Five Star Kiosk: Link | I11: TRUE | J11: Ăn Ngon Cùng Puu Quay ngày 15/5 - 13h00 MINI SHOP - Five Star Mega Q12 - Số 2 đường Trương Thị Hoa, KP 4A, Tân Thới Hiệp, TPHCM | M11: Đã quay | N11: =Draft!M11 -> https://docs.google.com/spreadsheets/d/1jC0a00h3FsNPkNZqCO8tCfHq8Ux2lS9cjcq9OYS5YDw/edit?gid=0#gid=0 | O11: =Draft!N11 | P11: - CP Group > đổi thành tập đoàn CP - Bổ sung thêm ý về sự đa dạng (nhiều món người lớn con nít đều ăn được, từ món ăn no tới món ăn vặt) - Thêm ý về việc ăn 1 mình hay ăn nhiều người đều siêu hợp - Gắn thêm địa chỉ về địa điểm Five Star mà bạn đã ghé | Q11: https://docs.google.com/spreadsheets/d/1jC0a00h3FsNPkNZqCO8tCfHq8Ux2lS9cjcq9OYS5YDw/edit?gid=1937930012#gid=1937930012 | R11: Đã update script và Outfit chờ team check | S11: Trang phục ok Script ok nhé Thêm CTA: "Xem Store gần nhất bên dưới phần comment" + Cmt link web | U11: https://drive.google.com/drive/folders/110dLNgTuRhRmD7fAW9mPfIvRAASVPXpA | V11: =Draft!U11 | W11: Khúc đầu gà bị ám xanh Bỏ địa chỉ chi tiết Gà tẩm ướt > đùi gà góc tư tẩm ướt Highlight một số xiên que lạ miệng hoặc đọc tên món chi tiết > chả giò gai jor, hotdog xúc xích phô mai tẩm khoai tây, v.v Đoạn cuối > chọn gà rán hay xiên que ở five star > Chọn | X11: https://drive.google.com/drive/folders/110dLNgTuRhRmD7fAW9mPfIvRAASVPXpA | Y11: =Draft!X11 | Z11: Thiếu CTA cuối clip | AA11: https://drive.google.com/drive/folders/110dLNgTuRhRmD7fAW9mPfIvRAASVPXpA | AD11: "Top 1 địa chỉ gà trong lòng Pu đó chính là Fivestar này nè cả nhà ơi #FiveStarVietnam #GaDau" | AE11: ok Leo: Top 1 địa chỉ gà rán trong lòng Pu đó chính là Fivestar này nè cả nhà ơi #FiveStarVietnam #GaDau #GaRan | AG11: 14/6
A12: 8 | B12: A dinosaur in the kitchen | C12: Tiktok | D12: 294.8K | E12: Micro | F12: https://www.tiktok.com/@phamtrang.2401 | G12: Hà Nội | H12: Sản xuất và đăng tải 01 Tiktok Video Review sản phẩm tại điểm bán Five Star Kiosk, theo định hướng nội dung của nhãn hàng - Thời lượng: 60-120s - Chất lượng: phù hợp điện thoại - Địa điểm: tại các Five Star Kiosk ở nơi sinh sống Map Five Star Kiosk: Link "01 tháng Sử dụng hình ảnh không độc quyền trên digital only *Bao gồm: Code Ads và reup kênh brand có chạy quảng cáo" | I12: TRUE | J12: Thứ 5 ngày 21/5 (11h trưa) địa điểm Ngãi Cầu | M12: Đã confirm lịch | N12: https://docs.google.com/spreadsheets/d/1z-HdLijlKbGSj5qe5SrB_0F34ISWgdy1XuSDOjDegrg/edit?gid=0#gid=0 | O12: =Draft!N12 | P12: Trang phục ok - Opening > chỉnh lại ko nhấn mạnh vào việc rẻ mà đổi thành giá dễ chịu, ko đau ví mà khẩu phần thì chất lượng - 7 Eleven k thuộc CP > remove - Chỉnh CP Group > Tập đoàn C.P. - Nội dung đang focus vào giá rẻ, giá mềm khá nhiều > chỉnh lại để tập trung vào sự tiện lợi, chất lượng món ăn | Q12: https://docs.google.com/spreadsheets/d/1z-HdLijlKbGSj5qe5SrB_0F34ISWgdy1XuSDOjDegrg/edit?gid=1633982349#gid=1633982349 | R12: Team đã update outfit + script | S12: Script ok Thêm CTA: "Xem Store gần nhất bên dưới phần comment" + Cmt link web | U12: https://drive.google.com/file/d/1QWiIeGyMi5lPxKIJ3cVXH9IjQi11wUNE/view?usp=drivesdk | V12: =Draft!U12 | W12: Đọc tên các món xiên que luôn nhé> chả giò gai jor, hotdog xúc xích phô mai tẩm khoai tây, v.v Phần má đùi > đùi góc tư tẩm tiêu | X12: https://drive.google.com/file/d/1a9cTmTDG8Q4oW3-jqPiq0IK9eus3n2ML/view?usp=drivesdk | Y12: =Draft!X12 | Z12: Chất lượng video thấp 1:06, màu miếng gà tươi hơn 0:36 - gà nugget ngôi sao > nếu ko add VO thì add text giúp c Leo's comment 1:03 - 1:08: Bỏ "Điểm thấy hơi tiếc là không có nhiều sauce đi kèm lắm" nội dung này sẽ làm hạn chế nhu cầu khách hàng. Có thể giữ idea "mua gà về rồi tự chế sauce ăn kèm" để mang tính sáng tạo | AA12: https://drive.google.com/file/d/1VYvbOQfbuMKOKGFAvVH6GgciZr8rN3NX/view?usp=drivesdk | AB12: Confirm | AD12: muốn ăn gà rán ngon, giá HSSV, đa dạng lựa chọn thì ghé Five Star | AE12: Đổi thành giá siêu hời / giá dễ tiếp cận | AF12: muốn ăn gà rán ngon, giá siêu hời, đa dạng lựa chọn thì ghé Five Star | AG12: 46362
A13: 9 | B13: Đi Ăn Chưa 🍪 | H13: Sản xuất và đăng tải 01 Tiktok Video Review sản phẩm tại điểm bán Five Star Kiosk, theo định hướng nội dung của nhãn hàng - Thời lượng: 60-120s - Chất lượng: phù hợp điện thoại - Địa điểm: tại các Five Star Kiosk ở nơi sinh sống Map Five Star Kiosk: Link "01 tháng Sử dụng hình ảnh không độc quyền trên digital only *Bao gồm: Code Ads và reup kênh brand có chạy quảng cáo" | I13: FALSE | J13: Ngày Quay: "20/5 (19h) 3) basic shop Thị Thắm: Viết Xuân - Hà Đông hà nội https://fivestarnearyou.cp.com.vn/?Longtitude=105.7684087&Latitude=20.9698673" | M13: Đã confirm lịch | N13: https://docs.google.com/spreadsheets/d/1qrkChaVikylLImYDjoO9c9LJguLywYjcZlrLUc7Q0hI/edit?gid=0#gid=0 | O13: =Draft!N12 | P13: Add thêm ý về chất lượng sản phẩm > tươi ngon, k bị bở, miếng nào chắc miếng đó, v.v | Q13: https://docs.google.com/spreadsheets/d/1qrkChaVikylLImYDjoO9c9LJguLywYjcZlrLUc7Q0hI/edit?gid=1924183939#gid=1924183939 | R13: =Draft!Q12 | S13: Trang phục ok Script ok nhé | U13: https://drive.google.com/file/d/1kQpIV8620mDHm-rlSMxU6fggdmfaQJjL/view?usp=drivesdk | V13: =Draft!U12 | W13: Đoạn đầu VO chưa match với scene Highlight thêm 1 số món xiên que như chả giò gai jor, hotdog xúc xích phô mai tẩm khoai tây, v.v. Cho màu các món tươi hơn | X13: https://drive.google.com/file/d/1z8o7htdhrZZ_rAseU7a6rqR9Js2gAuoM/view?usp=drivesdk | Y13: =Draft!X12 | Z13: 0:03: bị cắt mất địa chỉ 0:34: ""hotdog tẩm khoai tây"" -> sửa hotdog xúc xích phô mai tẩm khoai tây chỉnh thêm cho clip sáng chút - màu ok | AD13: cap:Five Star - địa điểm mà tui luôn ghé khi chưa biết ăn gì | AE13: ok | AG13: 13/6
A14: FOODY UGC | I14: FALSE | J14: =Draft!J14 | N14: =Draft!M14 | O14: =Draft!N14 | Q14: =Draft!P14 | R14: =Draft!Q14
A15: a | B15: TP HCM | I15: FALSE | J15: =Draft!J15 | N15: =Draft!M15 | O15: =Draft!N15 | Q15: =Draft!P15 | R15: =Draft!Q15
A16: 10 | B16: Nhà Mây | C16: Tiktok | D16: 187.9K | E16: Micro | F16: link | G16: Hồ Chí Minh | H16: Sản xuất và đăng tải 01 Tiktok Video Review sản phẩm tại điểm bán Five Star Kiosk, theo định hướng nội dung của nhãn hàng - Thời lượng: 60-120s - Chất lượng: phù hợp điện thoại - Địa điểm: tại các Five Star Kiosk ở nơi sinh sống Map Five Star Kiosk: Link "01 tháng Sử dụng hình ảnh không độc quyền trên digital only *Bao gồm: Code Ads và reup kênh brand có chạy quảng cáo" | I16: TRUE | J16: 16/05 - 16h00 Số 67 Đường 9, phường Trường Thọ, TP. Thủ Đức, TP. HCM | M16: Đã quay | N16: =Draft!M16 -> https://docs.google.com/spreadsheets/d/1xQ1mD1D5YIQbOnp-TcVfi31RHqUWCR8Z0vOrkp-JFkc/edit?gid=0#gid=0 | O16: =Draft!N16 | P16: - Bổ sung thêm context ở khúc đầu để rõ ý với tạo sự quen thuộc hơn > đón bé từ trường học về - Thêm góc nhìn của bé > ý kiến của bé về món ăn, reaction khi ăn > bé yêu thích như thế nào - Có thể bổ sung thêm yếu tố đa dạng, nhiều món từ ăn no tới ăn vặt - CTA chưa hấp dẫn> có thể chỉnh theo hướng "Muốn ăn nhanh, tiện mà vẫn ngon miệng thì Five Star là một option khá đáng thử" hoặc là "Hôm nào muốn đổi bữa cho đỡ ngán cơm nhà mà ko phải đi xa, thử dẫn bé ghé Five Star ăn nhanh một bữa nóng giòn nhé!" | Q16: https://docs.google.com/spreadsheets/d/1xQ1mD1D5YIQbOnp-TcVfi31RHqUWCR8Z0vOrkp-JFkc/edit?gid=1550874505#gid=1550874505 | R16: Đã update script và Outfit chờ team check | S16: Remove từ kiosk Remove từ "rẻ" Ko cần gắn địa chỉ lên video, add website CH fivestarnearyou.cp.com.vn ở phần comment | U16: https://drive.google.com/file/d/1x8QOtbLWnADBcJywmLn0W5ait-HDHlKo/view | V16: =Draft!U16 | W16: Frame 1 chưa theo sát script Remove đoạn dưới 300k > ko nhắc về giá rẻ Remove địa chỉ cuối clip > kêu gọi tới website Add text / hoặc thêm review ngắn các món xiên que, nêu tên cụ thể như hotdog xúc xích phô mai tẩm khoai tây, chả giò gai jor, gà nugget ngôi sao Màu clip tổng thể hơi tối > cho sáng lên | X16: https://drive.google.com/file/d/1keeYRqLAubhlGzyjqcHeWfszahdAURLY/view?usp=sharing | Y16: =Draft!X16 | Z16: Frame 1 chưa theo sát script 0:20 - cho clip chậm lại chút để đọc text CTA thêm ghé tiệm five star gần nhà Leo's comment: 0:16 - 0:18: Màu dầu hơi tối, chỉnh màu sáng hơn (trong trường hợp chỉnh sáng không được thì remove đoạn này) 0:40: Thoại của nhân vật con gái nói nhanh và âm thanh hơi chói, khó nghe. Nói chậm và rõ ý lại | AA16: Five Star.mp4 | AB16: Đã revise text pop up -> Confirm | AD16: "Món yêu thích của e bé nhà Mây là gà Fivestar đó cả nhà ơi #FiveStarVietnam #GaDau" | AE16: ok Leo: Hashtag - #FiveStarVietnam #GaDau #GaRan | AG16: 46271
A17: 11 | B17: Đi chill cùng Phương phiêu | C17: Tiktok | D17: 57.7K | E17: Nano | F17: link | G17: Hồ Chí Minh | H17: Sản xuất và đăng tải 01 Tiktok Video Review sản phẩm tại điểm bán Five Star Kiosk, theo định hướng nội dung của nhãn hàng - Thời lượng: 60-120s - Chất lượng: phù hợp điện thoại - Địa điểm: tại các Five Star Kiosk ở nơi sinh sống Map Five Star Kiosk: Link "01 tháng Sử dụng hình ảnh không độc quyền trên digital only *Bao gồm: Code Ads và reup kênh brand có chạy quảng cáo" | I17: FALSE | J17: 17h thứ 2 18/2 HN nha "Ngãi cầu Hà Nội | N17: =Draft!M17 -> https://docs.google.com/spreadsheets/d/1fpgklNz15kb8DM2y7cMvWmIrrpZJ52PQO1AcoqBHmEA/edit?gid=0#gid=0 | O17: =Draft!N17 | P17: - Review thêm hương vị các món xiên que (nóng hổi, thơm ngon, v.v.) - Add thêm tiếng cắn gà / tiếng ăn các món cho thêm hấp dẫn - Add thêm địa chỉ Five Star | Q17: https://docs.google.com/spreadsheets/d/1fpgklNz15kb8DM2y7cMvWmIrrpZJ52PQO1AcoqBHmEA/edit?gid=335140389#gid=335140389 | R17: Đã update script và Outfit chờ team check | S17: Trang phục ok Script ok Thêm CTA: "Xem Store gần nhất bên dưới phần comment" + Cmt link web | U17: https://drive.google.com/file/d/1Vo1WLNbMtD_wKSf6FcK2245x0oUL2Au6/view?usp=drivesdk | V17: =Draft!U17 | W17: 0:22 - giấy trên bàn > làm mờ đi vì làm hình tổng thể ko đẹp mắt Màu sắc đồ ăn cho tươi hơn, sáng hơn liệt kê các món xiên que > sử dụng đúng tên món như chả giò gai jor, hotdog xúc xích phô mai, v.v. Leo's comment: Mở bài hơi dài, tốn 18 giây (chiếm 38%) thời lượng clip => Cắt ngắn lại, giới thiệu về brand, về sản phẩm nhiều hơn 0:20 - 0:30: Nên thêm text tên món | X17: https://drive.google.com/file/d/1eF6shCgyyvjXuLPZACynSS5SwkfR5qDC/view?usp=drivesdk | Y17: =Draft!X17 | Z17: Thiếu CTA cuối clip 0:11 - clip hơi mờ > làm cho nét sharpen, rõ hơn 0:22 - sai tên món > đùi gà góc tư Leo's commet: 0:18: Vẫn còn "K" phải đợi | AD17: "Tan ca mà lười nấu ăn, thì Phương hay đến Fivestar để ăn nè. Nhanh tiện, mà giá cả quá ư là hợp lí nữa! #FiveStarVietnam #GaDau" | AE17: Caption ko hấp dẫn, chưa highlight dc vị ngon / điểm làm FS đặc biệt > nhanh, tiện, hợp vệ sinh là điều cơ bản hệ thống fastfood nào cũng phải có | AF17: """Tan ca mà lười nấu ăn, thì Phương hay đến Fivestar để ăn nè. Nhanh tiện, mà giá cả quá ư là hợp lí nữa! #FiveStarVietnam #GaDau""" | AG17: 46332
A18: 12 | B18: 🍊𝐕 𝐈 𝐓 𝐀 𝐌 𝐈 𝐍 𝐂🍊 | C18: Tiktok | D18: 10.1K | E18: Nano | F18: link | G18: Hồ Chí Minh | H18: Sản xuất và đăng tải 01 Tiktok Video Review sản phẩm tại điểm bán Five Star Kiosk, theo định hướng nội dung của nhãn hàng - Thời lượng: 60-120s - Chất lượng: phù hợp điện thoại - Địa điểm: tại các Five Star Kiosk ở nơi sinh sống Map Five Star Kiosk: Link "01 tháng Sử dụng hình ảnh không độc quyền trên digital only *Bao gồm: Code Ads và reup kênh brand có chạy quảng cáo" | I18: FALSE | J18: 14/5 - 12h00 PREAMIUM KIOSK 4*3 - HKD PHAN TẤN TÀI - 223 Ấp 2, xã Bình Chánh, TP HCM | M18: Đã quay | N18: =Draft!M18 -> https://docs.google.com/spreadsheets/d/1Zs-sbAumg9ydXNKSreenvInyRfXK3lg9oVTB-V7R3bY/edit?gid=0#gid=0 | O18: =Draft!N18 | P18: - Thay vì rủ bạn NV chính đi bằng cách nói đi cái này hay nè > chỉnh thành hướng tạo cảm giác “Five Star là chỗ quen thuộc nhưng lúc nào cũng thấy thích ghé”, để tăng sự yêu thích và cảm giác đặc biệt hơn với brand. Ví dụ như : “Đi Five Star hông, lâu rồi chưa ăn lại mà tự nhiên nhớ.”, “Không biết ăn gì là auto nghĩ tới Five Star luôn á.”, “Em biết chỗ này nè, mỗi lần bí kèo ăn là lại muốn ghé.” - Review thêm về độ phủ của Five Star (ở nhiều nơi, nhất là mấy khu dân cư / trường học > tùy theo quan sát của bạn KOC) - Review thêm hương vị của các món xiên que hoặc về độ nóng, độ giòn, độ juicy / dai ngon ăn kèm sốt thì ntn - Add thêm địa chỉ Five Star | Q18: https://docs.google.com/spreadsheets/d/1Zs-sbAumg9ydXNKSreenvInyRfXK3lg9oVTB-V7R3bY/edit?gid=137961595#gid=137961595 | R18: Đã update script và Outfit chờ team check | S18: Trang phục chọn màu sắc tươi năng động hơn Remove từ kiosk Còn lại ok Thêm CTA: "Xem Store gần nhất bên dưới phần comment" + Cmt link web | U18: https://drive.google.com/drive/folders/15ODXPBRTw5WmN8MAY5ueU-3G_tHaar-8 | V18: =Draft!U18 | W18: Bỏ địa chỉ Xiên que, highlight text thêm các món đặc biệt / lạ như chả giò gai jor (bạn nữ có ăn) 0:41, hotdog xúc xích phô mai tẩm khoai tây 0:43 Đoạn show đồ ăn 0:30s trở đi > cho màu sắc tươi hơn và sáng hơn | X18: https://drive.google.com/file/d/18El277CcGBgrfq_x9z3o9IyPtWrXKCY4/view?usp=drivesdk | Y18: =Draft!X18 | Z18: Leo's comment: 0:45: "Phần da tẩm vị hơi đậm" nghe như là chê mặn hơn là khen sự đậm đà => Đổi "Phần da tẩm vị đậm đà" | AA18: https://drive.google.com/file/d/126XMma-dkzPcV3-Uut9x2qxhXLqiFHIR/view?usp=drivesdk | AB18: Confirm (Add CTA / share địa chỉ Five Star) | AD18: "Mấy ngày công việc nhiều, không biết ăn gì thì Fivestar là món ngon mà 2 vợ chồng mình chọn #FiveStarVietnam #GaDau" | AE18: Leo: Ok | AG18: 46271
A19: 13 | B19: Chu Cao Food | C19: Tiktok | D19: 67.4K | E19: Nano | F19: Link | G19: Hồ Chí Minh | H19: Sản xuất và đăng tải 01 Tiktok Video Review sản phẩm tại điểm bán Five Star Kiosk, theo định hướng nội dung của nhãn hàng - Thời lượng: 60-120s - Chất lượng: phù hợp điện thoại - Địa điểm: tại các Five Star Kiosk ở nơi sinh sống Map Five Star Kiosk: Link "01 tháng Sử dụng hình ảnh không độc quyền trên digital only *Bao gồm: Code Ads và reup kênh brand có chạy quảng cáo" | I19: FALSE | J19: T2 18/05 15h BASIC SHOP - Nguyễn Thị Thuận - Số 67 Đường 9, phường Trường Thọ, TP. Thủ Đức, TP. HCM | M19: Đã confirm lịch | N19: =Draft!M19 -> https://docs.google.com/spreadsheets/d/191E4WQVYqKQGCKUc6VNpr6XcIAnFaPVzZakBmOWs_dE/edit?gid=0#gid=0 | O19: =Draft!N19 | P19: - Khi nói về mọng nước, có thể quay cận cảnh miếng gà - Nên có khúc trả lời cho câu "Hôm nay mình ăn thử lại xem còn ngon như trong trí nhớ không nha." - Add thêm địa chỉ Five Star | Q19: https://docs.google.com/spreadsheets/d/191E4WQVYqKQGCKUc6VNpr6XcIAnFaPVzZakBmOWs_dE/edit?gid=476608211#gid=476608211 | S19: Remove từ Kiosk Còn lại ok, Thêm CTA: "Xem Store gần nhất bên dưới phần comment" + Cmt link web | U19: https://drive.google.com/drive/folders/10RsGeU0svEawSYop60YVJ8WO2n4-KhtB | V19: =Draft!U19 | W19: - Đoạn đầu đang khác script "" kiểu đang không biết ăn gì mà cứ đi ngang thấy Five Star là tự động tấp vô"" - Âm thanh đang chưa ổn định, lúc to lúc nhỏ - Có thể treat text theo kiểu khác thay vì pop up từng chữ "- Ko để địa chỉ, chỉ share phần link địa chỉ ở comment - Giọng VO khó nghe, như có tiếng ồn giọng hơi nghẹt - Cho tiếng rán to hơn 1:20 - tên món là: HOTDOG XÚC XÍCH PHÔ MAI TẨM KHOAI TÂY" Nhi's comment: - 1:59: sai lỗi chính tả "recommend" - Voice chưa trôi chảy, nhiều từ "kiểu như là", à ờ hơi nhiều Leo's comment: - Nguyên video chỗ nào có hiệu ứng text bay phấp phới thì bỏ hết - 00:22: Bỏ "đông đông vui vui" cảnh trước vắng cảnh sau nói đông vui không khớp - 00:28: Bỏ source nhún nhảy + vuốt tóc bấm điện thoại, giữ thông tin chờ món nhanh ... thay bằng source hình khác - 00:34: Nghe tiếng xèo xèo nên đi kèm với source chiên gà. Thích lớp da vàng giòn nên đi kèm với source cầm miếng gà. Hiện tại tiếng và hình đang lệch nhau (cảm giác tiếng đi trước, hình theo sau) - 00:41: Giọng nghẹt nghe không rõ, "không có bị khô" dễ nghe thành "không có bị hôi" => fix âm thanh - 00:43: Nhìn "miếng gà thấy tan trong miệng luôn" nghe kì, không tạo cảm giác giòn, đổi thành "nhìn miếng gà màu vàng ươm sau khi mới chiên, cảm giác sẽ giòn rụm khi nhai luôn á" - 00:53: "Ở đây là một cái thức ăn nhanh, ăn xong thấy khá chất lượng luôn" > chỉnh lại "Đây là chuỗi thức ăn nhanh có gà rán và nhiều món nữa, mà nãy giờ ăn tui thấy chất lượng khá là tốt luôn" - 01:03: Remove source cầm dĩa gà khá trống nhưng lại nói đầy đặn, nghe hơi miễn cưỡng. "Giá phù hợp cho một (phần/người)? => Edit lỗi, fix. - 02:01: Bỏ "ăn mấy món này về tập thể dục đã luôn" - 02:09: Bỏ " FS lúc nào cũng có người đứng ăn". Bỏ "tiêu chí thứ nhất" vì sau khi liệt kê cũng không có thêm tiêu chí 2 và 3 nên không cần thiết | X19: FIVE STAR - Chu Cao Food | Z19: Tiếng hơi lớn hơi bị ồm 0:33 & 1:27 - lúc bạn nói chưa match với VO | AA19: https://drive.google.com/file/d/1Ee_jefL9ivLqDX_6vK1glOjjKN7Q7wHX/view?usp=drivesdk | AB19: Nhiều chỗ VO ko khớp > có thể thay scene cho phù hợp Giảm bớt độ lớn của VO Leo's comment: Tiếng hơi rè, không khớp hình. 0:30 - 0:36 nói cái gì không hiểu, lặp từ "đặc biệt", "bị hôi" là sao? 1:02 - 1:05 "chả cá hàn quốc, dog, xúc xích đức, hô mai..." ???? Không thể hiểu được đang lồng nội dung gì | AD19: Nếu hôm nay chưa biết ăn gì thì thử tự thưởng cho mình 1 phần gà Five Star nha 😭🍗 #FiveStarVietnam #GaDau | AE19: Có clip chưa ha? Về caption - Five Star ko chỉ có gà > highlight là Gà & các món ăn vặt - ăn no | AF19: "Tui muốn ăn gà, mà người iu tui muốn ăn xiên que. Hổng sợ tranh nhau nữa vì tui đã có Fivestar, đa dạng món ăn mà ngon bổ rẻ #FiveStarVietnam #GaDau" | AG19: 46179
A20: 14 | B20: Hi Ân nè | C20: Tiktok | D20: 6489 | E20: Nano | F20: link | G20: Hồ Chí Minh | H20: Sản xuất và đăng tải 01 Tiktok Video Review sản phẩm tại điểm bán Five Star Kiosk, theo định hướng nội dung của nhãn hàng - Thời lượng: 60-120s - Chất lượng: phù hợp điện thoại - Địa điểm: tại các Five Star Kiosk ở nơi sinh sống Map Five Star Kiosk: Link "01 tháng Sử dụng hình ảnh không độc quyền trên digital only *Bao gồm: Code Ads và reup kênh brand có chạy quảng cáo" | I20: FALSE | J20: 13h00 15/5, thứ 6 BASIC SHOP - Nguyễn Thị Thuận - Số 67 Đường 9, phường Trường Thọ, TP. Thủ Đức, TP. HCM | M20: Đã quay | N20: =Draft!M20 -> https://docs.google.com/spreadsheets/d/14zMYJFq84bLogXppl5iBijvsYFm90xU8MuxJDdbrRZ4/edit?gid=0#gid=0 | O20: =Draft!N20 | P20: - Bổ sung thêm context hoặc cảm xúc cá nhân / đặc điểm unique mà bạn thấy Fivestar có mà chỗ khác chưa có để tạo sự khác biệt, gần gũi và đáng nhớ cho ng xem hơn | Q20: https://docs.google.com/spreadsheets/d/14zMYJFq84bLogXppl5iBijvsYFm90xU8MuxJDdbrRZ4/edit?gid=1983410445#gid=1983410445 | S20: Thêm CTA: "Xem Store gần nhất bên dưới phần comment" + Cmt link web Script và trang phục ok | U20: https://drive.google.com/file/d/19qrXjrJe-qlyzar7iRfiheO-QPwlJR4O/view?usp=drive_link | V20: =Draft!U20 | W20: Màu các món hơi tối, chưa dc tươi Bỏ chỉ có 9k, chỉ có 10k, chưa tới 300 > ko highlight việc rẻ, có thể nói giá hời (theo script) Five star chicken > remove chữ chicken, font chữ đang để shading đen làm che món ăn Remove địa chỉ | X20: https://drive.google.com/file/d/18J0RawbXOkA9mYVVANfpCAohF9Hrz5TD/view?usp=drivesdk | Y20: =Draft!X20 | Z20: 0:39 - 0:43: nói tên các món xiên que + chèn thêm text Leo's comment: 0:32 - 0:33: Remove, nhìn phần thịt và xương không đủ juicy, không tạo cảm giác mềm mọng | AA20: https://drive.google.com/file/d/1F0SA7JeRx1EqdmlRkFGSBF_SaabxMNu8/view?usp=drivesdk | AB20: Confirm | AD20: Mỗi lần thèm đồ chiên là trong đầu chỉ hiện lên Five Star thôi á 🍗✨ #FiveStarVietnam #GaDau | AE20: Ok | AG20: 46118 | AH20: https://vt.tiktok.com/ZSQJJgvLk/
A21: 15 | B21: vuvicungyuhi | C21: Tiktok | D21: 82.9K | E21: Nano | F21: https://www.tiktok.com/@vuvicungyuhi | G21: Hồ Chí Minh | H21: Sản xuất và đăng tải 01 Tiktok Video Review sản phẩm tại điểm bán Five Star Kiosk, theo định hướng nội dung của nhãn hàng - Thời lượng: 60-120s - Chất lượng: phù hợp điện thoại - Địa điểm: tại các Five Star Kiosk ở nơi sinh sống Map Five Star Kiosk: Link "01 tháng Sử dụng hình ảnh không độc quyền trên digital only *Bao gồm: Code Ads và reup kênh brand có chạy quảng cáo" | I21: FALSE | J21: Thời gian: 13/5 - 11h00 7. OUTLET - HKD GÀ RÁN FIVE STAR THU HÀ - 37/3 Huỳnh Tấn Phát, Xã Nhà Bè, TPHCM | M21: Đã quay | N21: https://docs.google.com/spreadsheets/d/1hY2b8b5_EtKYxGXaNgirKjOArXXbMdXlIgAe3-7WkNw/edit?gid=0#gid=0 | O21: =Draft!N21 | P21: Trang phục năng động hơn, màu tươi hơn - Idea opening về việc từng thấy kiosk Five Star ở Thái ok, - Đoạn nói về “gà rán Thái Lan” hơi chưa thực tế vì thực ra trải nghiệm khác biệt giữa Thái và Việt Nam chủ yếu nằm ở phần sốt/vị địa phương hóa hơn là bản thân món gà. - Đoạn “không biết ở Việt Nam cũng có Five Star” đang chưa tự nhiên và thiếu hợp lý. Có thể chỉnh theo hướng cảm giác bất ngờ vì gặp lại brand từng thấy ở VN ngay tại Thái Lan > nên giờ muốn thử để xem có giống vị ko. - Chỉnh lại "Five Star là thương hiệu thức ăn nhanh đến từ Thái Lan với hơn 5000 điểm bán, thuộc tập đoàn CP Việt Nam" > Five Star là thương hiệu thức ăn nhanh đến từ tập đoàn CP của Thái Lan với gần 1000 điểm bán. | Q21: https://docs.google.com/spreadsheets/d/1hY2b8b5_EtKYxGXaNgirKjOArXXbMdXlIgAe3-7WkNw/edit?gid=0#gid=0 | R21: Team đã update outfit + script | S21: "Remove từ khóa ""bình dân"" Còn lại ok Thêm CTA: "Xem Store gần nhất bên dưới phần comment" + Cmt link web | U21: https://drive.google.com/file/d/1wQIqstwbnbealKyyFsN0sumUkzSEeYAn/view?usp=drivesdk | V21: =Draft!U21 | W21: 0:51 - Remove keyword "Giá cả bình dân" hoặc thay bằng "giá cả hợp lý" Remove đoạn chỉ từ 10-25k luôn Khi liệt kê các món xiên que > bên cạnh bò viên, cá viên thì đặc biệt còn có các món chả giò Gai Jor, Chả cá hàn quốc chiên | X21: https://drive.google.com/file/d/1KeJ_kihAFCrhD7fNant8IKnYB43OjuCU/view?usp=drivesdk | Y21: =Draft!X21 | Z21: đoạn này bạn chưa sửa: chả giò Gai Jor, Chả cá hàn quốc chiên, xúc xích sumo Mấy đoạn bạn cầm hộp thức ăn màu bị lạnh, chưa tươi | AA21: https://drive.google.com/file/d/16bpYZ2ZbxWQPkEa828FQZyQTt6JkgZ9U/view?usp=drivesdk | AB21: Confirm | AD21: Thử gà rán Fivestar chưa mấy bà? | AE21: Ok | AG21: 46059 | AH21: https://www.tiktok.com/@vuvicungyuhi/video/7645645226396241160?is_from_webapp=1&sender_device=pc&web_id=7637478982196135431
A22: 16 | B22: Koi Nam Ăng | C22: Tiktok | D22: 70.5K | E22: Nano | F22: https://www.tiktok.com/@koinamang | G22: Hồ Chí Minh | H22: Sản xuất và đăng tải 01 Tiktok Video Review sản phẩm tại điểm bán Five Star Kiosk, theo định hướng nội dung của nhãn hàng - Thời lượng: 60-120s - Chất lượng: phù hợp điện thoại - Địa điểm: tại các Five Star Kiosk ở nơi sinh sống Map Five Star Kiosk: Link "01 tháng Sử dụng hình ảnh không độc quyền trên digital only *Bao gồm: Code Ads và reup kênh brand có chạy quảng cáo" | I22: FALSE | J22: Thời gian quay: 14/5 - 10h00 MINI SHOP - Five Star Mega Q12 - Số 2 đường Trương Thị Hoa, KP 4A, Tân Thới Hiệp, TPHCM | M22: Đã quay | N22: https://docs.google.com/spreadsheets/d/1ElUYUftJAo28QUTzMDf6W8D9d5rKU9kobs52VaXPhHo/edit?gid=0#gid=0 | O22: =Draft!N22 | P22: - Đổi màu áo vàng hoặc đỏ nha - Giá mềm > đổi hết thành giá hợp lý hoặc chất lượng so với giá - Nếu được có thể bổ sung thêm vài tình huống/thời điểm cụ thể để gợi mở nhu cầu ăn một cách tự nhiên hơn, giúp Five Star xuất hiện như lựa chọn quen thuộc trong nhiều khoảnh khắc hằng ngày. - Add địa chỉ FS bạn ghé | Q22: https://docs.google.com/spreadsheets/d/1ElUYUftJAo28QUTzMDf6W8D9d5rKU9kobs52VaXPhHo/edit?gid=409127678#gid=409127678 | R22: Team đã update outfit + script | S22: Script và trang phục ok Thêm CTA: "Xem Store gần nhất bên dưới phần comment" + Cmt link web | U22: https://drive.google.com/file/d/1_ZH_c0Qo6GswWsr-zONSIpj6y2RG5PCK/view?usp=drivesdk | V22: =Draft!U22 | W22: Spaghetty > sai chính tả > spaghetti 0:01 > làm blur cái túi màu vàng trên tủ > che cái túi này trong mọi frame xuất hiện Bỏ giá Xúc xích sumo 0:09 Chả giò Gai Jor > ko phải chả giò xiên que 0:10 Hotdog xúc xích phô mai tẩm khoai tây Gà nugget hình ngôi sao Màu hơi ám xanh, màu sắc chưa tươi Xúc xích vs phô mai que > cũng cũng chưa đặc biệt > có thể remove cảnh này luôn nếu bạn thấy ko ngon | X22: https://drive.google.com/file/d/1LNhGaEE6QISIynkDb-q-U5JMbX22yDom/view?usp=drivesdk | Y22: =Draft!X22 | Z22: 1:05 - sai VO > chả giò xiên que > chả giò gai jor Leo's comment: 0:07: Sai tên xúc xích => Đổi thành "Xúc xích Horapa" 0:09: Sai tên => Đổi thành "Xúc xích hotdog phô mai tẩm khoai tây" 0:07 - 0:12: Tạp âm => Fix âm thanh 0:13 - 0:16: Remove, không quay cho pepsi | AA22: https://drive.google.com/file/d/1f8AMm7IEJ9TmpSEhkx8Wh6bMl_R-maIr/view?usp=drivesdk | AB22: Confirm | AD22: Lần đầu ăn thử Five Star ?? | AE22: Ok nh chưa có cllip final | AG22: 46118
A23: 17 | B23: Vie ở sài gòn | C23: Tiktok | D23: 64.7K | E23: Nano | F23: link | G23: Hồ Chí Minh | H23: Sản xuất và đăng tải 01 Tiktok Video Review sản phẩm tại điểm bán Five Star Kiosk, theo định hướng nội dung của nhãn hàng - Thời lượng: 60-120s - Chất lượng: phù hợp điện thoại - Địa điểm: tại các Five Star Kiosk ở nơi sinh sống Map Five Star Kiosk: Link "01 tháng Sử dụng hình ảnh không độc quyền trên digital only *Bao gồm: Code Ads và reup kênh brand có chạy quảng cáo" | I23: TRUE | J23: - 11-12h ngày 14/5 - MINI SHOP - Five Star Mega Q12 - Số 2 đường Trương Thị Hoa, KP 4A, Tân Thới Hiệp, TPHCM | M23: Đã quay | N23: =Draft!M23 -> https://docs.google.com/spreadsheets/d/1sFqEAfN8N0lcOoXThx0t58Z8JdMal5nNG1sEjaYr_5A/edit?gid=1051730808#gid=1051730808 | O23: =Draft!N23 | P23: - Khi nói về giá dễ chịu, nhắc kèm với chất lượng món. Ví dụ: Khẩu phần / chất lượng thơm ngon an toàn - CTA ghé Five Star + add địa chỉ - Trang phục ok | Q23: https://docs.google.com/spreadsheets/d/1sFqEAfN8N0lcOoXThx0t58Z8JdMal5nNG1sEjaYr_5A/edit?gid=1560319503#gid=1560319503 | R23: =Draft!Q23 | S23: Script ok | U23: DEMO | W23: Khúc cuối thiếu CTA Remove đoạn "chỉ hơn 200k", chỉ cần highlight giá hợp lý chất lượng món ăn > đoạn này ko có trong script Món ăn cho màu tươi hơn, khúc gần kính bị ám xanh | X23: Revised R1.mp4 | Z23: có thể thêm text - Chicken nugget hình ngôi sao Nhi's comment 0:37 - Lúc này hành động đang là xé miếng gà thì nên nhắc đến "gà giòn rụm, bên trong mọng nước" sẽ hợp lý hơn còn lại ok | AA23: Revised R2.mp4 | AB23: Confirm | AD23: CAPTION: Đồ ăn ngon sẽ làm mọi người có mood lại | AE23: Ok | AG23: 27/5 | AH23: https://www.tiktok.com/@vieinhcm/video/7644541637095443720?_r=1&_t=ZS-96iB9ChjAgv
A24: b | B24: Khu Vực miền Bắc
A25: 18 | B25: Dương Bảo Anh | C25: Tiktok | D25: 20.1K | E25: Nano | F25: https://www.tiktok.com/@duongbaoanh2kk?_r=1&_t=ZS-94n5aTW7D9A | G25: Hà Nội | H25: Sản xuất và đăng tải 01 Tiktok Video Review sản phẩm tại điểm bán Five Star Kiosk, theo định hướng nội dung của nhãn hàng - Thời lượng: 60-120s - Chất lượng: phù hợp điện thoại - Địa điểm: tại các Five Star Kiosk ở nơi sinh sống Map Five Star Kiosk: Link "01 tháng Sử dụng hình ảnh không độc quyền trên digital only *Bao gồm: Code Ads và reup kênh brand có chạy quảng cáo" | I25: FALSE | J25: 11h30 ngày 19/5 1) shop Five star ngãi cầu: Ngã 3 ngãi cầu - an khánh- Hà Nội https://fivestarnearyou.cp.com.vn/?Longtitude=105.72529189288616&Latitude=20.990128247353965 | M25: Đã confirm lịch | N25: =Draft!M25 -> https://docs.google.com/spreadsheets/d/1v_4l8kffwO5HDSDp9f0NMZ20h7cM9EQfqTMr2OwgAO4/edit?gid=0#gid=0 | O25: =Draft!N25 | P25: - Không dùng từ rẻ > giá hợp lý, mềm, dễ chịu - CTA khúc cuối > bổ sung ý như đoạn opening là kêu gọi ghé khi bận bù đầu mà vẫn muốn ăn gì ngon tiện nhanh | Q25: https://docs.google.com/spreadsheets/d/1v_4l8kffwO5HDSDp9f0NMZ20h7cM9EQfqTMr2OwgAO4/edit?gid=544064614#gid=544064614 | S25: Script & trang phục ok Thêm CTA: "Xem Store gần nhất bên dưới phần comment" + Cmt link web | U25: https://drive.google.com/drive/folders/17OaMFofAT9QZKayRtDBwvKrEDFY0qFNi | V25: =Draft!U25 | W25: Bỏ hình con gà ở trên Five Star 0:19, đằng sau dây điện lòng thòng hơi khó coi > có cách nào làm mờ đi ko cho màu đồ ăn sáng hơn 0:33 Bỏ chữ product hook_xiên que (trong VO và text) CTA dẫn đến các quán Five Star gần đó Leo's comment: 0:20 - 0:23: Kéo sáng, bàn ăn nhìn tối | X25: Five Star( dương bảo anh) | Y25: =Draft!X25 | Z25: 0:19 - vẫn có dây điện lòng thòng ở sau > làm mờ còn lại ok Leo's comment: - 0:10: Thay giúp bằng hiệu ứng làm mờ hoặc hình chữ nhật trắng để che hẵn, đang bôi bằng tay nhìn hơi nham nhở | AD25: Đồ ăn nhanh nhưng trải nghiệm thì không hề “qua loa” nha mí mom ơi 😭🍗 #FiveStarVietnam #GaDau | AE25: Caption Ok | AG25: 16/6
A26: 19 | B26: Nguyệt Thư | C26: Tiktok | D26: 45000 | E26: Nano | F26: tiktok.com/@vunguyetthu | G26: Hải Dương | H26: Sản xuất và đăng tải 01 Tiktok Video Review sản phẩm tại điểm bán Five Star Kiosk, theo định hướng nội dung của nhãn hàng - Thời lượng: 60-120s - Chất lượng: phù hợp điện thoại - Địa điểm: tại các Five Star Kiosk ở nơi sinh sống Map Five Star Kiosk: Link "01 tháng Sử dụng hình ảnh không độc quyền trên digital only *Bao gồm: Code Ads và reup kênh brand có chạy quảng cáo" | I26: FALSE | J26: 18/5 - 11h45 - Hà Nội cô Sâu thích đi chơ 4) outlet CN Phố xóm Yên Nghĩa | M26: Đã confirm lịch | N26: =Draft!M26 -> https://docs.google.com/spreadsheets/d/1cj90244KvR8OqH9KZFgowQ9lYz0p3GYlqiGHupXlQK4/edit?gid=0#gid=0 | O26: =Draft!N26 | P26: Ko dùng từ khóa rẻ, ko đắt > đổi thành "giá mềm, dễ chịu, giá hời" Highlight thêm về chất lượng > tươi ngon, khẩu phần hay miếng gà chất lượng,v.v. Trang phục ok | S26: Thêm CTA: "Xem Store gần nhất bên dưới phần comment" + Cmt link web | U26: https://drive.google.com/drive/folders/1YndvQ1ScckTHVKucJFIX6S6MjM8RgtrG | V26: =Draft!U26 | W26: Màu hơi lạnh > cho tươi hơn khúc 0:41 > tiếng cắn giòn ko khớp với hình 0:57 - chả giò gai jor 0:58 - gà nướng - đùi góc tư 0:58 - hot dog xúc xích phô mai tẩm khoai tây | X26: https://drive.google.com/drive/folders/1YndvQ1ScckTHVKucJFIX6S6MjM8RgtrG | Y26: =Draft!X26 | Z26: ok | AA26: https://drive.google.com/drive/folders/1YndvQ1ScckTHVKucJFIX6S6MjM8RgtrG | AB26: Confirm | AD26: Ăn thử một lần là hiểu vì sao tui recommend Five Star hoài 😭 #FiveStarVietnam #GaDau | AE26: Ok | AG26: 46148 | AH26: https://www.tiktok.com/@vunguyetthu/video/7647513882709314834
A27: 20 | B27: Nguyen Mai Ha My | C27: Tiktok | D27: 47.9K | E27: Nano | F27: https://www.tiktok.com/@ng.hamii | G27: Hà Nội | H27: Sản xuất và đăng tải 01 Tiktok Video Review sản phẩm tại điểm bán Five Star Kiosk, theo định hướng nội dung của nhãn hàng - Thời lượng: 60-120s - Chất lượng: phù hợp điện thoại - Địa điểm: tại các Five Star Kiosk ở nơi sinh sống Map Five Star Kiosk: Link "01 tháng Sử dụng hình ảnh không độc quyền trên digital only *Bao gồm: Code Ads và reup kênh brand có chạy quảng cáo" | I27: FALSE | J27: Thời gian: 15/5 - 12h00 3) basic shop Thị Thắm: Viết Xuân - Hà Đông hà nội | M27: Đã quay | N27: https://docs.google.com/spreadsheets/d/1-Tou9o64WjWdG5dHbESWyKyghnsgtgjtYtvRWVBT8eM/edit?gid=0#gid=0 | O27: =Draft!N27 -> PMAX Note: Kênh thường không xây dựng kịch bản chi tiết. mà muốn lồng ghép tuyến nội dung tự nhiên phù hợp với kênh. nên chỉ lên khung kịch bản và sẽ follow sát theo brief từ brand team | P27: - Bổ sung thêm tình huống hoặc thời điểm hoặc lý do để thuyết phục người xem ghé Five Star. Ví dụ như: những hôm thèm gà ngang mà ko biết đi đâu, down mood, v.v. | Q27: https://docs.google.com/spreadsheets/d/1-Tou9o64WjWdG5dHbESWyKyghnsgtgjtYtvRWVBT8eM/edit?gid=1629455125#gid=1629455125 | R27: Team đã update outfit + script | S27: Remove từ kiosk Còn lại ok Thêm CTA: "Xem Store gần nhất bên dưới phần comment" + Cmt link web | U27: https://drive.google.com/drive/folders/1IoEjLiuFyydLpkFb1FZlOKKYhvHwsAKU | V27: =Draft!U27 | W27: chỉnh lại chút > ko thua gì các brand gà rán khác > thay vì brand lớn Gà nugget hình ngôi sao | X27: https://drive.google.com/drive/folders/1IoEjLiuFyydLpkFb1FZlOKKYhvHwsAKU | Y27: =Draft!X27 | Z27: 0:20: sửa text "gà nugget" -> gà nugget hình ngôi sao | AA27: https://drive.google.com/drive/folders/1IoEjLiuFyydLpkFb1FZlOKKYhvHwsAKU | AB27: Confirm | AD27: "Gà ở đây vỏ siêu giòn mà sốt chua ngọt cũng ngonn cáa ✨ " | AG27: 46362
A28: 21 | B28: Tuấn food không phét | C28: Tiktok | D28: 18.5K | E28: Nano | F28: https://www.tiktok.com/@tuanfoodkhongphet | G28: Hà Nội | H28: Sản xuất và đăng tải 01 Tiktok Video Review sản phẩm tại điểm bán Five Star Kiosk, theo định hướng nội dung của nhãn hàng - Thời lượng: 60-120s - Chất lượng: phù hợp điện thoại - Địa điểm: tại các Five Star Kiosk ở nơi sinh sống Map Five Star Kiosk: Link "01 tháng Sử dụng hình ảnh không độc quyền trên digital only *Bao gồm: Code Ads và reup kênh brand có chạy quảng cáo" | I28: TRUE | J28: 19/5 ( 19h30) 3) basic shop Thị Thắm: Viết Xuân - Hà Đông hà nội https://fivestarnearyou.cp.com.vn/?Longtitude=105.7684087&Latitude=20.9698673 | M28: Đã confirm lịch | N28: https://docs.google.com/spreadsheets/d/1dJYfbH8b6VPdopiloXVCki9tb8tEfNmJswmXBej_IuY/edit?gid=0#gid=0 | O28: =Draft!N28 | P28: Trang phục ok - Bổ sung thêm tình huống hoặc thời điểm hoặc lý do để thuyết phục người xem ghé Five Star. Ví dụ như: những hôm thèm gà ngang mà ko biết đi đâu, down mood, v.v. - Review luôn các món khác bên cạnh gà nha | Q28: https://docs.google.com/spreadsheets/d/1dJYfbH8b6VPdopiloXVCki9tb8tEfNmJswmXBej_IuY/edit?gid=2147041016#gid=2147041016 | R28: Team đã update outfit + script | S28: Khúc đầu đang theo hướng ngon mà giá ok > chỉnh lại: gà rán siêu ngon mà còn chất lượng, tiện lợi mà giá mềm | U28: https://drive.google.com/file/d/1i5y7qeKhPxPWxi9rUEcOqDfE-RruS7Ds/view?usp=drivesdk | V28: =Draft!U28 | W28: Bỏ thoại chỉ có 39k Viên chiên > đọc tên của các món thay tên xiên que thông thường như trong order của bạn có > chả giò gai jor, hot dog xúc xích phô mai tẩm khoai tây | X28: https://drive.google.com/file/d/1UBhSebjZtII_oloZVUbhXPWoijbkfptQ/view?usp=drivesdk | Y28: =Draft!X28 | Z28: phần xiên que ko có VO thì có thể gắn text, same comment | AA28: https://drive.google.com/file/d/1ZRnaN3wKQ3O_eeiVTHfU_XCsfByghDlc/view?usp=drivesdk | AB28: VO > remove các từ kháo rẻ còn lại ok | AD28: "Quán gà rán tủ tui mê có nhiều cơ sở lắm nè mọi người đã thử chưa ?" | AE28: Caption Ok nhưng chưa có clip final | AG28: 46209
A29: 22 | B29: Bánh Ú 🇻🇳 | C29: Tiktok | D29: 22.6K | E29: Nano | F29: https://www.tiktok.com/@banhudaayyy?_r=1&_t=ZS-96SZmB6SpNM | G29: Hà Nội | H29: Sản xuất và đăng tải 01 Tiktok Video Review sản phẩm tại điểm bán Five Star Kiosk, theo định hướng nội dung của nhãn hàng - Thời lượng: 60-120s - Chất lượng: phù hợp điện thoại - Địa điểm: tại các Five Star Kiosk ở Tp. HCM Map Five Star Kiosk: Link "01 tháng Sử dụng hình ảnh không độc quyền trên digital only *Bao gồm: Code Ads và reup kênh brand có chạy quảng cáo" | I29: FALSE | J29: 19h 25/5 Nguyễn Viết Xuân - Hà Đông - Hà Nội | N29: https://docs.google.com/spreadsheets/d/16r94Uhc-qr9PG0gK2UeQAbXC_QauJPiw69iHxyJwxcc/edit?usp=sharing | U29: https://drive.google.com/file/d/1TLD5wGiqwJt9CCm74kCtjLmacn9Q_Kdm/view?usp=drivesdk | V29: =Draft!U28 | W29: 0:36 - 0:40: thêm text tên các món ăn 0:39: sai tên món -> chả giò gai jor" 0:08 - màu sắc ok nhưng quầy bị tối 0:48 - khi quán hơi đông > cảnh đằng sau vắng > ko hợp lý lắm > có thể remove VO nói khi quán đông | X29: https://drive.google.com/file/d/1rlzwgOq0PWq6fG1dmeEl0LV5iYQonkOI/view?usp=drivesdk | Y29: =Draft!X28 | AD29: Gà rán ngon lại gần nhà thì chỉ có Five Star | AE29: Caption Ok | AG29: 16/6
A30: c | B30: Khu vực miền Nam
A31: 23 | B31: Zăn Zăn Daily ✨ | C31: Tiktok | D31: 60K | E31: Nano | F31: https://www.tiktok.com/@zan.riviu?_r=1&_t=ZS-94n3uOkLyE8 | G31: Bình Dương | H31: Sản xuất và đăng tải 01 Tiktok Video Review sản phẩm tại điểm bán Five Star Kiosk, theo định hướng nội dung của nhãn hàng - Thời lượng: 60-120s - Chất lượng: phù hợp điện thoại - Địa điểm: tại các Five Star Kiosk ở Tp. HCM Map Five Star Kiosk: Link "01 tháng Sử dụng hình ảnh không độc quyền trên digital only *Bao gồm: Code Ads và reup kênh brand có chạy quảng cáo" | I31: FALSE | J31: T4 15h 13/05 BASIC SHOP - Nguyễn Thị Thuận - Số 67 Đường 9, phường Trường Thọ, TP. Thủ Đức, TP. HCM | M31: Đã quay | N31: =Draft!M31 -> https://docs.google.com/spreadsheets/d/1ZhzA7f0EEVZSZERZ6T98bKeCW85zp9ua9X8yo01_CDM/edit?gid=0#gid=0 | O31: =Draft!N31 -> Đổi trang phục theo Tone mood brand | P31: - Review thêm vị của 1 số món khác cạnh Gà - Add text địa chỉ kiosk | Q31: https://docs.google.com/spreadsheets/d/1ZhzA7f0EEVZSZERZ6T98bKeCW85zp9ua9X8yo01_CDM/edit?gid=871204788#gid=871204788 | S31: Script & trang phục ok Thêm CTA: "Xem Store gần nhất bên dưới phần comment" + Cmt link web | U31: https://drive.google.com/file/d/1bRU2TqH8q5zPYkAQuTaWxdYHemFj0fd_/view?usp=drivesdk | V31: =Draft!U31 | W31: Tên món xiên que > đọc tên hay chèn text chính xác tên 0:58: có hai mẹ con nên ko thấy đông khách lắm > remove VO nói đông khách Leo's comment: 0:34: Bỏ VO "chả quế" không có món này trong menu | X31: https://drive.google.com/file/d/1nOym0BHk3CDWARQsI_YUwBTK9Yz2JPGx/view?usp=drivesdk | Y31: =Draft!X31 | Z31: Vẫn thiếu CTA Add text đúng các tên món xiên que bạn show | AD31: Ngày mưa mà muốn ăn gà rán cùng với các loại xiên qua thì cứ tới Fivestar nha mng. Đồ ăn nóng hổi, giòn giòn mà giá cả quá hợp lí | AG31: 13/6
A32: 24 | B32: Phương Đi Chill 🌈 | C32: Tiktok | D32: 13600 | E32: Nano | F32: https://www.tiktok.com/@phuongoychillthoy | G32: Đồng Nai | H32: Sản xuất và đăng tải 01 Tiktok Video Review sản phẩm tại điểm bán Five Star Kiosk, theo định hướng nội dung của nhãn hàng - Thời lượng: 60-120s - Chất lượng: phù hợp điện thoại - Địa điểm: tại các Five Star Kiosk ở Tp. HCM Map Five Star Kiosk: Link "01 tháng Sử dụng hình ảnh không độc quyền trên digital only *Bao gồm: Code Ads và reup kênh brand có chạy quảng cáo" | I32: FALSE | J32: thứ 7 ngày 16/5 lúc 18h 3) basic shop Thị Thắm: Viết Xuân - Hà Đông hà nội https://fivestarnearyou.cp.com.vn/?Longtitude=105.7684087&Latitude=20.9698673 | M32: Đã quay | N32: =Draft!M32 -> https://docs.google.com/spreadsheets/d/1jtk6BCNAw-jnbFSu2pxRRbrxpwCHVeCHGWt7dLAr_9E/edit?gid=0#gid=0 | O32: =Draft!N32 | P32: - Review thêm vị và chất lượng các món xiên que - "Không cần lên kế hoạch trước, không cần chờ đợi lâu, chỉ cần ghé qua là có ngay một phần ăn" > phần ăn như thế nào? - add text địa chỉ kiosk | Q32: https://docs.google.com/spreadsheets/d/1uFmHyUA8c77qUKk6WPFkRM-bCzcgemvAJT4YpHjKU1M/edit?gid=985365261#gid=985365261 | S32: còn câu chưa chỉnh - "Không cần lên kế hoạch trước, không cần chờ đợi lâu, chỉ cần ghé qua là có ngay một phần ăn" > phần ăn như thế nào > gợi ý - phần ăn siêu nhiều với giá siêu hời, phần ăn nóng hổi order là có ngay? > Có thể add thêm lúc bạn quay | U32: https://drive.google.com/file/d/1LDe8C7Hg4HgxV-t6dIn5fYfzZkjEO6l_/view?usp=drive_link | V32: =Draft!U32 | W32: Gọi tên món cho đúng nha > đùi gà góc tư tầm tiêu HÌnh xúc xích nhưng VO là chả giò Đọc tên các món xiên que cho đúng > chả giò gai jor, hot dog xúc xích phô mai tẩm khoai tây, xúc xích sumo Ko nói giá siêu hạt dẻ > giá mềm, dễ chịu, hợp lý Ko cần mention địa chỉ ở khúc đầu trên text Frame cuối nếu mention địa chỉ > kêu gọi thêm mọi người tới quán gần nhà vì Five Star có nhiều chi nhánh | X32: https://drive.google.com/file/d/13PRMu6rqiok3LdKpppBpSY2cRnLBYAi_/view?usp=drivesdk | Y32: =Draft!X32 | Z32: phù hợp với hssv, dân văn phòng > add lên text same cmt | AA32: https://drive.google.com/file/d/141U7EOEvNY_4xTolh6R8QStMFTC8eDgZ/view?usp=drivesdk | AB32: Vẫn chưa chỉnh chỗ chả giò còn lại ok | AD32: "Tiệm gà yêu thích của Phương từ thời còn là học sinh đó chính là gà Fivestar nè, tiện, gọn mà quá nhanh và quá ngon #FiveStarVietnam #GaDau" | AE32: Caption Ok nhưng chưa có clip final | AG32: 46271
A33: 25 | B33: Đức Tân Bình | C33: Tiktok | D33: 42.4K | E33: Nano | F33: https://www.tiktok.com/@huynhhongocduc | G33: Đồng Nai | H33: Sản xuất và đăng tải 01 Tiktok Video Review sản phẩm tại điểm bán Five Star Kiosk, theo định hướng nội dung của nhãn hàng - Thời lượng: 60-120s - Chất lượng: phù hợp điện thoại - Địa điểm: tại các Five Star Kiosk ở Tp. HCM Map Five Star Kiosk: Link "01 tháng Sử dụng hình ảnh không độc quyền trên digital only *Bao gồm: Code Ads và reup kênh brand có chạy quảng cáo" | I33: FALSE | J33: 16/5 - 16h - Bình Dương. Kênh: Đức Tân Bình 1. PREAMIUM KIOSK 4*3 Hộ Kinh Doanh Đỗ Thị Thu Hồng Số 98, đường Trần Tử Bình, ấp Tân Định 3, Xã Củ Chi, TP. HCM | M33: Đã quay | N33: =Draft!M33 -> https://docs.google.com/spreadsheets/d/1uFmHyUA8c77qUKk6WPFkRM-bCzcgemvAJT4YpHjKU1M/edit?gid=0#gid=0 | O33: =Draft!N33 | P33: - Chưa biết CN nào nên ko biết phải CN mới không > nên để đảm bảo thì KOC có thể đưa địa chỉ quán để team check nha, hoặc ko thì remove ý về CN mới - Không mở đầu với việc hết tiền cuối tháng > vì team ko muốn gắn liền với giá rẻ - Ko nhắc giá hạt dẻ > đổi thành giá hợp lý, giá dễ chịu, mềm | Q33: https://docs.google.com/spreadsheets/d/1lt3E1B2b2qUAC6cYVT7NB805xBZGdfWfOiL1656BC0g/edit?gid=978883368#gid=978883368 | S33: Remove từ kiosk Ko dùng từ rẻ > đổi thành hời Bạn đi CN ở củ chi > mà trong script đang để là đồng nai | U33: https://drive.google.com/file/d/1BkXcgms9Vd5tj4I2vnBxqBY-y36BHvvs/view?usp=drive_link | V33: =Draft!U33 | W33: Text khúc đầu bị khó nhìn > nhiều màu và tối 0:32 - hot dog xúc xích phô mai tẩm khoai tây, Hot dog xúc xích phô mai ko dùng từ rẻ > ko highlight việc rẻ, chỉ nói giá hời, hợp lý | X33: https://drive.google.com/file/d/1XWw1i_WFPBCcsqW9luPL694uHyFhmr2t/view?usp=drivesdk | Y33: =Draft!X33 | Z33: Leo's comment: 0:34 "Xúc xích hotdog..." chứ không phải hotdog xúc xích, chỉnh text và tiếng | AA33: https://drive.google.com/file/d/1jqPVWc0iHQs98Qo15XJ1FBDgMzWcY1E4/view?usp=drivesdk | AB33: vẫn chưa chỉnh theo feedback phần text xúc xích Gà nugget hình ngôi sao > text CTA > đến five star gần nhất ko có | AD33: Một món vừa tiện vừa dễ ăn cho cả gia đình thì tui vote Five Star nha 🍗 #FiveStarVietnam #GaDau | AE33: Caption Ok nhưng chưa có clip final | AG33: 46271
A34: 26 | B34: Nguyễn Ly | C34: Tiktok | D34: 130K | E34: Nano | F34: http://www.tiktok.com/@lysambonreview | G34: Đồng Nai | H34: Sản xuất và đăng tải 01 Tiktok Video Review sản phẩm tại điểm bán Five Star Kiosk, theo định hướng nội dung của nhãn hàng - Thời lượng: 60-120s - Chất lượng: phù hợp điện thoại - Địa điểm: tại các Five Star Kiosk ở Tp. HCM Map Five Star Kiosk: Link "01 tháng Sử dụng hình ảnh không độc quyền trên digital only *Bao gồm: Code Ads và reup kênh brand có chạy quảng cáo" | I34: FALSE | J34: 17g ngày 16/5 PREAMIUM KIOSK 4*3 - HKD PHAN TẤN TÀI - 223 Ấp 2, xã Bình Chánh, TP HCM | M34: Đã quay | N34: =Draft!M32 -> https://docs.google.com/spreadsheets/d/1jtk6BCNAw-jnbFSu2pxRRbrxpwCHVeCHGWt7dLAr_9E/edit?gid=0#gid=0 | O34: =Draft!N32 | P34: - Khúc đầu chưa có điểm nhấn, hạn chế nhắc từ review - Review kỹ hơn phần hương vị và chất lượng món ăn so với giá - Add text địa chỉ kiosk | Q34: https://docs.google.com/spreadsheets/d/1jtk6BCNAw-jnbFSu2pxRRbrxpwCHVeCHGWt7dLAr_9E/edit?gid=587180911#gid=587180911 | S34: Script & trang phục ok Thêm CTA: "Xem Store gần nhất bên dưới phần comment" + Cmt link web | U34: https://drive.google.com/drive/folders/1Sp5ULQg_Nu-h32nZnI4lP3_Pp98IGOFR | V34: =Draft!U32 | W34: Hình bạn ăn đang bị tối > sáng với tươi hơn thiếu CTA > kêu gọi các bạn tới quán Five Star gần nhất | X34: https://drive.google.com/file/d/1RirYHb64UuE6VwiTk7eaJeHb4Ekwt5N9/view?usp=drivesdk | Y34: =Draft!X32 | Z34: Ok | AA34: https://drive.google.com/file/d/1RirYHb64UuE6VwiTk7eaJeHb4Ekwt5N9/view?usp=drivesdk | AB34: Confirm | AD34: Gà nóng, da giòn, ăn lúc đói là chạm đáy hạnh phúc luôn FiveStar ơi 😭 #FiveStarVietnam #GaDau | AE34: Caption: Gà nóng, da giòn, ăn lúc đói là đỉnh nóc hạnh phúc luôn FiveStar ơi 😭 #FiveStarVietnam #GaDau Chạm đáy nghe khổ quá :(( | AG34: 46148 | AH34: https://www.tiktok.com/@lysambonreview/video/7647516576224185620
A35: d | B35: Khu vực miền Tây
A36: 27 | B36: Nhà Bé Sushi | C36: Tiktok | D36: 270000 | E36: Micro | F36: https://www.tiktok.com/@meshushi121 | G36: Cần Thơ | H36: Sản xuất và đăng tải 01 Tiktok Video Review sản phẩm tại điểm bán Five Star Kiosk, theo định hướng nội dung của nhãn hàng - Thời lượng: 60-120s - Chất lượng: phù hợp điện thoại - Địa điểm: tại các Five Star Kiosk ở Tp. HCM Map Five Star Kiosk: Link "01 tháng Sử dụng hình ảnh không độc quyền trên digital only *Bao gồm: Code Ads và reup kênh brand có chạy quảng cáo" | I36: FALSE | J36: 13/5- 13h - Cần Thơ Fivestar ngã 6 hậu giang: https://goo.gl/maps/qYtJdih4aZFAcWmB7 | M36: Đã quay | N36: https://docs.google.com/spreadsheets/d/1t-7Q5oGMoWXh30EwMS3VIVjf3VlpRjXbjQu-7kPX60A/edit?gid=0#gid=0 | O36: =Draft!N36 | P36: - Review thêm vị xiên que - Ko dùng từ khóa rẻ > đổi thành giá hợp lý / giá mềm, ngon - bổ - tiện lợi - câu cuối > đủ chất bị hơi quá > đổi thành "...đỡ ngán cơm nhà mà vẫn tiện lợi, nhanh gọn và chất lượng cho bé thì ghé..." | Q36: https://docs.google.com/spreadsheets/d/1t-7Q5oGMoWXh30EwMS3VIVjf3VlpRjXbjQu-7kPX60A/edit?gid=911497265#gid=911497265 | S36: Đủ chất > sửa lại khúc này giúp c nha, còn lại ok Thêm CTA: "Xem Store gần nhất bên dưới phần comment" + Cmt link web | U36: https://drive.google.com/drive/folders/1popF1KGVp0UiLgw4ne5gDIiH7CtG3Wuf | V36: =Draft!U36 | W36: Cho màu đồ ăn tươi hơn, màu hiện tại hơi lạnh Các món xiên que > liệt kê tên chính xác | X36: https://drive.google.com/drive/folders/1popF1KGVp0UiLgw4ne5gDIiH7CtG3Wuf | Y36: =Draft!X36 | AD36: "Top 1 quán đồ chiên nhanh tiện lợi tui iu thích đó chính là Fivestar nè các mom ơi Một món vừa tiện vừa dễ ăn cho cả gia đình thì tui vote Five Star nha 🍗 #FiveStarVietnam #GaDau" | AE36: Caption Ok nhưng chưa có clip final | AG36: 13/6
A37: FOODY COMMUNITY
A38: 28 | B38: Địa điểm ăn uống (Fanpage) | C38: Facebook | D38: 5.2M | E38: Macro | F38: Link | G38: Mass | H38: Sản xuất và đăng tải Photo Post (rối đa 10 ảnh) check-in tại Five Star Kiosk, đưa tin và review sản phẩm gà rán, theo định hướng nhãn hàng. | I38: FALSE | J38: Photo Post không update hạng mục này | M38: Đang quay | N38: =Draft!M38 -> Photo Post không update hạng mục này | O38: =Draft!N38 -> Photo Post không update hạng mục này | P38: Photo Post không update hạng mục này | Q38: =Draft!P38 -> Photo Post không update hạng mục này | R38: =Draft!Q38 -> Photo Post không update hạng mục này | S38: Photo Post không update hạng mục này | U38: https://drive.google.com/drive/u/2/folders/18fhk1nYoP55xczYSJAJPpHe0uGZBAtS6 | W38: Bỏ hình số 9 HÌnh số 1,3,5,13 lên đầu Hình số 8 logo bị cắt | X38: LInk hình | Y38: Đã điều chỉnh lại số thứ tự hình Hình 8 logo bị cắt => bỏ hình đó luôn ạ | Z38: Hình ok | AA38: LInk hình | AB38: Confirm | AD38: Gu của mọi nhà GÀ RÁN gắn bó biết bao thế hệ Nhắc tới tên thôi là thấy cả 1 hành trình gắn bó trong sự nghiệp ăn uống của mình =)) Từ thời học sinh, lên sinh viên, rồi giờ ra trường đi làm thế mà Gà rán Fivestar vẫn có sức hút riêng nha. Chắc ai cũng như mình đã từng Fivestar phải không nào! Vừa tiện lợi, nhanh, gọn, lẹ mà gà rán thì mãi "cuốn" thôi: lớp da giòn rụm, bên trong vẫn giữ được độ mềm và mọng nước. Cắn miếng gà nóng giòn là đỉnh nhất, có hương vị đặc trưng riêng, lớp bột giòn và tẩm ướp đậm vừa phải, dễ hợp gu, ăn không bị ngán. Mà đâu chỉ có gà đâu, lúc xưa có mấy món đơn giản: gà lắc, khoai tây,... chứ giờ bạt ngàn món cho dân tình mình tha hồ chọn: gợi ý mấy món xiên que nha cả nhà: nóng hổi vừa tiện lại vừa ngon. Giá mềm dễ chịu, menu có đủ từ món ăn vặt đến ăn no, đi 1 mình hay đi nhóm đều dễ chọn. Sáng thì có gà rán burger, trưa tối có mì Ý. Mà thú thiệt mình cũng mê mì Ý ở đây lắm nha, ăn kèm gà viên hay mấy loại xiên que là "dính" lắm nha. Ưu điểm mà mình thích nhất, là đi đâu cũng dễ thấy, mua nhanh, lấy liền không phải chờ lâu. Đặc biệt, ngoài những Kiosk bán mang đi nhanh giờ còn có nhiều cửa hàng xịn sò cho dân tình mình ngồi lại luôn đó. Thèm gà rán, xiên que, ăn vặt hay ăn no thì cứ ngại gì không tấp chỗ quen thuộc Fivestar vừa nhanh lại vừa mờ lem: ăn sáng, trưa, chiều, tối hay đơn giản thòm thèm muốn ăn thôi! Còn chưa biết hay muốn tìm tọa độ Fivestar gần nhất thì dễ ợt à cả nhà. Cứ search: Hệ thống Gà rán Fivestar là ra, rồi chọn cho mình vị trí tấp ưng ý nhất thôi <3 Bật mí với cả nhà là lúc nào cũng có khuyến mãi đó nha, đợt này mình đi đang có tặng xôi ấy, nên cả nhà nắm bắt để được ưu đãi hời nè! | AE38: Xiên que - highlight thêm 1 số món xiên que đặc biệt: Chả giò Gai Jor, Chả Cá Chiên Hàn Quốc, Hotdog Xúc xích Phô mai Tẩm Khoai Tây, Xúc xích toperdo, Gà Nugget ngôi sao, v.v. Chắc ai cũng như mình đã từng Fivestar phải không nào! > từng gì ah? thiếu từ đơn giản thòm thèm muốn ăn thôi! > bỏ chữ thòm Share link dẫn tới https://fivestarnearyou.cp.com.vn/ | AF38: Gu của mọi nhà GÀ RÁN gắn bó biết bao thế hệ Nhắc tới tên thôi là thấy cả 1 hành trình gắn bó trong sự nghiệp ăn uống của mình =)) Từ thời học sinh, lên sinh viên, rồi giờ ra trường đi làm thế mà Gà rán Fivestar vẫn có sức hút riêng nha. Chắc ai cũng như mình đã từng thử Fivestar phải không nào! Vừa tiện lợi, nhanh, gọn, lẹ mà gà rán thì mãi ""cuốn"" thôi: lớp da giòn rụm, bên trong vẫn giữ được độ mềm và mọng nước. Cắn miếng gà nóng giòn là đỉnh nhất, có hương vị đặc trưng riêng, lớp bột giòn và tẩm ướp đậm vừa phải, dễ hợp gu, ăn không bị ngán. Mà đâu chỉ có gà đâu, lúc xưa có mấy món đơn giản: gà lắc, khoai tây,... chứ giờ bạt ngàn món cho dân tình mình tha hồ chọn: gợi ý mấy món xiên que như: chả giò Gai Jor, chả cá chiên Hàn Quốc, hotdog xúc xích phô mai tẩm khoai tây, xúc xích toperdo, gà nugget ngôi sao, v.v. nhìn là muốn lấy mỗi loại một cây. Ai ăn no thì có burger, mì Ý, cơm… nha cả nhà: nóng hổi vừa tiện lại vừa ngon. Giá mềm dễ chịu, menu có đủ từ món ăn vặt đến ăn no, đi 1 mình hay đi nhóm đều dễ chọn. Sáng thì có gà rán burger, trưa tối có mì Ý. Mà thú thiệt mình cũng mê mì Ý ở đây lắm nha, ăn kèm gà viên hay mấy loại xiên que là ""dính"" lắm nha. Ưu điểm mà mình thích nhất, là đi đâu cũng dễ thấy, mua nhanh, lấy liền không phải chờ lâu. Đặc biệt, ngoài những Kiosk bán mang đi nhanh giờ còn có nhiều cửa hàng xịn sò cho dân tình mình ngồi lại luôn đó. Thèm gà rán, xiên que, ăn vặt hay ăn no thì cứ ngại gì không tấp chỗ quen thuộc Fivestar vừa nhanh lại vừa mờ lem: ăn sáng, trưa, chiều, tối hay đơn giản thèm muốn ăn thôi! Còn chưa biết hay muốn tìm tọa độ Fivestar gần nhất thì dễ ợt à cả nhà. Cứ search: Hệ thống Gà rán Fivestar là ra, rồi chọn cho mình vị trí tấp ưng ý nhất thôi <3 Bật mí với cả nhà là lúc nào cũng có khuyến mãi đó nha, đợt này mình đi đang có tặng xôi ấy, nên cả nhà nắm bắt để được ưu đãi hời nè! Xiên que, gà rán, mì ý ở đây nè https://fivestarnearyou.cp.com.vn/ | AG38: 46087 | AH38: https://www.facebook.com/share/p/1BEEgaStVN/?mibextid=wwXIfr
A39: 29 | B39: Thèm (Fanpage) | C39: Facebook | D39: 2M | E39: Macro | F39: link | G39: Mass | H39: Sản xuất và đăng tải Photo Post (rối đa 10 ảnh) check-in tại Five Star Kiosk, đưa tin và review sản phẩm gà rán, theo định hướng nhãn hàng. | I39: FALSE | J39: Photo Post không update hạng mục này | M39: Đang quay | N39: =Draft!M39 -> Photo Post không update hạng mục này | O39: =Draft!N39 -> Photo Post không update hạng mục này | P39: Photo Post không update hạng mục này | Q39: =Draft!P39 -> Photo Post không update hạng mục này | R39: =Draft!Q39 -> Photo Post không update hạng mục này | S39: Photo Post không update hạng mục này | U39: https://drive.google.com/drive/u/2/folders/11BREkfdsiSkqXHPqIoTuB_X3TVhndd7_ | W39: Bỏ hình số 1 Chọn hình 21, 18, 2 (chỉnh lại chỗ logo), 4,9 Hình số 2 bị cắt logo | X39: LINK HÌNH | Y39: hình số 1 => đã bỏ hình số 2 bị cắt logo => đã cắt | Z39: Nếu chỉ pick 10 hình: 2, 4,6, 7, 12 (cho màu tươi lên), 9,16, 18,21, 13 | AA39: link hình pick | AB39: Confirm | AD39: Không biết từ bao giờ mà cứ nhắc tới đồ ăn nhanh là trong đầu mình auto hiện ra hình ảnh mấy kiosk vàng đỏ quen thuộc 😆 Hồi còn đi học tan trường là tụ tập mua gà rán ăn cho đã cái miệng, tới giờ đi làm rồi mà lâu lâu thèm vẫn tấp vô mua như một thói quen luôn á. Công nhận Gà rán Fivestar có cái sức hút rất riêng nha. Gà lúc nào cũng nóng hổi, lớp da giòn nghe “rộp rộp” vui tai cực, còn phần thịt bên trong vẫn mềm và juicy chứ không bị khô. Cái vị tẩm ướp cũng vừa miệng, không quá nặng gia vị nên ăn hoài vẫn thấy hợp gu. Mình thích nhất là kiểu tiện cực kỳ. Đói bụng ghé mua cái là có ngay, không phải đợi lâu. Đi đâu cũng dễ bắt gặp nên nhiều hôm chỉ cần chạy ngang thấy mùi thơm thôi là tự động quẹo vô 😭 Giờ menu cũng đa dạng hơn hồi xưa nhiều lắm nha. Không chỉ có gà rán với khoai đâu, mà còn đủ kiểu xiên que nóng hổi nhìn là muốn lấy mỗi loại một cây. Ai ăn no thì có burger, mì Ý, cơm… đủ combo luôn. Riêng mình mê combo mì Ý ăn kèm gà viên với xiên que lắm, kiểu ăn chơi mà thành ăn no luôn á =)) Điểm cộng nữa là giá vẫn rất dễ chịu, học sinh sinh viên hay dân văn phòng đều dễ ăn. Đi một mình mua snack nhẹ hay đi đông gọi combo share cũng hợp. Mà giờ ngoài mấy kiosk mua mang đi nhanh gọn, nhiều chỗ còn có không gian ngồi lại khá xịn sò luôn. Thành ra từ ăn vặt, ăn no, tụ tập bạn bè hay đơn giản lên cơn thèm gà lúc chiều chiều thì cũng có chỗ “chữa”. Ai lâu rồi chưa ăn thử lại thì mình nghĩ nên tấp vô ăn một bữa cho nhớ tuổi thơ nha 😆 Với nhớ canh mấy chương trình khuyến mãi nữa, mình đi đợt này còn được tặng xôi nên thấy hời dữ lắm luôn! | AE39: Xiên que - highlight thêm 1 số món xiên que đặc biệt: Chả giò Gai Jor, Chả Cá Chiên Hàn Quốc, Hotdog Xúc xích Phô mai Tẩm Khoai Tây, Xúc xích toperdo, Gà Nugget ngôi sao, v.v. Share link dẫn tới https://fivestarnearyou.cp.com.vn/ | AF39: Không biết từ bao giờ mà cứ nhắc tới đồ ăn nhanh là trong đầu mình auto hiện ra hình ảnh mấy kiosk vàng đỏ quen thuộc 😆 Hồi còn đi học tan trường là tụ tập mua gà rán ăn cho đã cái miệng, tới giờ đi làm rồi mà lâu lâu thèm vẫn tấp vô mua như một thói quen luôn á. Công nhận Gà rán Fivestar có cái sức hút rất riêng nha. Gà lúc nào cũng nóng hổi, lớp da giòn nghe “rộp rộp” vui tai cực, còn phần thịt bên trong vẫn mềm và juicy chứ không bị khô. Cái vị tẩm ướp cũng vừa miệng, không quá nặng gia vị nên ăn hoài vẫn thấy hợp gu. Mình thích nhất là kiểu tiện cực kỳ. Đói bụng ghé mua cái là có ngay, không phải đợi lâu. Đi đâu cũng dễ bắt gặp nên nhiều hôm chỉ cần chạy ngang thấy mùi thơm thôi là tự động quẹo vô 😭 Giờ menu cũng đa dạng hơn hồi xưa nhiều lắm nha. Không chỉ có gà rán với khoai đâu, mà còn đủ kiểu xiên que nóng hổi nào là chả giò Gai Jor, chả cá chiên Hàn Quốc, hotdog xúc xích phô mai tẩm khoai tây, xúc xích toperdo, gà nugget ngôi sao, v.v. nhìn là muốn lấy mỗi loại một cây. Ai ăn no thì có burger, mì Ý, cơm… đủ combo luôn. Riêng mình mê combo mì Ý ăn kèm gà viên với xiên que lắm, kiểu ăn chơi mà thành ăn no luôn á =)) Điểm cộng nữa là giá vẫn rất dễ chịu, học sinh sinh viên hay dân văn phòng đều dễ ăn. Đi một mình mua snack nhẹ hay đi đông gọi combo share cũng hợp. Mà giờ ngoài mấy kiosk mua mang đi nhanh gọn, nhiều chỗ còn có không gian ngồi lại khá xịn sò luôn. Thành ra từ ăn vặt, ăn no, tụ tập bạn bè hay đơn giản lên cơn thèm gà lúc chiều chiều thì cũng có chỗ “chữa”. Ai lâu rồi chưa ăn thử lại thì mình nghĩ nên tấp vô ăn một bữa cho nhớ tuổi thơ nha 😆 Với nhớ canh mấy chương trình khuyến mãi nữa, mình đi đợt này còn được tặng xôi nên thấy hời dữ lắm luôn! Tới ngay FIVESTART thui nào: https://fivestarnearyou.cp.com.vn/ | AG39: 46087 | AH39: https://www.facebook.com/share/p/18h4jLfJWe/?mibextid=wwXIfr
A40: 30 | B40: Không Sợ Đói (Group) | C40: Facebook | D40: 1.3M | E40: Macro | F40: Link | G40: Mass | H40: Sản xuất và đăng tải Photo Post (rối đa 10 ảnh) check-in tại Five Star Kiosk, đưa tin và review sản phẩm gà rán, theo định hướng nhãn hàng. | I40: FALSE | J40: Photo Post không update hạng mục này | M40: Đang quay | N40: =Draft!M40 -> Photo Post không update hạng mục này | O40: =Draft!N40 -> Photo Post không update hạng mục này | P40: Photo Post không update hạng mục này | Q40: =Draft!P40 -> Photo Post không update hạng mục này | R40: =Draft!Q40 -> Photo Post không update hạng mục này | S40: Photo Post không update hạng mục này | U40: https://drive.google.com/drive/folders/1iw0zlpAoQ_rBV9CaS6qtBBt_JZI2J-se?usp=sharing | W40: Ko show hình 1,2,3 (các hình có cửa hàng) Bổ sung thêm hình đồ ăn Leo's comment: Không duyệt 1,2,3,4,5. Miễn cưỡng 6,7,8, cần thêm hình đồ ăn | X40: LINK HÌNH | Y40: Đã xóa hình 1,2,3 | Z40: Layout ok nhưng màu hình đang quá tối, món ăn nhìn ko hấp dẫn - chỉnh lại màu sắc | AA40: ĐÃ UPDATE HÌNH RETOUCH 2805 | AB40: Confirm | AD40: ĐANG BẬN RỘN ĐI CHƠI THÌ ĂN GÌ? Nay trên đường đi chơi xuyên tỉnh, đang chạy lịch liên tục thì tự nhiên khờ ngang… không biết ăn gì. Mỗi lần dừng lại ăn uống là mất kha khá thời gian, nên đang chạy xe thấy ngay quán quen bên đường là tấp vô liền luôn. Five Star thì khỏi nói về độ phổ biến và uy tín trong mảng thức ăn nhanh rồi. Mua nhanh – lấy liền, mà cái mình thích nhất là giá lúc nào cũng “mềm”, gọi đồ khá thoải mái mà không bị áp lực ví tiền. Menu giờ đa dạng lắm, kiểu từ ăn chơi tới ăn no đều có luôn: gà rán, mì Ý, xiên que, phô mai que, chả cá, nugget sao, gà popcorn… thiếu điều đứng lựa bị phân vân. Mà công nhận giá mềm thiệt nhưng phần ăn lại khá đầy đặn. Gà chiên lớp da giòn rụm, bên trong vẫn mềm và mọng nước, ăn lúc nóng đúng kiểu “nhức nách”. Vị nêm ở đây đậm vừa phải, dễ hợp gu nhiều người nên ăn không bị ngán. Bò viên thì chắc nịch, vị bò rõ ràng chứ không bị kiểu toàn mùi bột. Nugget sao nhìn cute dễ sợ luôn. Vỏ giòn, bên trong mềm và thơm. Món này trẻ em thích mà người lớn cũng ngồi ăn ké liên tục. Gà popcorn nhỏ nhỏ giòn giòn, mỗi miếng vừa miệng nên ăn vui lắm. Chấm tương cà, tương ớt hay sốt phô mai đều hợp, kiểu càng chấm càng dính. Chả cá, khoai tây chiên với sủi cảo thì vị ổn áp, dễ ăn. Với mình kiểu đã quen và an tâm về thương hiệu rồi nên ăn tự tin lắm thành ra thấy ngon miệng. Tổng thiệt hại hôm nay chưa tới 400k: 6 miếng gà, 2 bò viên, 2 nugget gà, 2 sủi cảo, 2 chả cá, 4 phô mai que, 2 chả cá Hàn Quốc, 2 gà popcorn mà chưa tới 400k. 6 người trên xe tính ra mỗi người hơn 60k xíu thôi mà ăn uống no nê luôn. Điểm khiến mình chắc chắn vẫn sẽ tiếp tục chọn Five Star mỗi lần đi đường: Chế biến nhanh, giá hợp lý, quán phủ nhiều, dễ tìm – dễ mua – tiện ghé dọc đường #FiveStar #FiveStarVietnam #GaRanFiveStar #GaDay" | AE40: ĐANG BẬN RỘN ĐI CHƠI THÌ ĂN GÌ? > ko make sense lắm Xiên que - highlight thêm 1 số món xiên que đặc biệt: Chả giò Gai Jor, Chả Cá Chiên Hàn Quốc, Hotdog Xúc xích Phô mai Tẩm Khoai Tây, Xúc xích toperdo, Gà Nugget ngôi sao, v.v. Bỏ đoạn này vì ko muốn highlight việc rẻ "Tổng thiệt hại hôm nay chưa tới 400k: 6 miếng gà, 2 bò viên, 2 nugget gà, 2 sủi cảo, 2 chả cá, 4 phô mai que, 2 chả cá Hàn Quốc, 2 gà popcorn mà chưa tới 400k. 6 người trên xe tính ra mỗi người hơn 60k xíu thôi mà ăn uống no nê luôn. " > hoặc chỉnh lại theo hướng giá hời chất lượng Share link dẫn tới https://fivestarnearyou.cp.com.vn/ | AF40: Đang chạy xuyên tỉnh, đói bụng giữa đường mà không muốn mất nhiều thời gian kiếm quán, thấy ngay quầy Five Star Vietnam quen là tấp vô liền. Mua nhanh – lấy liền, đúng kiểu tiện cho những chuyến đi đường dài. Điều mình thích nhất là menu xiên que phong phú, nhìn thôi đã muốn gọi hết: Chả giò Gai Jor – giòn rụm, thơm đậm hương. Chả Cá Chiên Hàn Quốc – dai vừa, vị đậm đà dễ ghiền. Hotdog Xúc xích Phô mai tẩm Khoai Tây – cắn một miếng là phô mai kéo sợi, đã “ná thở”. Xúc xích Toperdo – cây to chắc thịt, ăn rất đã. Gà Nugget ngôi sao – giòn vui miệng, trẻ em hay người lớn đều mê. Ngoài xiên que, gà rán vẫn là “signature”: lớp da giòn, thịt bên trong mềm mọng, ăn nóng lên là chuẩn bài. Những món khác như gà popcorn, phô mai que, sủi cảo… thì dễ ăn, lên nhanh, hợp kiểu dừng chân lấy năng lượng rồi lên đường tiếp. Tổng quan: giá vẫn rất hời so với chất lượng và phần ăn, đặc biệt lúc đang đi chơi mà cần món nhanh – gọn – ngon thì Five Star luôn là lựa chọn “an tâm”. Tìm quán Five Star gần bạn tại đây: https://fivestarnearyou.cp.com.vn/ #FiveStar #FiveStarVietnam #GaRanFiveStar #GaDay | AG40: 46148 | AH40: https://www.facebook.com/groups/kosodoi/posts/27023379973991978
A41: 31 | B41: Măm Măn Sài gòn (Group) | C41: Facebook | D41: 780.6K | E41: Micro | F41: Link | G41: Hồ Chí Minh | H41: Sản xuất và đăng tải Photo Post (rối đa 10 ảnh) check-in tại Five Star Kiosk, đưa tin và review sản phẩm gà rán, theo định hướng nhãn hàng. | I41: FALSE | J41: Photo Post không update hạng mục này | M41: Đang quay | N41: =Draft!M41 -> Photo Post không update hạng mục này | O41: =Draft!N41 -> Photo Post không update hạng mục này | P41: Photo Post không update hạng mục này | Q41: =Draft!P41 -> Photo Post không update hạng mục này | R41: =Draft!Q41 -> Photo Post không update hạng mục này | S41: Photo Post không update hạng mục này | U41: https://drive.google.com/drive/folders/1yzIsQySNlHH9Qmnnu6ONb51zbOesHe78?usp=sharing | W41: Hình 1 bị cắt mất địa chỉ Remove hình 6 Màu sắc món chưa tươi và hấp dẫn, đang bị quá nhạt | X41: ĐÃ UPDATE HÌNH RETOUCH 2805 HÌNH 1: SUGGEST XÓA | Z41: Hình 2 retouched bị cắt logo và vỡ hình | AA41: https://drive.google.com/drive/folders/10s11E7iNwe0c-1YJ934qrUvZV6idnMgU | AB41: Confirm Caption bỏ "Vietnam" | AC41: Ok Leo: Bỏ "Vietnam". Đã dùng từ quán thì không cần thêm vào, trừ khi dùng từ chuỗi https://drive.google.com/drive/folders/10s11E7iNwe0c-1YJ934qrUvZV6idnMgU | AD41: "Giới thiệu cho mn quán ruột của mình mỗi tuần nè :D Quán ruột của mình là Five Star vì độ phổ biến, mua nhanh- lấy liền. Menu giờ đa dạng quá trời, từ ăn no tới ăn chơi có đủ hết, mà giá thì ổn so với phần ăn đầy đặn như vậy nha 💯 điểm Trước giờ mình vào cứ nhắm mắt mua đại gà rán, tại ở đây chiên lớp da giòn rụm mà bên trong mềm với mọng nước lắm, vị thì nêm vừa phải- dễ hợp gu nhiều người/ Nay thấy có thêm gà tatsutaage kiểu Nhật, mềm thơm ngon, ướp đậm đà sẵn ko cần chấm luôn. Cá viên, bò viên, khoai tây chiên, gà popcorn ăn ổn áp, kiểu ko có gì quá nổi bậc nhưng cũng không có gì để chê luôn. Được cái quay qua quay lại hết lúc nào hong ai hay Lâu lâu đổi gió mua về 1 mâm vậy không có bao nhiêu mà gia đình 4 người tụ họp lại ăn zui zẻ lên liền Nào chán cơm nhà thì thử kiểu này đi mọi người, kiểu ăn chơi vui mà no thiệt, kiểu ăn đã miệng đã thèm mà nó no á." | AF41: Quán mình hay ghé là Five Star – phổ biến, tiện, vô là mua nhanh – lấy liền. Menu giờ đa dạng từ ăn chơi tới ăn no, phần ăn lúc nào cũng đầy đặn nên rất “đã”. Ngoài gà rán auto-ngon với lớp da giòn rụm và thịt mềm mọng, mình nghiện nhất là mảng xiên que ở đây luôn. Mấy món đáng thử: Chả giò Gai Jor – giòn tan, thơm đặc trưng, cắn một miếng là “dính”. Chả Cá Chiên Hàn Quốc – dai nhẹ, vị đậm đà kiểu Hàn, ăn rất cuốn. Hotdog Xúc xích Phô mai tẩm Khoai Tây – cắn cái nghe phô mai tan chảy, bên ngoài khoai chiên giòn rụm. Xúc xích Toperdo – cây to, chắc thịt, ăn rất đã miệng. Gà Nugget Ngôi Sao – nhỏ xinh, giòn vui miệng, trẻ con lẫn người lớn đều mê. Mấy món khác như gà popcorn, khoai tây chiên, cá viên, bò viên… thì ổn áp, kiểu quay cái là hết sạch lúc nào không hay. Lâu lâu đổi gió mua nguyên mâm vậy thôi mà gia đình 4 người ngồi lại ăn là vui liền, vừa no vừa đúng kiểu “ăn chơi mà no thiệt”. Hôm nào chán cơm nhà thì thử kiểu này đi mọi người. Ngon – vui – nhanh – tiện, đúng chuẩn ngày lười nấu :D Địa chỉ các quán Fivestar ở đây nhen: https://fivestarnearyou.cp.com.vn/ #FiveStar #FiveStarVietnam #GaRanFiveStar #GaDay | AG41: 46240
A42: 32 | B42: Đảo Đồ Ăn (Group) | C42: Facebook | D42: 508.4K | E42: Micro | F42: Link | G42: Mass | H42: Sản xuất và đăng tải Photo Post (tối đa 10 ảnh) check-in tại Five Star Kiosk, đưa tin và review sản phẩm gà rán, theo định hướng nhãn hàng. | I42: FALSE | J42: Photo Post không update hạng mục này | M42: Đang quay | N42: =Draft!M42 -> Photo Post không update hạng mục này | O42: =Draft!N42 -> Photo Post không update hạng mục này | P42: Photo Post không update hạng mục này | Q42: =Draft!P42 -> Photo Post không update hạng mục này | R42: =Draft!Q42 -> Photo Post không update hạng mục này | S42: Photo Post không update hạng mục này | U42: https://drive.google.com/drive/folders/12yBGOkeqhLxeerxDXMuBtK-41vgUeWxf?usp=sharing | W42: Hình 8, 14, 17,19,25,28,30,31,33,34 Thay Chai Pepsi bằng ly nước ngọt có Five Star (check trước giùm c) | X42: LINK HÌNH | Z42: HÌnh ok | AA42: LINK HÌNH | AB42: Confirm | AD42: QUÁN ĂN FAST FOOD GẮN LIỀN VỚI TUỔI THƠ CỦA NHIỀU NGƯỜI BÂY GIỜ ĐÃ RA SAO 📍 Gà Rán Five Star 489 🏡 🏡 489 Đ. Lê Văn Sỹ, Tân Sơn Hòa, Hồ Chí Minh ⏰⏰ 11h – 22h30 💰💰 8 xu – 45 xu 📍Về món 🐥🍗Tính ra thương hiệu Five Star này cũng lâu rồi chứ bộ, nhắc đến ở đâu mà có gà rán vừa chất lượng, giá HSSV, mà còn đa dạng món là tui nghĩ đến brand này liền luôn á. Lâu lắm rồi tui mới quay lại thử thì thấy giá vẫn hợp lý như cũ nè giao động từ 8 xu đến 45 xu thôi. Mà đợt này còn có những combo siêu tiện lợi luôn. 🍗🍗Tui gọi Combo Bạn Bè (158 xu) mà có tận 3 miếng gà bự, xúc xích, xiên chả giò thái lan, khoai tây, rồi còn có 2 chai nước ngọt nữa. Tính ra mua combo dị tiện quá chời mà còn nhiều nữa. Gà rán quán làm giòn rụm, mộng nước, chắc thịt, không bị quá khô đâu nha. Này mình có thể ăn kèm với 3 loại xốt cay, xốt phô mai, xốt mắm tỏi, mỗi loại xốt thêm 5 xu nè. Riêng ai gu ăn cay, kêu xốt cay nha, còn xốt phô mai thì beo béo, xốt mắm tỏi thì đậm đà thơm mùi tỏi. Higly recommend mấy bà gọi mắm tỏi nha. 🍢🍡Ngoài ra mấy bà có thể thử mấy loại xiên que ở Five Star nha, siêu ngon luôn, mà giá chỉ từ 8 xu đến 17 xu mỗi xiên thôi. Tui bị mê xiên chả cá, xúc xích, cá viên, chả cá quế, phô mai que ở đây nha, kiểu quán chiên vàng giòn, nóng hổi, cầm siêu tiện lợi luôn, chấm cùng với sốt cà chua, siêu ngon. Tui còn mua thêm phần Mì Ý (39 xu) với Gà Nugget (25 xu), mì ý tui thấy ăn cũng tạm ổn thôi nè. 📍Về quán 🍗🍜Tính ra nguyên bàn của tui vừa có gà rán, mỳ ý, các loại xiên que, gà nugget, khoai tây, tính tổng chỉ có hơn 300 xu xíu thôi, mà cỡ 5 đến 6 người ăn mới hết. Lâu lâu trở lại thấy thương hiệu ngày càng nâng cấp với chất lượng hơn. Hôm tui đi chi nhánh tui đi nằm ở Lê Văn Sỹ chủ yếu bán theo dạng take away thôi. Chị nhân viên cũng dễ thương, nhiệt tình nữa. Ai mà muốn ăn gà rán, xiên que đa dạng món, tiện lợi, giá cả hợp lý, thì có thể tham khảo chỗ này nhe. #FiveStar #FiveStarVietnam #GaRanFiveStar #GaDay | AE42: Bỏ địa chỉ và thời gian > CTA tới quán gần nhất, chia sẻ map link https://fivestarnearyou.cp.com.vn/ Bỏ phần giá chi tiết > chủ yếu highlight giá hợp lý với chất lượng và khẩu phần xịn Giá hssv > giá hợp lý / mềm mộng nước > mọng nước Gọi tên của các món xiên que luôn - highlight thêm 1 số món xiên que đặc biệt: Chả giò Gai Jor, Chả Cá Chiên Hàn Quốc, Hotdog Xúc xích Phô mai Tẩm Khoai Tây, Xúc xích toperdo, Gà Nugget ngôi sao, v.v. | AF42: QUÁN ĂN FAST FOOD GẮN LIỀN VỚI TUỔI THƠ CỦA NHIỀU NGƯỜI BÂY GIỜ ĐÃ RA SAO 📍 Gà Rán Five Star 489 🏡 🏡 Chi nhánh gần nhất: https://fivestarnearyou.cp.com.vn/ ⏰⏰ 11h – 22h30 📍Về món 🐥🍗Tính ra thương hiệu Five Star này cũng lâu rồi chứ bộ, nhắc đến ở đâu mà có gà rán vừa chất lượng, giá hợp lý và mềm, mà còn đa dạng món là tui nghĩ đến brand này liền luôn á. Lâu lắm rồi tui mới quay lại thử thì thấy giá vẫn hợp lý như cũ nè giao động từ 8 xu đến 45 xu thôi. Mà đợt này còn có những combo siêu tiện lợi luôn. 🍗🍗Tui gọi Combo Bạn Bè (158 xu) mà có tận 3 miếng gà bự, xúc xích, xiên chả giò thái lan, khoai tây, rồi còn có 2 chai nước ngọt nữa. Tính ra mua combo dị tiện quá chời mà còn nhiều nữa. Gà rán quán làm giòn rụm, mọng nước, chắc thịt, không bị quá khô đâu nha. Này mình có thể ăn kèm với 3 loại xốt cay, xốt phô mai, xốt mắm tỏi, mỗi loại xốt thêm 5 xu nè. Riêng ai gu ăn cay, kêu xốt cay nha, còn xốt phô mai thì beo béo, xốt mắm tỏi thì đậm đà thơm mùi tỏi. Higly recommend mấy bà gọi mắm tỏi nha. 🍢🍡Ngoài ra mấy bà có thể thử mấy loại xiên que ở Five Star nha, siêu ngon luôn, mà giá chỉ từ 8 xu đến 17 xu mỗi xiên thôi. Một trong số món xiên que đặc biệt mà tui tâm đắc: Chả giò Gai Jor, Chả Cá Chiên Hàn Quốc, Hotdog Xúc xích Phô mai Tẩm Khoai Tây, Xúc xích toperdo, Gà Nugget ngôi sao, v.v. Kiểu quán chiên vàng giòn, nóng hổi, cầm siêu tiện lợi luôn, chấm cùng với sốt cà chua, siêu ngon. Tui còn mua thêm phần Mì Ý (39 xu) với Gà Nugget (25 xu), mì ý tui thấy ăn cũng tạm ổn thôi nè. 📍Về quán 🍗🍜Tính ra nguyên bàn của tui vừa có gà rán, mỳ ý, các loại xiên que, gà nugget, khoai tây, tính tổng chỉ có hơn 300 xu xíu thôi, mà cỡ 5 đến 6 người ăn mới hết. Lâu lâu trở lại thấy thương hiệu ngày càng nâng cấp với chất lượng hơn. Hôm tui đi chi nhánh tui đi nằm ở Lê Văn Sỹ chủ yếu bán theo dạng take away thôi. Chị nhân viên cũng dễ thương, nhiệt tình nữa. Ai mà muốn ăn gà rán, xiên que đa dạng món, tiện lợi, giá cả hợp lý, thì có thể tham khảo chỗ này nhe. #FiveStar #FiveStarVietnam #GaRanFiveStar #GaDay | AG42: 46028 | AH42: https://www.facebook.com/share/p/1BHGncNZtK/?mibextid=wwXIfr
A43: 33 | B43: Hà Nội Ăn Gì? | C43: Tiktok | D43: 1M | E43: Macro | F43: Link | G43: Hà Nội | H43: Sản xuất và đăng tải Video Post (60-120s) check-in tại Five Star Kiosk, đưa tin và review sản phẩm gà rán, theo định hướng nhãn hàng. | I43: TRUE | J43: - Khung giờ đến quay: 11h30 trưa T7 16/5 - basic shop Thị Thắm: Viết Xuân - Hà Đông hà nội | M43: Đã quay | N43: =Draft!M43 -> https://docs.google.com/spreadsheets/d/1VVMeHf2sGW8ymO4iXQtvCgyoT4rc0OuQeg-j3A20B_o/edit?gid=719708239#gid=719708239 | O43: =Draft!N43 | P43: "- Trang phục ok - Nhờ dùng gà chuẩn quy trình 3F (Feed - Farm - Food) từ trang trại đến bàn ăn > bỏ ý này, ghi đơn giản theo giọng của người tiêu dùng, highlight là gà từ tập đoàn CP thì tiêu chuẩn an tâm, chất lượng cao nên thịt tươi ngon, mọng nước - Có thể bổ sung ý hương vị ai cũng thích, đa dạng các món ai cũng mê - Add thêm text vị trí địa điểm five star mà bạn vừa ghé" | Q43: https://docs.google.com/spreadsheets/d/1VVMeHf2sGW8ymO4iXQtvCgyoT4rc0OuQeg-j3A20B_o/edit?gid=1999364123#gid=1999364123 | S43: Script ok, bổ sung CTA voice off/ text on frame "Xem comment để xem store Fivestar gần nhất" | U43: DEMO | V43: 0:54 - 0:59 - Nhạc hơi to Còn hơi nhiều tạp âm những khúc quay ngoài trời | W43: 0:42: bị cắt mất địa chỉ > có source nào show địa chỉ ko 0:50, dưới đất có rác > remove tiếng bạn ở quán hơi nhỏ Các món xiên que đọc tên đúng giúp m nhé: chả giò gai jor, gà nugget ngôi sao CTA comment link tìm kiếm địa chỉ | X43: https://drive.google.com/file/d/1xUctY1jCB8DIvVNOzGEOgksOCw67MR25/view?usp=drive_link | Z43: 0:18: VO đổi từ kios > hệ thống / quán 1:18, chả giò gai jor | AA43: https://drive.google.com/file/d/19C2bLoYd_3sijzlxA-4Aj_cw6a9xtfTX/view?usp=drivesdk | AB43: Leo's commet: -0:07 & 0:10: Zoom để che hoặc Remove cảnh cho thức từ túi giấy ra, nhìn túi giấy hơi đẫm dầu, hiểu là đồ chiên nhưng hạn chế hình ảnh tương tự - 0:26: Bỏ "kiosk" => Nhờ bạn hỗ trợ sửa nhen | AD43: CAPTION: Chúng tôi sẽ ăn và đánh giá tất cả các hãng gà rán #vrmgr #hnag #xh | AE43: ok | AG43: 46148
A44: 34 | B44: Vi vu Sài Gòn | C44: Tiktok | D44: 292.7K | E44: Micro | F44: Link | G44: Hồ Chí Minh | H44: Sản xuất và đăng tải Video Post (60-120s) check-in tại Five Star Kiosk, đưa tin và review sản phẩm gà rán, theo định hướng nhãn hàng. | I44: TRUE | J44: Đã đi quay MINI SHOP - Five Star Mega Q12 - Số 2 đường Trương Thị Hoa, KP 4A, Tân Thới Hiệp, TPHCM Thời gian: 16H ngày 12/5 (chiều mai) | M44: Đã quay | N44: =Draft!M44 -> https://docs.google.com/spreadsheets/d/1ExKareGYH9VR7c6hXA2BPlNn2qL7U879Nzgg7lYOoyk/edit?gid=0#gid=0 | O44: =Draft!N44 | P44: - Trang phục ok - Add thêm các cảnh cận món xiên que - Highlight thêm gà Five Star giòn lâu > dù có bớt nóng chút nhưng gà vẫn giữ đc độ giòn - Đoạn "Người bước vào cửa hàng / order món" và "Khách đang ăn vui vẻ, mua mang về/ Nhân viên đang vui vẻ tư vấn cho khách" > add thêm keyword "đa dạng" / "nhiều món để lựa chọn" - Add thêm text vị trí địa điểm five star mà bạn vừa ghé | Q44: =Draft!P44 -> https://docs.google.com/spreadsheets/d/1ExKareGYH9VR7c6hXA2BPlNn2qL7U879Nzgg7lYOoyk/edit?gid=1350617545#gid=1350617545 | R44: =Draft!Q44 -> Team KOC đã điều chỉnh theo feedback của brand từ round trước | S44: Đã đi quay | U44: DEMO FIVE STAR - VVSG | V44: =Draft!U44 | W44: 0:23 - khúc đó gà hơi hồng, mình move nhanh hoặc zoom in để tránh thấy nha Mình note bỏ chữ kiosk trong VO 0:43 > quán / quầy premium kiosk Ko cần để text địa chỉ quán ở trên chỉ cần CTA kêu gọi tới quán five star gần nhất | X44: https://drive.google.com/drive/folders/1hn0ZUu3LSUPwUmZw8WCjPiD3dMHiONEQ | Y44: Đoạn 00:44 - cắt hình ảnh khách nữ đứng quay vô ống kính, nhìn không clean | Z44: Leo's comment: Đoạn 00:44 - cắt hình ảnh khách nữ đứng quay vô ống kính, nhìn không clean => cmt này fbs sau nên sẽ input ở round 2 Note 0:34 - add text tên món - Chả Giò Gai Jor, Hotdog Xúc Xích Phô Mai Tẩm Khoai Tây (nếu add dc VO về các loại xiên que lạ thì add giúp c nhe) | AA44: https://drive.google.com/file/d/1Xfi4scMbDGQeex1Llpxafvuu7LVFnkvn/view?usp=sharing | AB44: Confirm | AD44: Ghé Five Star là có món liền nha mấy bồ ơi !!!! #FiveStarVietnam #GaDau #FiveStar | AG44: 19h 27/5 | AH44: https://vt.tiktok.com/ZSx4j4dK3/
A45: 35 | B45: Thong dong đó đây | C45: Tiktok | D45: 100.2K | E45: Micro | F45: Link | G45: Mass | H45: Sản xuất và đăng tải Video Post (60-120s) check-in tại Five Star Kiosk, đưa tin và review sản phẩm gà rán, theo định hướng nhãn hàng. | I45: TRUE | J45: - 13h30 - 14h ngày 13/5 - BASIC SHOP: Nguyễn Thị Thuận - 67 Đường 9, P. Trường Thọ, Thành Phố Thủ Đức, TP. HCM | M45: Đã quay | N45: =Draft!M45 -> https://docs.google.com/spreadsheets/d/19KBHFXJZdTSkntAMXMrEZpTkm9ELKraMsDFSVYrKolo/edit?gid=1454906472#gid=1454906472 | O45: =Draft!N45 | P45: - Bổ sung thêm tình huống hoặc thời điểm hoặc lý do để thuyết phục người xem ghé Five Star. Ví dụ như: những hôm thèm gà ngang mà ko biết đi đâu, down mood, v.v. - Review luôn các món khác bên cạnh gà nha | Q45: https://docs.google.com/spreadsheets/d/19KBHFXJZdTSkntAMXMrEZpTkm9ELKraMsDFSVYrKolo/edit?gid=1139038946#gid=1139038946 | R45: Nature kênh không xuất hiện hình ảnh KOC nên không gửi outfit | S45: Script ok Thêm CTA: "Xem Store gần nhất bên dưới phần comment" + Cmt link web | U45: DEMO KOC tặng bộ ảnh để brand có thể dùng: Ảnh tặng | V45: - Text đang hơi to che hình ản sản phẩm - Nhạc đang hơi lớn > có thể cân nhắc chuyển sang nhạc không lời | W45: Text to quá, layout chữ che sản phẩm và hơi nhiều chữ Chuyển sang nhạc ko lời và sôi động hơn chút Đoạn 00:34 - đúng tên món "Chả Giò Gai Jor" | X45: Revised.mp4 | Z45: Nhi's comment Chưa sửa comment của anh Leo "Chả Giò Gai Jor" | AA45: https://drive.google.com/file/d/1CHksn0Bqm_2snadSuMjJY6TOvPXveQPX/view?usp=drive_link | AB45: revise caption + air | AD45: CAPTION: Ở Thủ Đức mấy bồ đã biết tới quàn gà chiên siêu ngon này chưa ? | AE45: quán gà chiên > đổi lại theo hướng thành "quán thức ăn nhanh mà có món gà chiên siêu ngon" | AF45: Đâu nghĩ ở Thủ Đức có quán thức ăn nhanh mà có món gà chiên siêu ngon như thế này | AG45: 46118 | AH45: https://vt.tiktok.com/ZSQYL87Kt/
A46: 36 | B46: SÀI GÒN MAP | C46: Tiktok | D46: 154.5K | E46: Micro | F46: Link | G46: Hồ Chí Minh | H46: Sản xuất và đăng tải Video Post (60-120s) check-in tại Five Star Kiosk, đưa tin và review sản phẩm gà rán, theo định hướng nhãn hàng. | I46: FALSE | J46: 17g - 14/5 quay chi nhánh Huỳnh Tấn Phát, Nhà Bè, TP HCM 7. OUTLET - HKD GÀ RÁN FIVE STAR THU HÀ - 37/3 Huỳnh Tấn Phát, Xã Nhà Bè, TPHCM | M46: Đã quay | N46: =Draft!M46 -> https://docs.google.com/spreadsheets/d/165wHINGJNG6u-TKltL9IFycAvysmlg8PM9SMb5b7ZEI/edit?gid=0#gid=0 | O46: =Draft!N46 | P46: - Đoạn đầu khi dẫn về Five Star chưa có sự liên kết > có thể nói về việc nghĩ tới gà rán là nghĩ tới Five Star hoặc là nghĩ tới gà rán mà mềm mọng, vừa nhanh gọn lẹ ngon thì Five Star là lựa chọn đầu tiên. - Highlight thêm về giá cả > giá hợp lý, giá dễ chịu, khẩu phần chất lượng hơn so với giá > ko nhắc tới keyword rẻ hay mắc - Review thêm về tính đa dạng trong menu > ăn no hay ăn vặt đều hợp, các món mà người lớn con nít đều yêu thích | Q46: =Draft!P46 -> https://docs.google.com/spreadsheets/d/165wHINGJNG6u-TKltL9IFycAvysmlg8PM9SMb5b7ZEI/edit?gid=369007203#gid=369007203 | R46: =Draft!Q46 -> Đã bổ sung outfit Team KOC đã điều chỉnh theo feedback | S46: Script ok Remove địa chỉ quán > thay bằng add website địa điểm phần comment Thêm CTA: "Xem Store gần nhất bên dưới phần comment" + Cmt link web | T46: PMAX x C.P FIVESTAR | SÀI GÒN MAP Script | U46: https://drive.google.com/file/d/126voDv_eow-AZySZj8J51bk2YXbbR-t8/view?usp=drivesdk | V46: =Draft!U46 | W46: Phần xiên que: mention tên các món thay vì nói là xiên que: chả giò gai jor, hotdog xúc xích phô mai tẩm khoai tây, hotdog toperdo, gà nugget ngôi sao Ko cần để text địa chỉ quán ở trên chỉ cần CTA kêu gọi tới quán five star gần nhất | X46: https://drive.google.com/file/d/1sZ5JkOylTp90aiUK9_A_gKbwBLGshMRr/view?usp=drivesdk | Y46: =Draft!X46 | Z46: Clip ok | AA46: https://drive.google.com/file/d/1sZ5JkOylTp90aiUK9_A_gKbwBLGshMRr/view?usp=drivesdk | AB46: Confirm | AD46: Tiệm gà rán siêu ngon gắn liền tuổi thơ bao người🍗✨ | AG46: 11h 28/5 | AH46: https://www.tiktok.com/@saigonmap/video/7644787494319312136?_r=1&_t=ZS-96jG8hKdGL9
A47: 37 | B47: Yến Vy ( Miên Man Hà Nội ) | C47: Tiktok | D47: 141.2K | E47: Micro | F47: Link | G47: Hà Nội | H47: Sản xuất và đăng tải Video Post (60-120s) check-in tại Five Star Kiosk, đưa tin và review sản phẩm gà rán, theo định hướng nhãn hàng. | I47: TRUE | J47: - Khung giờ đến quay: 16h ngày 19/5 - basic shop lê tuyết: Phố xốm- Yên Nghĩa- Hà Nội | M47: Đã confirm lịch | N47: =Draft!M47 -> https://docs.google.com/spreadsheets/d/1s73hp06B3Mcm2XxooLuX0PBD9R1WJN7cKVv-1JsxMNo/edit?usp=sharing | O47: =Draft!N47 | P47: Trang phục ok - Tập đoàn CP Food > chỉnh lại là Tập đoàn CP - Giá cả bình dân > đổi thành giá hợp lý - Bổ sung thêm ý về chất lượng tươi ngon của món (ví dụ ko bị bở, tươi, .vv.) | Q47: https://docs.google.com/spreadsheets/d/1s73hp06B3Mcm2XxooLuX0PBD9R1WJN7cKVv-1JsxMNo/edit?gid=1596471473#gid=1596471473 | R47: =Draft!Q47 | S47: Script & trang phục ok Thêm CTA: "Xem Store gần nhất bên dưới phần comment" + Cmt link web | U47: DEMO | V47: 0:14 - 0:18: Giọng bạn NV đang hơi giống bạn KOL => hơi khó phân biệt | W47: Phần xiên que: mention tên các món thay vì nói là xiên que: chả giò gai jor, hotdog xúc xích phô mai tẩm khoai tây, hotdog toperdo, gà nugget ngôi sao 0:40 - VO là xúc xích hot dog mà show món gà > ko hợp lý Text cuối: bạn có thể share địa chỉ nơi bạn đi và kêu gọi các bạn fan tìm kiếm chi nhánh gần nhất qua địa chỉ web | X47: https://drive.google.com/file/d/1hYXC7LQYH8BUbAQdxdv9tKJ5ZfyK3TGH/view?usp=drive_link | Z47: "0:41: ""chả cá"" -> chả giò gai jor 0:37 - 0:43: Phần xiên que: mention tên các món thay vì nói là xiên que: chả giò gai jor, hotdog xúc xích phô mai tẩm khoai tây, hotdog toperdo, gà nugget ngôi sao 0:40: nói ""xúc xích"" nhưng lại show chả giò" | AA47: https://drive.google.com/file/d/1E6JcPVC4gF0_iY-Hr49W_iDMtM5NxT8Z/view?usp=drive_link | AB47: Leo's commet: - 0:29: Sửa text "mì spaghetti" - "xúc xích torpedo" chứ không phải "toperdo" - 0:42: Sửa voice "hot torpedo" chứ không phải "hotdog pertedo" | AD47: Trải nghiệm 1 quán gà rán, đồ ăn nhanh tủ của các bạn học sinh sinh viên | AG47: 46209
A48: SEEDING PACKAGE | J48: =Draft!J48
A49: 1 | B49: Comment Seeding | C49: Gói Seeding (bao gồm sản xuất nội dung) theo yêu cầu và dán bình luận trên các post được chỉ định của Nhãn hàng - Account: người thật, nam & nữ, trong khoảng 18 - 30 tuổi, Việt Nam only, hình ảnh liên quan đến lifestyle, sinh viên, người đi làm, gia đình - Bao gồm chi phí soạn nội dung comment - Số lượng comment: 2.000 comments | J49: =Draft!J49
J65: Column 1

Sheet INT | Influencer Performance Tr
A1: PMAX | C.P.GROUP VIETNAM — PERFORMANCE TRACKING (End-user)
A2: STT | B2: Tên Người Ảnh Hưởng | C2: Lượng Người Theo Dõi | D2: Link | E2: Nền Tảng | F2: Link air | G2: NGÀY AIR | H2: KPI | J2: Actual collectables | M2: Runrate | O2: NGÀY CẬP NHẬT
H3: View | I3: Engagement | J3: View | K3: Engagements | L3: Screenshot nghiệm thu | M3: View | N3: Engagements
A4: FOODY REVIEWER | F4: =counta(F6:F1001) &"/37" -> 18/37 | H4: =SUM(H5:H48) -> 1551500 | I4: =SUM(I5:I48) -> 82200 | J4: =SUM(J5:J48) -> 426156 | K4: =SUM(K5:K48) -> 23229
A5: 1 | B5: Thắng Lợi | C5: 426.5K | D5: Link | E5: Tiktok | F5: https://vt.tiktok.com/ZSQ1XDNsR/ | G5: 46087 | H5: 50000 | I5: 3000 | J5: 2765 | K5: 64 | M5: =IFERROR(IF(H5>0,J5/H5,""),"") -> 0.0553 | N5: =IFERROR(IF(I5>0,K5/I5,""),"") -> 0.021333333 | O5: 46148
A6: 2 | B6: Lulu Review | C6: 336.4K | D6: Link | E6: Tiktok | F6: https://www.tiktok.com/@lulureview_/video/7644513610072460551?_r=1&_t=ZS-96jI4dZLIL1 | G6: 27/5 | H6: 100000 | I6: 3000 | J6: 43497 | K6: 1204 | M6: =IFERROR(IF(H6>0,J6/H6,""),"") -> 0.43497 | N6: =IFERROR(IF(I6>0,K6/I6,""),"") -> 0.40133333 | O6: 46148
A7: 3 | B7: Hello Lập Đây | C7: 260K | D7: Link | E7: Tiktok | F7: https://vt.tiktok.com/ZSxt8cXaM/ | G7: 46059 | H7: 130000 | I7: 4000 | J7: 70387 | K7: 1099 | M7: =IFERROR(IF(H7>0,J7/H7,""),"") -> 0.54143846 | N7: =IFERROR(IF(I7>0,K7/I7,""),"") -> 0.27475 | O7: 46148
E8: Instagram (FOC) | F8: https://www.instagram.com/reel/DY9hZnczdim/?igsh=MWk3cnVvcjlwZ3VndA== | J8: 0 | K8: 39 | O8: 46148
A9: 4 | B9: Huyền Nhi | C9: 118.1K | D9: Link | E9: Tiktok | F9: https://www.tiktok.com/@hhuyennhiii/video/7644779715093482772?_r=1&_t=ZS-96jFcDqShi1 | G9: 29/5 | H9: 30000 | I9: 1200 | J9: 32589 | K9: 2502 | M9: =IFERROR(IF(H9>0,J9/H9,""),"") -> 1.0863 | N9: =IFERROR(IF(I9>0,K9/I9,""),"") -> 2.085 | O9: 46148
A10: 5 | B10: Thư Bonny | C10: 114.7K | D10: Link | E10: Tiktok | F10: https://www.tiktok.com/@thubonny/video/7646757218007715079?_r=1&_t=ZS-96sF5iS0M78 | G10: 46059 | H10: 50000 | I10: 3000 | J10: 17565 | K10: 1940 | M10: =IFERROR(IF(H10>0,J10/H10,""),"") -> 0.3513 | N10: =IFERROR(IF(I10>0,K10/I10,""),"") -> 0.64666667 | O10: 46148
A11: 6 | B11: Nuchuu nè | C11: 756K | D11: Link | E11: Tiktok | F11: https://vt.tiktok.com/ZSx45rKrU/ | G11: 28/5 | H11: 120000 | I11: 4500 | J11: 81088 | K11: 1195 | M11: =IFERROR(IF(H11>0,J11/H11,""),"") -> 0.67573333 | N11: =IFERROR(IF(I11>0,K11/I11,""),"") -> 0.26555556 | O11: 46148
A12: 7 | B12: Ăn ngon cùng Puu | C12: 345.4K | D12: Link | E12: Tiktok | H12: 100000 | I12: 4000 | M12: =IFERROR(IF(H12>0,J12/H12,""),"") -> 0 | N12: =IFERROR(IF(I12>0,K12/I12,""),"") -> 0
A13: 8 | B13: A dinosaur in the kitchen | C13: 294.8K | D13: Link | E13: Tiktok | H13: 65000 | I13: 3000 | M13: =IFERROR(IF(H13>0,J13/H13,""),"") -> 0 | N13: =IFERROR(IF(I13>0,K13/I13,""),"") -> 0
A14: 9 | B14: Đi Ăn Chưa 🍪 | C14: 289.3K | D14: Link | E14: Tiktok | H14: 65000 | I14: 3000 | M14: =IFERROR(IF(H14>0,J14/H14,""),"") -> 0 | N14: =IFERROR(IF(I14>0,K14/I14,""),"") -> 0
A15: FOODY UGC
A16: TP HCM
A17: 10 | B17: Nhà Mây | C17: 187.9K | D17: Link | E17: Tiktok | H17: 30000 | I17: 2000 | M17: =IFERROR(IF(H17>0,J17/H17,""),"") -> 0 | N17: =IFERROR(IF(I17>0,K17/I17,""),"") -> 0
A18: 11 | B18: Đi chill cùng Phương phiêu | C18: 57.7K | D18: Link | E18: Tiktok | H18: 20000 | I18: 1500 | M18: =IFERROR(IF(H18>0,J18/H18,""),"") -> 0 | N18: =IFERROR(IF(I18>0,K18/I18,""),"") -> 0
A19: 12 | B19: 🍊𝐕 𝐈 𝐓 𝐀 𝐌 𝐈 𝐍 𝐂🍊 | C19: 10.1K | D19: Link | E19: Tiktok | H19: 20000 | I19: 1500 | M19: =IFERROR(IF(H19>0,J19/H19,""),"") -> 0 | N19: =IFERROR(IF(I19>0,K19/I19,""),"") -> 0
A20: 13 | B20: Chu Cao Food | C20: 67.4K | D20: Link | E20: Tiktok | H20: 20000 | I20: 1500 | M20: =IFERROR(IF(H20>0,J20/H20,""),"") -> 0 | N20: =IFERROR(IF(I20>0,K20/I20,""),"") -> 0
A21: 14 | B21: Hi Ân nè | C21: 6489 | D21: Link | E21: Tiktok | F21: https://vt.tiktok.com/ZSQJJgvLk/ | G21: 46118 | H21: 15000 | I21: 1000 | J21: 574 | K21: 12 | M21: =IFERROR(IF(H21>0,J21/H21,""),"") -> 0.038266667 | N21: =IFERROR(IF(I21>0,K21/I21,""),"") -> 0.012 | O21: 46148
A22: 15 | B22: vuvicungyuhi | C22: 82.9K | D22: Link | E22: Tiktok | F22: https://www.tiktok.com/@vuvicungyuhi/video/7645645226396241160?is_from_webapp=1&sender_device=pc&web_id=7637478982196135431 | G22: 46059 | H22: 46000 | I22: 2000 | J22: 32001 | K22: 354 | M22: =IFERROR(IF(H22>0,J22/H22,""),"") -> 0.69567391 | N22: =IFERROR(IF(I22>0,K22/I22,""),"") -> 0.177 | O22: 46148
A23: 16 | B23: Koi Nam Ăng | C23: 70.5K | D23: Link | E23: Tiktok | H23: 40500 | I23: 2000 | M23: =IFERROR(IF(H23>0,J23/H23,""),"") -> 0 | N23: =IFERROR(IF(I23>0,K23/I23,""),"") -> 0
A24: 17 | B24: Vie ở sài gòn | C24: 64.7K | D24: Link | E24: Tiktok | F24: https://www.tiktok.com/@vieinhcm/video/7644541637095443720?_r=1&_t=ZS-96iB9ChjAgv | G24: 27/5 | H24: 60000 | I24: 3000 | J24: 36124 | K24: 1048 | M24: =IFERROR(IF(H24>0,J24/H24,""),"") -> 0.60206667 | N24: =IFERROR(IF(I24>0,K24/I24,""),"") -> 0.34933333 | O24: 46148
A25: Khu Vực miền Bắc
A26: 18 | B26: Dương Bảo Anh | C26: 20.1K | D26: Link | E26: Tiktok | H26: 20000 | I26: 1500 | M26: =IFERROR(IF(H26>0,J26/H26,""),"") -> 0 | N26: =IFERROR(IF(I26>0,K26/I26,""),"") -> 0
A27: 19 | B27: Nguyệt Thư | C27: 45000 | D27: Link | E27: Tiktok | F27: https://www.tiktok.com/@vunguyetthu/video/7647513882709314834 | G27: 46148 | H27: 20000 | I27: 1500 | J27: 38472 | K27: 2311 | M27: =IFERROR(IF(H27>0,J27/H27,""),"") -> 1.9236 | N27: =IFERROR(IF(I27>0,K27/I27,""),"") -> 1.5406667 | O27: 46148
A28: 20 | B28: Nguyen Mai Ha My | C28: 47.9K | D28: Link | E28: Tiktok | H28: 35000 | I28: 1500 | M28: =IFERROR(IF(H28>0,J28/H28,""),"") -> 0 | N28: =IFERROR(IF(I28>0,K28/I28,""),"") -> 0
A29: 21 | B29: Tuấn food không phét | C29: 18.5K | D29: Link | E29: Tiktok | H29: 30000 | I29: 1500 | M29: =IFERROR(IF(H29>0,J29/H29,""),"") -> 0 | N29: =IFERROR(IF(I29>0,K29/I29,""),"") -> 0
A30: 22 | B30: Bánh Ú 🇻🇳 | C30: 22.6K | D30: Link | E30: Tiktok | H30: 30000 | I30: 1500 | M30: =IFERROR(IF(H30>0,J30/H30,""),"") -> 0 | N30: =IFERROR(IF(I30>0,K30/I30,""),"") -> 0
A31: Khu vực miền Nam
A32: 23 | B32: Zăn Zăn Daily ✨ | C32: 60K | D32: Link | E32: Tiktok | H32: 40000 | I32: 2000 | M32: =IFERROR(IF(H32>0,J32/H32,""),"") -> 0 | N32: =IFERROR(IF(I32>0,K32/I32,""),"") -> 0
A33: 24 | B33: Phương Đi Chill 🌈 | C33: 13600 | D33: Link | E33: Tiktok | H33: 25000 | I33: 1500 | M33: =IFERROR(IF(H33>0,J33/H33,""),"") -> 0 | N33: =IFERROR(IF(I33>0,K33/I33,""),"") -> 0
A34: 25 | B34: Đức Tân Bình | C34: 42.4K | D34: Link | E34: Tiktok | H34: 20000 | I34: 1000 | M34: =IFERROR(IF(H34>0,J34/H34,""),"") -> 0 | N34: =IFERROR(IF(I34>0,K34/I34,""),"") -> 0
A35: 26 | B35: Nguyễn Ly | C35: 130K | D35: Link | E35: Tiktok | F35: https://www.tiktok.com/@lysambonreview/video/7647516576224185620 | G35: 46148 | H35: 20000 | I35: 1500 | J35: 1188 | K35: 160 | M35: =IFERROR(IF(H35>0,J35/H35,""),"") -> 0.0594 | N35: =IFERROR(IF(I35>0,K35/I35,""),"") -> 0.10666667
A36: Khu vực miền Tây
A37: 27 | B37: Nhà Bé Sushi | C37: 270000 | D37: Link | E37: Tiktok | H37: 30000 | I37: 2000 | M37: =IFERROR(IF(H37>0,J37/H37,""),"") -> 0 | N37: =IFERROR(IF(I37>0,K37/I37,""),"") -> 0
A38: FOODY COMMUNITY
A39: 28 | B39: Địa điểm ăn uống (Fanpage) | C39: 5.2M | D39: Link | E39: Facebook | F39: https://www.facebook.com/share/p/1BEEgaStVN/?mibextid=wwXIfr | G39: 46087 | H39: 0 | I39: 3000 | J39: 0 | K39: 2858 | M39: =IFERROR(IF(H39>0,J39/H39,""),"") | N39: =IFERROR(IF(I39>0,K39/I39,""),"") -> 0.95266667 | O39: 46148
A40: 29 | B40: Thèm (Fanpage) | C40: 2M | D40: Link | E40: Facebook | F40: https://www.facebook.com/share/p/18h4jLfJWe/?mibextid=wwXIfr | G40: 46087 | H40: 0 | I40: 3000 | J40: 0 | K40: 2854 | M40: =IFERROR(IF(H40>0,J40/H40,""),"") | N40: =IFERROR(IF(I40>0,K40/I40,""),"") -> 0.95133333 | O40: 46148
A41: 30 | B41: Không Sợ Đói (Group) | C41: 1.3M | D41: Link | E41: Facebook | F41: https://www.facebook.com/groups/kosodoi/posts/27023379973991978 | G41: 46148 | H41: 0 | I41: 3000 | M41: =IFERROR(IF(H41>0,J41/H41,""),"") | N41: =IFERROR(IF(I41>0,K41/I41,""),"") -> 0
A42: 31 | B42: Măm Măn Sài gòn (Group) | C42: 780.6K | D42: Link | E42: Facebook | H42: 0 | I42: 3000 | M42: =IFERROR(IF(H42>0,J42/H42,""),"") | N42: =IFERROR(IF(I42>0,K42/I42,""),"") -> 0
A43: 32 | B43: Đảo Đồ Ăn (Group) | C43: 508.4K | D43: Link | E43: Facebook | F43: https://www.facebook.com/share/p/1BHGncNZtK/?mibextid=wwXIfr | G43: 46028 | H43: 0 | I43: 3000 | J43: 0 | K43: 2556 | M43: =IFERROR(IF(H43>0,J43/H43,""),"") | N43: =IFERROR(IF(I43>0,K43/I43,""),"") -> 0.852 | O43: 46148
A44: 33 | B44: Hà Nội Ăn Gì? | C44: 1M | D44: Link | E44: Tiktok | H44: 80000 | I44: 2000 | M44: =IFERROR(IF(H44>0,J44/H44,""),"") -> 0 | N44: =IFERROR(IF(I44>0,K44/I44,""),"") -> 0
A45: 34 | B45: Vi vu Sài Gòn | C45: 292.7K | D45: Link | E45: Tiktok | F45: https://vt.tiktok.com/ZSx4j4dK3/ | G45: 27/5 | H45: 30000 | I45: 1500 | J45: 31774 | K45: 124 | M45: =IFERROR(IF(H45>0,J45/H45,""),"") -> 1.0591333 | N45: =IFERROR(IF(I45>0,K45/I45,""),"") -> 0.082666667 | O45: 46148
A46: 35 | B46: Thong dong đó đây | C46: 100.2K | D46: Link | E46: Tiktok | F46: https://vt.tiktok.com/ZSQYL87Kt/ | G46: 46118 | H46: 80000 | I46: 1500 | M46: =IFERROR(IF(H46>0,J46/H46,""),"") -> 0 | N46: =IFERROR(IF(I46>0,K46/I46,""),"") -> 0
A47: 36 | B47: SÀI GÒN MAP | C47: 154.5K | D47: Link | E47: Tiktok | F47: https://www.tiktok.com/@saigonmap/video/7644787494319312136?_r=1&_t=ZS-96jG8hKdGL9 | G47: 28/5 | H47: 50000 | I47: 1500 | J47: 38132 | K47: 2909 | M47: =IFERROR(IF(H47>0,J47/H47,""),"") -> 0.76264 | N47: =IFERROR(IF(I47>0,K47/I47,""),"") -> 1.9393333 | O47: 46148
A48: 37 | B48: Phê Hà Nội | C48: 141.2K | D48: Link | E48: Tiktok | H48: 80000 | I48: 2000 | M48: =IFERROR(IF(H48>0,J48/H48,""),"") -> 0 | N48: =IFERROR(IF(I48>0,K48/I48,""),"") -> 0

Sheet List địa điểm RCM
A1: HÀ NỘI
A2: 1) shop Five star ngãi cầu: Ngã 3 ngãi cầu - an khánh- Hà Nội https://fivestarnearyou.cp.com.vn/?Longtitude=105.72529189288616&Latitude=20.990128247353965 2) basic shop lê tuyết: Phố xốm- Yên Nghĩa- Hà Nội https://fivestarnearyou.cp.com.vn/?Longtitude=105.7567036&Latitude=20.9464944 3) basic shop Thị Thắm: Viết Xuân - Hà Đông hà nội https://fivestarnearyou.cp.com.vn/?Longtitude=105.7684087&Latitude=20.9698673 4) outlet quốc nguyễn - đô nghĩa - yên nghĩa hà nội https://fivestarnearyou.cp.com.vn/?Longtitude=105.73732741441492&Latitude=20.957116989172075
A3: HỒ CHÍ MINH
A4: 1. PREAMIUM KIOSK 4*3 Hộ Kinh Doanh Đỗ Thị Thu Hồng Số 98, đường Trần Tử Bình, ấp Tân Định 3, Xã Củ Chi, TP. HCM 2. MINI SHOP - Five Star Mega Q12 - Số 2 đường Trương Thị Hoa, KP 4A, Tân Thới Hiệp, TPHCM 3. BASIC SHOP - Nguyễn Thị Thuận - Số 67 Đường 9, phường Trường Thọ, TP. Thủ Đức, TP. HCM 4. OUTLET - HKD FIVE STAR TRUNG HIẾU - B8/28M Đường Hưng Nhơn, xã Tân Nhựt, TP HCM 5. OUTLET - HKD LÝ VĂN PHÁT - D23/39 Ấp 10, Xã Hưng Long, Tp. Hồ Chí Minh 6. PREAMIUM KIOSK 4*3 - HKD PHAN TẤN TÀI - 223 Ấp 2, xã Bình Chánh, TP HCM 7. OUTLET - HKD GÀ RÁN FIVE STAR THU HÀ - 37/3 Huỳnh Tấn Phát, Xã Nhà Bè, TPHCM 8. PREAMIUM KIOSK 3*3 - HKD FIVE STAR ĐINH ĐỨC THIỆN - 1/26 Đinh Đức Thiện, xã Bình Chánh, TP HCM

Sheet INT | Influencer Workplan
A1: PMAX | C.P.GROUP VIETNAM - INFLUENCERS WORKPLAN
A2: OVERVIEW
A3: STT | B3: CHECKLIST | C3: PIC | D3: Quantity of lead time | E3: START DATE | F3: END DATE | G3: STATUS
B4: Influencer Review
B5: KOC List & Brief
B6: Gửi báo giá Influencer Review | C6: PMAX | G6: Done
B7: Chốt Influencer & SOW | C7: PMAX-BRAND | G7: Done
B8: Chuẩn bị Influencer Content Direction | C8: PMAX-BRAND | G8: Done
B9: Soạn Influencer Brief | C9: PMAX | E9: 46147 | F9: 46147 | G9: Done
B10: Chốt Influencer Brief | C10: PMAX-BRAND | E10: 46147 | F10: 46147 | G10: Done
B11: Lead time Influencer | C11: PMAX | E11: 46146 | F11: 46148 | G11: On going
B12: Briefing cho Influencer | C12: PMAX | E12: 46147 | F12: 46148 | G12: On going
B13: Kịch bản & Trang phục
B14: Gửi kịch bản & trang phục | C14: PMAX | E14: 46148 | F14: 46155
B15: Thống nhất kịch bản & trang phục | C15: PMAX-BRAND | E15: 46148 | F15: 46155
B16: Video
B17: Đi quay tại Kiosk | C17: PMAX-BRAND | E17: 46156 | F17: 46158
B18: Thực hiện dựng video + quay các source bổ sung | C18: PMAX | E18: 46158 | F18: 46163
B19: Check demo & chốt video review | C19: PMAX-BRAND | E19: 46163 | F19: 46203
A22: =IFERROR(__xludf.DUMMYFUNCTION("IMPORTRANGE(""https://docs.google.com/spreadsheets/d/1vaepmEWZwQPcFnJybT7zJVCFQxsVk_MSW_pJStnUg6U/edit?gid=401671460#gid=401671460"",""'Overall Workplan'!A1:G534"")"),"EXECUTION") -> EXECUTION
A23: =IFERROR(__xludf.DUMMYFUNCTION("""COMPUTED_VALUE"""),"STT") -> STT | B23: =IFERROR(__xludf.DUMMYFUNCTION("""COMPUTED_VALUE"""),"ITEM") -> ITEM | C23: =IFERROR(__xludf.DUMMYFUNCTION("""COMPUTED_VALUE"""),"NOTE") -> NOTE | D23: =IFERROR(__xludf.DUMMYFUNCTION("""COMPUTED_VALUE"""),"PIC") -> PIC | E23: =IFERROR(__xludf.DUMMYFUNCTION("""COMPUTED_VALUE"""),"STATUS") -> STATUS | F23: =IFERROR(__xludf.DUMMYFUNCTION("""COMPUTED_VALUE"""),"START DATE") -> START DATE | G23: =IFERROR(__xludf.DUMMYFUNCTION("""COMPUTED_VALUE"""),"END DATE") -> END DATE
A24: =IFERROR(__xludf.DUMMYFUNCTION("""COMPUTED_VALUE"""),"9") -> 9 | B24: =IFERROR(__xludf.DUMMYFUNCTION("""COMPUTED_VALUE"""),"FOODY REVIEWER") -> FOODY REVIEWER
A25: =IFERROR(__xludf.DUMMYFUNCTION("""COMPUTED_VALUE"""),1.0) -> 1 | B25: =IFERROR(__xludf.DUMMYFUNCTION("""COMPUTED_VALUE"""),"Thắng Lợi") -> Thắng Lợi | J25: https://docs.google.com/spreadsheets/d/1vaepmEWZwQPcFnJybT7zJVCFQxsVk_MSW_pJStnUg6U/edit?gid=401671460#gid=401671460
B26: =IFERROR(__xludf.DUMMYFUNCTION("""COMPUTED_VALUE"""),"Briefing cho Influencer") -> Briefing cho Influencer | D26: =IFERROR(__xludf.DUMMYFUNCTION("""COMPUTED_VALUE"""),"PMAX") -> PMAX | E26: =IFERROR(__xludf.DUMMYFUNCTION("""COMPUTED_VALUE"""),"Not start yet") -> Not start yet | F26: =IFERROR(__xludf.DUMMYFUNCTION("""COMPUTED_VALUE"""),46147.0) -> 46147 | G26: =IFERROR(__xludf.DUMMYFUNCTION("""COMPUTED_VALUE"""),46148.0) -> 46148 | J26: Timeline est
B27: =IFERROR(__xludf.DUMMYFUNCTION("""COMPUTED_VALUE"""),"Script R1 + Outfits") -> Script R1 + Outfits | D27: =IFERROR(__xludf.DUMMYFUNCTION("""COMPUTED_VALUE"""),"PMAX") -> PMAX | E27: =IFERROR(__xludf.DUMMYFUNCTION("""COMPUTED_VALUE"""),"Not start yet") -> Not start yet | F27: =IFERROR(__xludf.DUMMYFUNCTION("""COMPUTED_VALUE"""),46148.0) -> 46148 | G27: =IFERROR(__xludf.DUMMYFUNCTION("""COMPUTED_VALUE"""),46150.0) -> 46150 | I27: 1 | J27: 2/4 có KOL brief
B28: =IFERROR(__xludf.DUMMYFUNCTION("""COMPUTED_VALUE"""),"Feedback Script R1 + outfits") -> Feedback Script R1 + outfits | D28: =IFERROR(__xludf.DUMMYFUNCTION("""COMPUTED_VALUE"""),"BRAND") -> BRAND | E28: =IFERROR(__xludf.DUMMYFUNCTION("""COMPUTED_VALUE"""),"Not start yet") -> Not start yet | F28: =IFERROR(__xludf.DUMMYFUNCTION("""COMPUTED_VALUE"""),46150.0) -> 46150 | G28: =IFERROR(__xludf.DUMMYFUNCTION("""COMPUTED_VALUE"""),46150.0) -> 46150 | J28: 4/4 Script R1
B29: =IFERROR(__xludf.DUMMYFUNCTION("""COMPUTED_VALUE"""),"Script R2") -> Script R2 | D29: =IFERROR(__xludf.DUMMYFUNCTION("""COMPUTED_VALUE"""),"PMAX") -> PMAX | E29: =IFERROR(__xludf.DUMMYFUNCTION("""COMPUTED_VALUE"""),"Not start yet") -> Not start yet | F29: =IFERROR(__xludf.DUMMYFUNCTION("""COMPUTED_VALUE"""),46151.0) -> 46151 | G29: =IFERROR(__xludf.DUMMYFUNCTION("""COMPUTED_VALUE"""),46152.0) -> 46152
B30: =IFERROR(__xludf.DUMMYFUNCTION("""COMPUTED_VALUE"""),"Feedback Script R2") -> Feedback Script R2 | D30: =IFERROR(__xludf.DUMMYFUNCTION("""COMPUTED_VALUE"""),"BRAND") -> BRAND | E30: =IFERROR(__xludf.DUMMYFUNCTION("""COMPUTED_VALUE"""),"Not start yet") -> Not start yet | F30: =IFERROR(__xludf.DUMMYFUNCTION("""COMPUTED_VALUE"""),46153.0) -> 46153 | G30: =IFERROR(__xludf.DUMMYFUNCTION("""COMPUTED_VALUE"""),46153.0) -> 46153
B31: =IFERROR(__xludf.DUMMYFUNCTION("""COMPUTED_VALUE"""),"Finalize scripts + outfits") -> Finalize scripts + outfits | D31: =IFERROR(__xludf.DUMMYFUNCTION("""COMPUTED_VALUE"""),"PMAX-BRAND") -> PMAX-BRAND | E31: =IFERROR(__xludf.DUMMYFUNCTION("""COMPUTED_VALUE"""),"Not start yet") -> Not start yet | F31: =IFERROR(__xludf.DUMMYFUNCTION("""COMPUTED_VALUE"""),46153.0) -> 46153 | G31: =IFERROR(__xludf.DUMMYFUNCTION("""COMPUTED_VALUE"""),46153.0) -> 46153 | I31: 1 | J31: 6/4 script R2
B32: =IFERROR(__xludf.DUMMYFUNCTION("""COMPUTED_VALUE"""),"Đi quay tại site") -> Đi quay tại site | D32: =IFERROR(__xludf.DUMMYFUNCTION("""COMPUTED_VALUE"""),"PMAX") -> PMAX | E32: =IFERROR(__xludf.DUMMYFUNCTION("""COMPUTED_VALUE"""),"Not start yet") -> Not start yet | F32: =IFERROR(__xludf.DUMMYFUNCTION("""COMPUTED_VALUE"""),46154.0) -> 46154 | G32: =IFERROR(__xludf.DUMMYFUNCTION("""COMPUTED_VALUE"""),46156.0) -> 46156 | I32: 2
B33: =IFERROR(__xludf.DUMMYFUNCTION("""COMPUTED_VALUE"""),"Demo R1") -> Demo R1 | D33: =IFERROR(__xludf.DUMMYFUNCTION("""COMPUTED_VALUE"""),"PMAX") -> PMAX | E33: =IFERROR(__xludf.DUMMYFUNCTION("""COMPUTED_VALUE"""),"Not start yet") -> Not start yet | F33: =IFERROR(__xludf.DUMMYFUNCTION("""COMPUTED_VALUE"""),46156.0) -> 46156 | G33: =IFERROR(__xludf.DUMMYFUNCTION("""COMPUTED_VALUE"""),46159.0) -> 46159 | I33: 4 | J33: 14/4 demo R1
B34: =IFERROR(__xludf.DUMMYFUNCTION("""COMPUTED_VALUE"""),"Feedback demo R1") -> Feedback demo R1 | D34: =IFERROR(__xludf.DUMMYFUNCTION("""COMPUTED_VALUE"""),"BRAND") -> BRAND | E34: =IFERROR(__xludf.DUMMYFUNCTION("""COMPUTED_VALUE"""),"Not start yet") -> Not start yet | F34: =IFERROR(__xludf.DUMMYFUNCTION("""COMPUTED_VALUE"""),46160.0) -> 46160 | G34: =IFERROR(__xludf.DUMMYFUNCTION("""COMPUTED_VALUE"""),46160.0) -> 46160 | J34: 16/4 demo R2
B35: =IFERROR(__xludf.DUMMYFUNCTION("""COMPUTED_VALUE"""),"Demo R2") -> Demo R2 | D35: =IFERROR(__xludf.DUMMYFUNCTION("""COMPUTED_VALUE"""),"PMAX") -> PMAX | E35: =IFERROR(__xludf.DUMMYFUNCTION("""COMPUTED_VALUE"""),"Not start yet") -> Not start yet | F35: =IFERROR(__xludf.DUMMYFUNCTION("""COMPUTED_VALUE"""),46161.0) -> 46161 | G35: =IFERROR(__xludf.DUMMYFUNCTION("""COMPUTED_VALUE"""),46163.0) -> 46163
B36: =IFERROR(__xludf.DUMMYFUNCTION("""COMPUTED_VALUE"""),"Feedback demo R2") -> Feedback demo R2 | D36: =IFERROR(__xludf.DUMMYFUNCTION("""COMPUTED_VALUE"""),"BRAND") -> BRAND | E36: =IFERROR(__xludf.DUMMYFUNCTION("""COMPUTED_VALUE"""),"Not start yet") -> Not start yet | F36: =IFERROR(__xludf.DUMMYFUNCTION("""COMPUTED_VALUE"""),46164.0) -> 46164 | G36: =IFERROR(__xludf.DUMMYFUNCTION("""COMPUTED_VALUE"""),46164.0) -> 46164
B37: =IFERROR(__xludf.DUMMYFUNCTION("""COMPUTED_VALUE"""),"Finalize demo") -> Finalize demo | D37: =IFERROR(__xludf.DUMMYFUNCTION("""COMPUTED_VALUE"""),"PMAX") -> PMAX | E37: =IFERROR(__xludf.DUMMYFUNCTION("""COMPUTED_VALUE"""),"Not start yet") -> Not start yet | F37: =IFERROR(__xludf.DUMMYFUNCTION("""COMPUTED_VALUE"""),46164.0) -> 46164 | G37: =IFERROR(__xludf.DUMMYFUNCTION("""COMPUTED_VALUE"""),46164.0) -> 46164 | I37: 1 | J37: 18/4 finalize demo
B38: =IFERROR(__xludf.DUMMYFUNCTION("""COMPUTED_VALUE"""),"Air") -> Air | D38: =IFERROR(__xludf.DUMMYFUNCTION("""COMPUTED_VALUE"""),"PMAX") -> PMAX | E38: =IFERROR(__xludf.DUMMYFUNCTION("""COMPUTED_VALUE"""),"Not start yet") -> Not start yet | F38: =IFERROR(__xludf.DUMMYFUNCTION("""COMPUTED_VALUE"""),"TBU") -> TBU | G38: =IFERROR(__xludf.DUMMYFUNCTION("""COMPUTED_VALUE"""),"TBU") -> TBU | I38: 1
A39: =IFERROR(__xludf.DUMMYFUNCTION("""COMPUTED_VALUE"""),2.0) -> 2 | B39: =IFERROR(__xludf.DUMMYFUNCTION("""COMPUTED_VALUE"""),"Lulu Review") -> Lulu Review
B40: =IFERROR(__xludf.DUMMYFUNCTION("""COMPUTED_VALUE"""),"Briefing cho Influencer") -> Briefing cho Influencer | D40: =IFERROR(__xludf.DUMMYFUNCTION("""COMPUTED_VALUE"""),"PMAX") -> PMAX | E40: =IFERROR(__xludf.DUMMYFUNCTION("""COMPUTED_VALUE"""),"Done") -> Done | F40: =IFERROR(__xludf.DUMMYFUNCTION("""COMPUTED_VALUE"""),"Thứ 3. 5/ 5") -> Thứ 3. 5/ 5 | G40: =IFERROR(__xludf.DUMMYFUNCTION("""COMPUTED_VALUE"""),"Thứ 4. 6/ 5") -> Thứ 4. 6/ 5 | J40: Timeline est
B41: =IFERROR(__xludf.DUMMYFUNCTION("""COMPUTED_VALUE"""),"Script R1 + Outfits") -> Script R1 + Outfits | D41: =IFERROR(__xludf.DUMMYFUNCTION("""COMPUTED_VALUE"""),"PMAX") -> PMAX | E41: =IFERROR(__xludf.DUMMYFUNCTION("""COMPUTED_VALUE"""),"Done") -> Done | F41: =IFERROR(__xludf.DUMMYFUNCTION("""COMPUTED_VALUE"""),"Thứ 4. 6/ 5") -> Thứ 4. 6/ 5 | G41: =IFERROR(__xludf.DUMMYFUNCTION("""COMPUTED_VALUE"""),"Thứ 6. 8/ 5") -> Thứ 6. 8/ 5 | I41: 1 | J41: 2/4 có KOL brief
B42: =IFERROR(__xludf.DUMMYFUNCTION("""COMPUTED_VALUE"""),"Feedback Script R1 + outfits") -> Feedback Script R1 + outfits | D42: =IFERROR(__xludf.DUMMYFUNCTION("""COMPUTED_VALUE"""),"BRAND") -> BRAND | E42: =IFERROR(__xludf.DUMMYFUNCTION("""COMPUTED_VALUE"""),"On going") -> On going | F42: =IFERROR(__xludf.DUMMYFUNCTION("""COMPUTED_VALUE"""),"Thứ 6. 8/ 5") -> Thứ 6. 8/ 5 | G42: =IFERROR(__xludf.DUMMYFUNCTION("""COMPUTED_VALUE"""),"Thứ 6. 8/ 5") -> Thứ 6. 8/ 5 | J42: 4/4 Script R1
B43: =IFERROR(__xludf.DUMMYFUNCTION("""COMPUTED_VALUE"""),"Script R2") -> Script R2 | D43: =IFERROR(__xludf.DUMMYFUNCTION("""COMPUTED_VALUE"""),"PMAX") -> PMAX | E43: =IFERROR(__xludf.DUMMYFUNCTION("""COMPUTED_VALUE"""),"Not start yet") -> Not start yet | F43: =IFERROR(__xludf.DUMMYFUNCTION("""COMPUTED_VALUE"""),"Thứ 7. 9/ 5") -> Thứ 7. 9/ 5 | G43: =IFERROR(__xludf.DUMMYFUNCTION("""COMPUTED_VALUE"""),"CN. 10/ 5") -> CN. 10/ 5
B44: =IFERROR(__xludf.DUMMYFUNCTION("""COMPUTED_VALUE"""),"Feedback Script R2") -> Feedback Script R2 | D44: =IFERROR(__xludf.DUMMYFUNCTION("""COMPUTED_VALUE"""),"BRAND") -> BRAND | E44: =IFERROR(__xludf.DUMMYFUNCTION("""COMPUTED_VALUE"""),"Not start yet") -> Not start yet | F44: =IFERROR(__xludf.DUMMYFUNCTION("""COMPUTED_VALUE"""),"Thứ 2. 11/ 5") -> Thứ 2. 11/ 5 | G44: =IFERROR(__xludf.DUMMYFUNCTION("""COMPUTED_VALUE"""),"Thứ 2. 11/ 5") -> Thứ 2. 11/ 5
B45: =IFERROR(__xludf.DUMMYFUNCTION("""COMPUTED_VALUE"""),"Finalize scripts + outfits") -> Finalize scripts + outfits | D45: =IFERROR(__xludf.DUMMYFUNCTION("""COMPUTED_VALUE"""),"PMAX-BRAND") -> PMAX-BRAND | E45: =IFERROR(__xludf.DUMMYFUNCTION("""COMPUTED_VALUE"""),"Not start yet") -> Not start yet | F45: =IFERROR(__xludf.DUMMYFUNCTION("""COMPUTED_VALUE"""),"Thứ 2. 11/ 5") -> Thứ 2. 11/ 5 | G45: =IFERROR(__xludf.DUMMYFUNCTION("""COMPUTED_VALUE"""),"Thứ 2. 11/ 5") -> Thứ 2. 11/ 5 | I45: 1 | J45: 6/4 script R2
B46: =IFERROR(__xludf.DUMMYFUNCTION("""COMPUTED_VALUE"""),"Đi quay tại site") -> Đi quay tại site | D46: =IFERROR(__xludf.DUMMYFUNCTION("""COMPUTED_VALUE"""),"PMAX") -> PMAX | E46: =IFERROR(__xludf.DUMMYFUNCTION("""COMPUTED_VALUE"""),"Not start yet") -> Not start yet | F46: =IFERROR(__xludf.DUMMYFUNCTION("""COMPUTED_VALUE"""),"Thứ 3. 12/ 5") -> Thứ 3. 12/ 5 | G46: =IFERROR(__xludf.DUMMYFUNCTION("""COMPUTED_VALUE"""),"Thứ 5. 14/ 5") -> Thứ 5. 14/ 5 | I46: 2
B47: =IFERROR(__xludf.DUMMYFUNCTION("""COMPUTED_VALUE"""),"Demo R1") -> Demo R1 | D47: =IFERROR(__xludf.DUMMYFUNCTION("""COMPUTED_VALUE"""),"PMAX") -> PMAX | E47: =IFERROR(__xludf.DUMMYFUNCTION("""COMPUTED_VALUE"""),"Not start yet") -> Not start yet | F47: =IFERROR(__xludf.DUMMYFUNCTION("""COMPUTED_VALUE"""),"Thứ 6. 15/ 5") -> Thứ 6. 15/ 5 | G47: =IFERROR(__xludf.DUMMYFUNCTION("""COMPUTED_VALUE"""),"CN. 17/ 5") -> CN. 17/ 5 | I47: 4 | J47: 14/4 demo R1
B48: =IFERROR(__xludf.DUMMYFUNCTION("""COMPUTED_VALUE"""),"Feedback demo R1") -> Feedback demo R1 | D48: =IFERROR(__xludf.DUMMYFUNCTION("""COMPUTED_VALUE"""),"BRAND") -> BRAND | E48: =IFERROR(__xludf.DUMMYFUNCTION("""COMPUTED_VALUE"""),"Not start yet") -> Not start yet | F48: =IFERROR(__xludf.DUMMYFUNCTION("""COMPUTED_VALUE"""),"Thứ 2. 18/ 5") -> Thứ 2. 18/ 5 | G48: =IFERROR(__xludf.DUMMYFUNCTION("""COMPUTED_VALUE"""),"Thứ 2. 18/ 5") -> Thứ 2. 18/ 5 | J48: 16/4 demo R2
B49: =IFERROR(__xludf.DUMMYFUNCTION("""COMPUTED_VALUE"""),"Demo R2") -> Demo R2 | D49: =IFERROR(__xludf.DUMMYFUNCTION("""COMPUTED_VALUE"""),"PMAX") -> PMAX | E49: =IFERROR(__xludf.DUMMYFUNCTION("""COMPUTED_VALUE"""),"Not start yet") -> Not start yet | F49: =IFERROR(__xludf.DUMMYFUNCTION("""COMPUTED_VALUE"""),"Thứ 3. 19/ 5") -> Thứ 3. 19/ 5 | G49: =IFERROR(__xludf.DUMMYFUNCTION("""COMPUTED_VALUE"""),"Thứ 5. 21/ 5") -> Thứ 5. 21/ 5
B50: =IFERROR(__xludf.DUMMYFUNCTION("""COMPUTED_VALUE"""),"Feedback demo R2") -> Feedback demo R2 | D50: =IFERROR(__xludf.DUMMYFUNCTION("""COMPUTED_VALUE"""),"BRAND") -> BRAND | E50: =IFERROR(__xludf.DUMMYFUNCTION("""COMPUTED_VALUE"""),"Not start yet") -> Not start yet | F50: =IFERROR(__xludf.DUMMYFUNCTION("""COMPUTED_VALUE"""),"Thứ 6. 22/ 5") -> Thứ 6. 22/ 5 | G50: =IFERROR(__xludf.DUMMYFUNCTION("""COMPUTED_VALUE"""),"Thứ 6. 22/ 5") -> Thứ 6. 22/ 5
B51: =IFERROR(__xludf.DUMMYFUNCTION("""COMPUTED_VALUE"""),"Finalize demo") -> Finalize demo | D51: =IFERROR(__xludf.DUMMYFUNCTION("""COMPUTED_VALUE"""),"PMAX") -> PMAX | E51: =IFERROR(__xludf.DUMMYFUNCTION("""COMPUTED_VALUE"""),"Not start yet") -> Not start yet | F51: =IFERROR(__xludf.DUMMYFUNCTION("""COMPUTED_VALUE"""),"Thứ 6. 22/ 5") -> Thứ 6. 22/ 5 | G51: =IFERROR(__xludf.DUMMYFUNCTION("""COMPUTED_VALUE"""),"Thứ 6. 22/ 5") -> Thứ 6. 22/ 5 | I51: 1 | J51: 18/4 finalize demo
B52: =IFERROR(__xludf.DUMMYFUNCTION("""COMPUTED_VALUE"""),"Air") -> Air | D52: =IFERROR(__xludf.DUMMYFUNCTION("""COMPUTED_VALUE"""),"PMAX") -> PMAX | E52: =IFERROR(__xludf.DUMMYFUNCTION("""COMPUTED_VALUE"""),"Not start yet") -> Not start yet | F52: =IFERROR(__xludf.DUMMYFUNCTION("""COMPUTED_VALUE"""),"TBU") -> TBU | G52: =IFERROR(__xludf.DUMMYFUNCTION("""COMPUTED_VALUE"""),"TBU") -> TBU | I52: 1
A53: =IFERROR(__xludf.DUMMYFUNCTION("""COMPUTED_VALUE"""),3.0) -> 3 | B53: =IFERROR(__xludf.DUMMYFUNCTION("""COMPUTED_VALUE"""),"Hello Lập Đây") -> Hello Lập Đây
B54: =IFERROR(__xludf.DUMMYFUNCTION("""COMPUTED_VALUE"""),"Briefing cho Influencer") -> Briefing cho Influencer | D54: =IFERROR(__xludf.DUMMYFUNCTION("""COMPUTED_VALUE"""),"PMAX") -> PMAX | E54: =IFERROR(__xludf.DUMMYFUNCTION("""COMPUTED_VALUE"""),"Done") -> Done | F54: =IFERROR(__xludf.DUMMYFUNCTION("""COMPUTED_VALUE"""),46147.0) -> 46147 | G54: =IFERROR(__xludf.DUMMYFUNCTION("""COMPUTED_VALUE"""),46148.0) -> 46148 | J54: Timeline est
B55: =IFERROR(__xludf.DUMMYFUNCTION("""COMPUTED_VALUE"""),"Script R1 + Outfits") -> Script R1 + Outfits | D55: =IFERROR(__xludf.DUMMYFUNCTION("""COMPUTED_VALUE"""),"PMAX") -> PMAX | E55: =IFERROR(__xludf.DUMMYFUNCTION("""COMPUTED_VALUE"""),"Done") -> Done | F55: =IFERROR(__xludf.DUMMYFUNCTION("""COMPUTED_VALUE"""),46150.0) -> 46150 | G55: =IFERROR(__xludf.DUMMYFUNCTION("""COMPUTED_VALUE"""),46150.0) -> 46150 | I55: 1 | J55: 2/4 có KOL brief
B56: =IFERROR(__xludf.DUMMYFUNCTION("""COMPUTED_VALUE"""),"Feedback Script R1 + outfits") -> Feedback Script R1 + outfits | D56: =IFERROR(__xludf.DUMMYFUNCTION("""COMPUTED_VALUE"""),"BRAND") -> BRAND | E56: =IFERROR(__xludf.DUMMYFUNCTION("""COMPUTED_VALUE"""),"Not start yet") -> Not start yet | F56: =IFERROR(__xludf.DUMMYFUNCTION("""COMPUTED_VALUE"""),46151.0) -> 46151 | G56: =IFERROR(__xludf.DUMMYFUNCTION("""COMPUTED_VALUE"""),46152.0) -> 46152 | J56: 4/4 Script R1
B57: =IFERROR(__xludf.DUMMYFUNCTION("""COMPUTED_VALUE"""),"Script R2") -> Script R2 | D57: =IFERROR(__xludf.DUMMYFUNCTION("""COMPUTED_VALUE"""),"PMAX") -> PMAX | E57: =IFERROR(__xludf.DUMMYFUNCTION("""COMPUTED_VALUE"""),"Not start yet") -> Not start yet | F57: =IFERROR(__xludf.DUMMYFUNCTION("""COMPUTED_VALUE"""),46153.0) -> 46153 | G57: =IFERROR(__xludf.DUMMYFUNCTION("""COMPUTED_VALUE"""),46153.0) -> 46153
B58: =IFERROR(__xludf.DUMMYFUNCTION("""COMPUTED_VALUE"""),"Feedback Script R2") -> Feedback Script R2 | D58: =IFERROR(__xludf.DUMMYFUNCTION("""COMPUTED_VALUE"""),"BRAND") -> BRAND | E58: =IFERROR(__xludf.DUMMYFUNCTION("""COMPUTED_VALUE"""),"Not start yet") -> Not start yet | F58: =IFERROR(__xludf.DUMMYFUNCTION("""COMPUTED_VALUE"""),46153.0) -> 46153 | G58: =IFERROR(__xludf.DUMMYFUNCTION("""COMPUTED_VALUE"""),46153.0) -> 46153
B59: =IFERROR(__xludf.DUMMYFUNCTION("""COMPUTED_VALUE"""),"Finalize scripts + outfits") -> Finalize scripts + outfits | D59: =IFERROR(__xludf.DUMMYFUNCTION("""COMPUTED_VALUE"""),"PMAX-BRAND") -> PMAX-BRAND | E59: =IFERROR(__xludf.DUMMYFUNCTION("""COMPUTED_VALUE"""),"Not start yet") -> Not start yet | F59: =IFERROR(__xludf.DUMMYFUNCTION("""COMPUTED_VALUE"""),46154.0) -> 46154 | G59: =IFERROR(__xludf.DUMMYFUNCTION("""COMPUTED_VALUE"""),46154.0) -> 46154 | I59: 1 | J59: 6/4 script R2
B60: =IFERROR(__xludf.DUMMYFUNCTION("""COMPUTED_VALUE"""),"Đi quay tại site") -> Đi quay tại site | D60: =IFERROR(__xludf.DUMMYFUNCTION("""COMPUTED_VALUE"""),"PMAX") -> PMAX | E60: =IFERROR(__xludf.DUMMYFUNCTION("""COMPUTED_VALUE"""),"Not start yet") -> Not start yet | F60: =IFERROR(__xludf.DUMMYFUNCTION("""COMPUTED_VALUE"""),46154.0) -> 46154 | G60: =IFERROR(__xludf.DUMMYFUNCTION("""COMPUTED_VALUE"""),46154.0) -> 46154 | I60: 2
B61: =IFERROR(__xludf.DUMMYFUNCTION("""COMPUTED_VALUE"""),"Demo R1") -> Demo R1 | D61: =IFERROR(__xludf.DUMMYFUNCTION("""COMPUTED_VALUE"""),"PMAX") -> PMAX | E61: =IFERROR(__xludf.DUMMYFUNCTION("""COMPUTED_VALUE"""),"Not start yet") -> Not start yet | F61: =IFERROR(__xludf.DUMMYFUNCTION("""COMPUTED_VALUE"""),46159.0) -> 46159 | G61: =IFERROR(__xludf.DUMMYFUNCTION("""COMPUTED_VALUE"""),46159.0) -> 46159 | I61: 4 | J61: 14/4 demo R1
B62: =IFERROR(__xludf.DUMMYFUNCTION("""COMPUTED_VALUE"""),"Feedback demo R1") -> Feedback demo R1 | D62: =IFERROR(__xludf.DUMMYFUNCTION("""COMPUTED_VALUE"""),"BRAND") -> BRAND | E62: =IFERROR(__xludf.DUMMYFUNCTION("""COMPUTED_VALUE"""),"Not start yet") -> Not start yet | F62: =IFERROR(__xludf.DUMMYFUNCTION("""COMPUTED_VALUE"""),46160.0) -> 46160 | G62: =IFERROR(__xludf.DUMMYFUNCTION("""COMPUTED_VALUE"""),46160.0) -> 46160 | J62: 16/4 demo R2
B63: =IFERROR(__xludf.DUMMYFUNCTION("""COMPUTED_VALUE"""),"Demo R2") -> Demo R2 | D63: =IFERROR(__xludf.DUMMYFUNCTION("""COMPUTED_VALUE"""),"PMAX") -> PMAX | E63: =IFERROR(__xludf.DUMMYFUNCTION("""COMPUTED_VALUE"""),"Not start yet") -> Not start yet | F63: =IFERROR(__xludf.DUMMYFUNCTION("""COMPUTED_VALUE"""),46162.0) -> 46162 | G63: =IFERROR(__xludf.DUMMYFUNCTION("""COMPUTED_VALUE"""),46162.0) -> 46162
B64: =IFERROR(__xludf.DUMMYFUNCTION("""COMPUTED_VALUE"""),"Feedback demo R2") -> Feedback demo R2 | D64: =IFERROR(__xludf.DUMMYFUNCTION("""COMPUTED_VALUE"""),"BRAND") -> BRAND | E64: =IFERROR(__xludf.DUMMYFUNCTION("""COMPUTED_VALUE"""),"Not start yet") -> Not start yet | F64: =IFERROR(__xludf.DUMMYFUNCTION("""COMPUTED_VALUE"""),46163.0) -> 46163 | G64: =IFERROR(__xludf.DUMMYFUNCTION("""COMPUTED_VALUE"""),46163.0) -> 46163
B65: =IFERROR(__xludf.DUMMYFUNCTION("""COMPUTED_VALUE"""),"Finalize demo") -> Finalize demo | D65: =IFERROR(__xludf.DUMMYFUNCTION("""COMPUTED_VALUE"""),"PMAX") -> PMAX | E65: =IFERROR(__xludf.DUMMYFUNCTION("""COMPUTED_VALUE"""),"Not start yet") -> Not start yet | F65: =IFERROR(__xludf.DUMMYFUNCTION("""COMPUTED_VALUE"""),46164.0) -> 46164 | G65: =IFERROR(__xludf.DUMMYFUNCTION("""COMPUTED_VALUE"""),46165.0) -> 46165 | I65: 1 | J65: 18/4 finalize demo
B66: =IFERROR(__xludf.DUMMYFUNCTION("""COMPUTED_VALUE"""),"Air") -> Air | D66: =IFERROR(__xludf.DUMMYFUNCTION("""COMPUTED_VALUE"""),"PMAX") -> PMAX | E66: =IFERROR(__xludf.DUMMYFUNCTION("""COMPUTED_VALUE"""),"Not start yet") -> Not start yet | F66: =IFERROR(__xludf.DUMMYFUNCTION("""COMPUTED_VALUE"""),"TBU") -> TBU | G66: =IFERROR(__xludf.DUMMYFUNCTION("""COMPUTED_VALUE"""),"TBU") -> TBU | I66: 1
A67: =IFERROR(__xludf.DUMMYFUNCTION("""COMPUTED_VALUE"""),4.0) -> 4 | B67: =IFERROR(__xludf.DUMMYFUNCTION("""COMPUTED_VALUE"""),"Huyền Nhi") -> Huyền Nhi
B68: =IFERROR(__xludf.DUMMYFUNCTION("""COMPUTED_VALUE"""),"Briefing cho Influencer") -> Briefing cho Influencer | D68: =IFERROR(__xludf.DUMMYFUNCTION("""COMPUTED_VALUE"""),"PMAX") -> PMAX | E68: =IFERROR(__xludf.DUMMYFUNCTION("""COMPUTED_VALUE"""),"Done") -> Done | F68: =IFERROR(__xludf.DUMMYFUNCTION("""COMPUTED_VALUE"""),"Thứ 3. 5/ 5") -> Thứ 3. 5/ 5 | G68: =IFERROR(__xludf.DUMMYFUNCTION("""COMPUTED_VALUE"""),"Thứ 4. 6/ 5") -> Thứ 4. 6/ 5 | J68: Timeline est
B69: =IFERROR(__xludf.DUMMYFUNCTION("""COMPUTED_VALUE"""),"Script R1 + Outfits") -> Script R1 + Outfits | D69: =IFERROR(__xludf.DUMMYFUNCTION("""COMPUTED_VALUE"""),"PMAX") -> PMAX | E69: =IFERROR(__xludf.DUMMYFUNCTION("""COMPUTED_VALUE"""),"Done") -> Done | F69: =IFERROR(__xludf.DUMMYFUNCTION("""COMPUTED_VALUE"""),"Thứ 6. 8/ 5") -> Thứ 6. 8/ 5 | G69: =IFERROR(__xludf.DUMMYFUNCTION("""COMPUTED_VALUE"""),"Thứ 6. 8/ 5") -> Thứ 6. 8/ 5 | I69: 1 | J69: 2/4 có KOL brief
B70: =IFERROR(__xludf.DUMMYFUNCTION("""COMPUTED_VALUE"""),"Feedback Script R1 + outfits") -> Feedback Script R1 + outfits | D70: =IFERROR(__xludf.DUMMYFUNCTION("""COMPUTED_VALUE"""),"BRAND") -> BRAND | E70: =IFERROR(__xludf.DUMMYFUNCTION("""COMPUTED_VALUE"""),"Not start yet") -> Not start yet | F70: =IFERROR(__xludf.DUMMYFUNCTION("""COMPUTED_VALUE"""),"Thứ 6. 8/ 5") -> Thứ 6. 8/ 5 | G70: =IFERROR(__xludf.DUMMYFUNCTION("""COMPUTED_VALUE"""),"Thứ 6. 8/ 5") -> Thứ 6. 8/ 5 | J70: 4/4 Script R1
B71: =IFERROR(__xludf.DUMMYFUNCTION("""COMPUTED_VALUE"""),"Script R2") -> Script R2 | D71: =IFERROR(__xludf.DUMMYFUNCTION("""COMPUTED_VALUE"""),"PMAX") -> PMAX | E71: =IFERROR(__xludf.DUMMYFUNCTION("""COMPUTED_VALUE"""),"Not start yet") -> Not start yet | F71: =IFERROR(__xludf.DUMMYFUNCTION("""COMPUTED_VALUE"""),"Thứ 7. 9/ 5") -> Thứ 7. 9/ 5 | G71: =IFERROR(__xludf.DUMMYFUNCTION("""COMPUTED_VALUE"""),"CN. 10/ 5") -> CN. 10/ 5
B72: =IFERROR(__xludf.DUMMYFUNCTION("""COMPUTED_VALUE"""),"Feedback Script R2") -> Feedback Script R2 | D72: =IFERROR(__xludf.DUMMYFUNCTION("""COMPUTED_VALUE"""),"BRAND") -> BRAND | E72: =IFERROR(__xludf.DUMMYFUNCTION("""COMPUTED_VALUE"""),"Not start yet") -> Not start yet | F72: =IFERROR(__xludf.DUMMYFUNCTION("""COMPUTED_VALUE"""),"Thứ 2. 11/ 5") -> Thứ 2. 11/ 5 | G72: =IFERROR(__xludf.DUMMYFUNCTION("""COMPUTED_VALUE"""),"Thứ 2. 11/ 5") -> Thứ 2. 11/ 5
B73: =IFERROR(__xludf.DUMMYFUNCTION("""COMPUTED_VALUE"""),"Finalize scripts + outfits") -> Finalize scripts + outfits | D73: =IFERROR(__xludf.DUMMYFUNCTION("""COMPUTED_VALUE"""),"PMAX-BRAND") -> PMAX-BRAND | E73: =IFERROR(__xludf.DUMMYFUNCTION("""COMPUTED_VALUE"""),"Not start yet") -> Not start yet | F73: =IFERROR(__xludf.DUMMYFUNCTION("""COMPUTED_VALUE"""),"Thứ 2. 11/ 5") -> Thứ 2. 11/ 5 | G73: =IFERROR(__xludf.DUMMYFUNCTION("""COMPUTED_VALUE"""),"Thứ 2. 11/ 5") -> Thứ 2. 11/ 5 | I73: 1 | J73: 6/4 script R2
B74: =IFERROR(__xludf.DUMMYFUNCTION("""COMPUTED_VALUE"""),"Đi quay tại site") -> Đi quay tại site | D74: =IFERROR(__xludf.DUMMYFUNCTION("""COMPUTED_VALUE"""),"PMAX") -> PMAX | E74: =IFERROR(__xludf.DUMMYFUNCTION("""COMPUTED_VALUE"""),"Not start yet") -> Not start yet | F74: =IFERROR(__xludf.DUMMYFUNCTION("""COMPUTED_VALUE"""),"Thứ 5. 14/ 5") -> Thứ 5. 14/ 5 | G74: =IFERROR(__xludf.DUMMYFUNCTION("""COMPUTED_VALUE"""),"Thứ 5. 14/ 5") -> Thứ 5. 14/ 5 | I74: 2
B75: =IFERROR(__xludf.DUMMYFUNCTION("""COMPUTED_VALUE"""),"Demo R1") -> Demo R1 | D75: =IFERROR(__xludf.DUMMYFUNCTION("""COMPUTED_VALUE"""),"PMAX") -> PMAX | E75: =IFERROR(__xludf.DUMMYFUNCTION("""COMPUTED_VALUE"""),"Not start yet") -> Not start yet | F75: =IFERROR(__xludf.DUMMYFUNCTION("""COMPUTED_VALUE"""),"Thứ 7. 16/ 5") -> Thứ 7. 16/ 5 | G75: =IFERROR(__xludf.DUMMYFUNCTION("""COMPUTED_VALUE"""),"CN. 17/ 5") -> CN. 17/ 5 | I75: 4 | J75: 14/4 demo R1
B76: =IFERROR(__xludf.DUMMYFUNCTION("""COMPUTED_VALUE"""),"Feedback demo R1") -> Feedback demo R1 | D76: =IFERROR(__xludf.DUMMYFUNCTION("""COMPUTED_VALUE"""),"BRAND") -> BRAND | E76: =IFERROR(__xludf.DUMMYFUNCTION("""COMPUTED_VALUE"""),"Not start yet") -> Not start yet | F76: =IFERROR(__xludf.DUMMYFUNCTION("""COMPUTED_VALUE"""),"Thứ 2. 18/ 5") -> Thứ 2. 18/ 5 | G76: =IFERROR(__xludf.DUMMYFUNCTION("""COMPUTED_VALUE"""),"Thứ 2. 18/ 5") -> Thứ 2. 18/ 5 | J76: 16/4 demo R2
B77: =IFERROR(__xludf.DUMMYFUNCTION("""COMPUTED_VALUE"""),"Demo R2") -> Demo R2 | D77: =IFERROR(__xludf.DUMMYFUNCTION("""COMPUTED_VALUE"""),"PMAX") -> PMAX | E77: =IFERROR(__xludf.DUMMYFUNCTION("""COMPUTED_VALUE"""),"Not start yet") -> Not start yet | F77: =IFERROR(__xludf.DUMMYFUNCTION("""COMPUTED_VALUE"""),"Thứ 3. 19/ 5") -> Thứ 3. 19/ 5 | G77: =IFERROR(__xludf.DUMMYFUNCTION("""COMPUTED_VALUE"""),"Thứ 5. 21/ 5") -> Thứ 5. 21/ 5
B78: =IFERROR(__xludf.DUMMYFUNCTION("""COMPUTED_VALUE"""),"Feedback demo R2") -> Feedback demo R2 | D78: =IFERROR(__xludf.DUMMYFUNCTION("""COMPUTED_VALUE"""),"BRAND") -> BRAND | E78: =IFERROR(__xludf.DUMMYFUNCTION("""COMPUTED_VALUE"""),"Not start yet") -> Not start yet | F78: =IFERROR(__xludf.DUMMYFUNCTION("""COMPUTED_VALUE"""),"Thứ 6. 22/ 5") -> Thứ 6. 22/ 5 | G78: =IFERROR(__xludf.DUMMYFUNCTION("""COMPUTED_VALUE"""),"Thứ 6. 22/ 5") -> Thứ 6. 22/ 5
B79: =IFERROR(__xludf.DUMMYFUNCTION("""COMPUTED_VALUE"""),"Finalize demo") -> Finalize demo | D79: =IFERROR(__xludf.DUMMYFUNCTION("""COMPUTED_VALUE"""),"PMAX") -> PMAX | E79: =IFERROR(__xludf.DUMMYFUNCTION("""COMPUTED_VALUE"""),"Not start yet") -> Not start yet | F79: =IFERROR(__xludf.DUMMYFUNCTION("""COMPUTED_VALUE"""),"Thứ 6. 22/ 5") -> Thứ 6. 22/ 5 | G79: =IFERROR(__xludf.DUMMYFUNCTION("""COMPUTED_VALUE"""),"Thứ 6. 22/ 5") -> Thứ 6. 22/ 5 | I79: 1 | J79: 18/4 finalize demo
B80: =IFERROR(__xludf.DUMMYFUNCTION("""COMPUTED_VALUE"""),"Air") -> Air | D80: =IFERROR(__xludf.DUMMYFUNCTION("""COMPUTED_VALUE"""),"PMAX") -> PMAX | E80: =IFERROR(__xludf.DUMMYFUNCTION("""COMPUTED_VALUE"""),"Not start yet") -> Not start yet | F80: =IFERROR(__xludf.DUMMYFUNCTION("""COMPUTED_VALUE"""),"TBU") -> TBU | G80: =IFERROR(__xludf.DUMMYFUNCTION("""COMPUTED_VALUE"""),"TBU") -> TBU | I80: 1
A81: =IFERROR(__xludf.DUMMYFUNCTION("""COMPUTED_VALUE"""),5.0) -> 5 | B81: =IFERROR(__xludf.DUMMYFUNCTION("""COMPUTED_VALUE"""),"Thư Bonny") -> Thư Bonny
B82: =IFERROR(__xludf.DUMMYFUNCTION("""COMPUTED_VALUE"""),"Briefing cho Influencer") -> Briefing cho Influencer | D82: =IFERROR(__xludf.DUMMYFUNCTION("""COMPUTED_VALUE"""),"PMAX") -> PMAX | E82: =IFERROR(__xludf.DUMMYFUNCTION("""COMPUTED_VALUE"""),"Done") -> Done | F82: =IFERROR(__xludf.DUMMYFUNCTION("""COMPUTED_VALUE"""),"Thứ 3. 5/ 5") -> Thứ 3. 5/ 5 | G82: =IFERROR(__xludf.DUMMYFUNCTION("""COMPUTED_VALUE"""),"Thứ 4. 6/ 5") -> Thứ 4. 6/ 5 | J82: Timeline est
B83: =IFERROR(__xludf.DUMMYFUNCTION("""COMPUTED_VALUE"""),"Script R1 + Outfits") -> Script R1 + Outfits | D83: =IFERROR(__xludf.DUMMYFUNCTION("""COMPUTED_VALUE"""),"PMAX") -> PMAX | E83: =IFERROR(__xludf.DUMMYFUNCTION("""COMPUTED_VALUE"""),"Done") -> Done | F83: =IFERROR(__xludf.DUMMYFUNCTION("""COMPUTED_VALUE"""),"Thứ 4. 6/ 5") -> Thứ 4. 6/ 5 | G83: =IFERROR(__xludf.DUMMYFUNCTION("""COMPUTED_VALUE"""),"Thứ 6. 8/ 5") -> Thứ 6. 8/ 5 | I83: 1 | J83: 2/4 có KOL brief
B84: =IFERROR(__xludf.DUMMYFUNCTION("""COMPUTED_VALUE"""),"Feedback Script R1 + outfits") -> Feedback Script R1 + outfits | D84: =IFERROR(__xludf.DUMMYFUNCTION("""COMPUTED_VALUE"""),"BRAND") -> BRAND | E84: =IFERROR(__xludf.DUMMYFUNCTION("""COMPUTED_VALUE"""),"Not start yet") -> Not start yet | F84: =IFERROR(__xludf.DUMMYFUNCTION("""COMPUTED_VALUE"""),"Thứ 6. 8/ 5") -> Thứ 6. 8/ 5 | G84: =IFERROR(__xludf.DUMMYFUNCTION("""COMPUTED_VALUE"""),"Thứ 6. 8/ 5") -> Thứ 6. 8/ 5 | J84: 4/4 Script R1
B85: =IFERROR(__xludf.DUMMYFUNCTION("""COMPUTED_VALUE"""),"Script R2") -> Script R2 | D85: =IFERROR(__xludf.DUMMYFUNCTION("""COMPUTED_VALUE"""),"PMAX") -> PMAX | E85: =IFERROR(__xludf.DUMMYFUNCTION("""COMPUTED_VALUE"""),"Not start yet") -> Not start yet | F85: =IFERROR(__xludf.DUMMYFUNCTION("""COMPUTED_VALUE"""),"Thứ 7. 9/ 5") -> Thứ 7. 9/ 5 | G85: =IFERROR(__xludf.DUMMYFUNCTION("""COMPUTED_VALUE"""),"CN. 10/ 5") -> CN. 10/ 5
B86: =IFERROR(__xludf.DUMMYFUNCTION("""COMPUTED_VALUE"""),"Feedback Script R2") -> Feedback Script R2 | D86: =IFERROR(__xludf.DUMMYFUNCTION("""COMPUTED_VALUE"""),"BRAND") -> BRAND | E86: =IFERROR(__xludf.DUMMYFUNCTION("""COMPUTED_VALUE"""),"Not start yet") -> Not start yet | F86: =IFERROR(__xludf.DUMMYFUNCTION("""COMPUTED_VALUE"""),"Thứ 2. 11/ 5") -> Thứ 2. 11/ 5 | G86: =IFERROR(__xludf.DUMMYFUNCTION("""COMPUTED_VALUE"""),"Thứ 2. 11/ 5") -> Thứ 2. 11/ 5
B87: =IFERROR(__xludf.DUMMYFUNCTION("""COMPUTED_VALUE"""),"Finalize scripts + outfits") -> Finalize scripts + outfits | D87: =IFERROR(__xludf.DUMMYFUNCTION("""COMPUTED_VALUE"""),"PMAX-BRAND") -> PMAX-BRAND | E87: =IFERROR(__xludf.DUMMYFUNCTION("""COMPUTED_VALUE"""),"Not start yet") -> Not start yet | F87: =IFERROR(__xludf.DUMMYFUNCTION("""COMPUTED_VALUE"""),"Thứ 2. 11/ 5") -> Thứ 2. 11/ 5 | G87: =IFERROR(__xludf.DUMMYFUNCTION("""COMPUTED_VALUE"""),"Thứ 2. 11/ 5") -> Thứ 2. 11/ 5 | I87: 1 | J87: 6/4 script R2
B88: =IFERROR(__xludf.DUMMYFUNCTION("""COMPUTED_VALUE"""),"Đi quay tại site") -> Đi quay tại site | D88: =IFERROR(__xludf.DUMMYFUNCTION("""COMPUTED_VALUE"""),"PMAX") -> PMAX | E88: =IFERROR(__xludf.DUMMYFUNCTION("""COMPUTED_VALUE"""),"Not start yet") -> Not start yet | F88: =IFERROR(__xludf.DUMMYFUNCTION("""COMPUTED_VALUE"""),"Thứ 2. 11/ 5") -> Thứ 2. 11/ 5 | G88: =IFERROR(__xludf.DUMMYFUNCTION("""COMPUTED_VALUE"""),"Thứ 5. 14/ 5") -> Thứ 5. 14/ 5 | I88: 2
B89: =IFERROR(__xludf.DUMMYFUNCTION("""COMPUTED_VALUE"""),"Demo R1") -> Demo R1 | D89: =IFERROR(__xludf.DUMMYFUNCTION("""COMPUTED_VALUE"""),"PMAX") -> PMAX | E89: =IFERROR(__xludf.DUMMYFUNCTION("""COMPUTED_VALUE"""),"Not start yet") -> Not start yet | F89: =IFERROR(__xludf.DUMMYFUNCTION("""COMPUTED_VALUE"""),"Thứ 5. 14/ 5") -> Thứ 5. 14/ 5 | G89: =IFERROR(__xludf.DUMMYFUNCTION("""COMPUTED_VALUE"""),"CN. 17/ 5") -> CN. 17/ 5 | I89: 4 | J89: 14/4 demo R1
B90: =IFERROR(__xludf.DUMMYFUNCTION("""COMPUTED_VALUE"""),"Feedback demo R1") -> Feedback demo R1 | D90: =IFERROR(__xludf.DUMMYFUNCTION("""COMPUTED_VALUE"""),"BRAND") -> BRAND | E90: =IFERROR(__xludf.DUMMYFUNCTION("""COMPUTED_VALUE"""),"Not start yet") -> Not start yet | F90: =IFERROR(__xludf.DUMMYFUNCTION("""COMPUTED_VALUE"""),"Thứ 2. 18/ 5") -> Thứ 2. 18/ 5 | G90: =IFERROR(__xludf.DUMMYFUNCTION("""COMPUTED_VALUE"""),"Thứ 2. 18/ 5") -> Thứ 2. 18/ 5 | J90: 16/4 demo R2
B91: =IFERROR(__xludf.DUMMYFUNCTION("""COMPUTED_VALUE"""),"Demo R2") -> Demo R2 | D91: =IFERROR(__xludf.DUMMYFUNCTION("""COMPUTED_VALUE"""),"PMAX") -> PMAX | E91: =IFERROR(__xludf.DUMMYFUNCTION("""COMPUTED_VALUE"""),"Not start yet") -> Not start yet | F91: =IFERROR(__xludf.DUMMYFUNCTION("""COMPUTED_VALUE"""),"Thứ 3. 19/ 5") -> Thứ 3. 19/ 5 | G91: =IFERROR(__xludf.DUMMYFUNCTION("""COMPUTED_VALUE"""),"Thứ 5. 21/ 5") -> Thứ 5. 21/ 5
B92: =IFERROR(__xludf.DUMMYFUNCTION("""COMPUTED_VALUE"""),"Feedback demo R2") -> Feedback demo R2 | D92: =IFERROR(__xludf.DUMMYFUNCTION("""COMPUTED_VALUE"""),"BRAND") -> BRAND | E92: =IFERROR(__xludf.DUMMYFUNCTION("""COMPUTED_VALUE"""),"Not start yet") -> Not start yet | F92: =IFERROR(__xludf.DUMMYFUNCTION("""COMPUTED_VALUE"""),"Thứ 6. 22/ 5") -> Thứ 6. 22/ 5 | G92: =IFERROR(__xludf.DUMMYFUNCTION("""COMPUTED_VALUE"""),"Thứ 6. 22/ 5") -> Thứ 6. 22/ 5
B93: =IFERROR(__xludf.DUMMYFUNCTION("""COMPUTED_VALUE"""),"Finalize demo") -> Finalize demo | D93: =IFERROR(__xludf.DUMMYFUNCTION("""COMPUTED_VALUE"""),"PMAX") -> PMAX | E93: =IFERROR(__xludf.DUMMYFUNCTION("""COMPUTED_VALUE"""),"Not start yet") -> Not start yet | F93: =IFERROR(__xludf.DUMMYFUNCTION("""COMPUTED_VALUE"""),"Thứ 6. 22/ 5") -> Thứ 6. 22/ 5 | G93: =IFERROR(__xludf.DUMMYFUNCTION("""COMPUTED_VALUE"""),"Thứ 6. 22/ 5") -> Thứ 6. 22/ 5 | I93: 1 | J93: 18/4 finalize demo
B94: =IFERROR(__xludf.DUMMYFUNCTION("""COMPUTED_VALUE"""),"Air") -> Air | D94: =IFERROR(__xludf.DUMMYFUNCTION("""COMPUTED_VALUE"""),"PMAX") -> PMAX | E94: =IFERROR(__xludf.DUMMYFUNCTION("""COMPUTED_VALUE"""),"Not start yet") -> Not start yet | F94: =IFERROR(__xludf.DUMMYFUNCTION("""COMPUTED_VALUE"""),"TBU") -> TBU | G94: =IFERROR(__xludf.DUMMYFUNCTION("""COMPUTED_VALUE"""),"TBU") -> TBU | I94: 1
A95: =IFERROR(__xludf.DUMMYFUNCTION("""COMPUTED_VALUE"""),6.0) -> 6 | B95: =IFERROR(__xludf.DUMMYFUNCTION("""COMPUTED_VALUE"""),"Nuchuu nè") -> Nuchuu nè
B96: =IFERROR(__xludf.DUMMYFUNCTION("""COMPUTED_VALUE"""),"Briefing cho Influencer") -> Briefing cho Influencer | D96: =IFERROR(__xludf.DUMMYFUNCTION("""COMPUTED_VALUE"""),"PMAX") -> PMAX | E96: =IFERROR(__xludf.DUMMYFUNCTION("""COMPUTED_VALUE"""),"Done") -> Done | F96: =IFERROR(__xludf.DUMMYFUNCTION("""COMPUTED_VALUE"""),46147.0) -> 46147 | G96: =IFERROR(__xludf.DUMMYFUNCTION("""COMPUTED_VALUE"""),46148.0) -> 46148 | J96: Timeline est
B97: =IFERROR(__xludf.DUMMYFUNCTION("""COMPUTED_VALUE"""),"Script R1 + Outfits") -> Script R1 + Outfits | D97: =IFERROR(__xludf.DUMMYFUNCTION("""COMPUTED_VALUE"""),"PMAX") -> PMAX | E97: =IFERROR(__xludf.DUMMYFUNCTION("""COMPUTED_VALUE"""),"Done") -> Done | F97: =IFERROR(__xludf.DUMMYFUNCTION("""COMPUTED_VALUE"""),46150.0) -> 46150 | G97: =IFERROR(__xludf.DUMMYFUNCTION("""COMPUTED_VALUE"""),46150.0) -> 46150 | I97: 1 | J97: 2/4 có KOL brief
B98: =IFERROR(__xludf.DUMMYFUNCTION("""COMPUTED_VALUE"""),"Feedback Script R1 + outfits") -> Feedback Script R1 + outfits | D98: =IFERROR(__xludf.DUMMYFUNCTION("""COMPUTED_VALUE"""),"BRAND") -> BRAND | E98: =IFERROR(__xludf.DUMMYFUNCTION("""COMPUTED_VALUE"""),"Not start yet") -> Not start yet | F98: =IFERROR(__xludf.DUMMYFUNCTION("""COMPUTED_VALUE"""),46151.0) -> 46151 | G98: =IFERROR(__xludf.DUMMYFUNCTION("""COMPUTED_VALUE"""),46152.0) -> 46152 | J98: 4/4 Script R1
B99: =IFERROR(__xludf.DUMMYFUNCTION("""COMPUTED_VALUE"""),"Script R2") -> Script R2 | D99: =IFERROR(__xludf.DUMMYFUNCTION("""COMPUTED_VALUE"""),"PMAX") -> PMAX | E99: =IFERROR(__xludf.DUMMYFUNCTION("""COMPUTED_VALUE"""),"Not start yet") -> Not start yet | F99: =IFERROR(__xludf.DUMMYFUNCTION("""COMPUTED_VALUE"""),46153.0) -> 46153 | G99: =IFERROR(__xludf.DUMMYFUNCTION("""COMPUTED_VALUE"""),46153.0) -> 46153
